Workbook
Name Beta: #REF!
Name CostofDebt: #REF!
Name DebtValue: #REF!
Name EquityValue: #REF!
Name MarketReturns: #REF!
Name RiskFreeRate: #REF!
Name TaxRate: #REF!

Sheet One Page Profile
B2: Apple Inc. - One Page Profile
B10: Key Financial Metrics | F10: =F20 -> 2020 | G10: =G20 -> 2021 | H10: =H20 -> 2022 | I10: =I20 -> 2023 | K10: Share Price - 5Y
B11: ='Ratio Analysis'!B9 -> Sales Growth | F11: ='Ratio Analysis'!I9 -> 0.055120804 | G11: ='Ratio Analysis'!J9 -> 0.33259385 | H11: ='Ratio Analysis'!K9 -> 0.077937876 | I11: ='Ratio Analysis'!L9 -> -0.028004605
B12: ='Ratio Analysis'!B16 -> EBITDA Margin | F12: ='Ratio Analysis'!I16 -> 0.28174781 | G12: ='Ratio Analysis'!J16 -> 0.3286698 | H12: ='Ratio Analysis'!K16 -> 0.33104674 | I12: ='Ratio Analysis'!L16 -> 0.32826748
B13: ='Ratio Analysis'!B17 -> EBIT Margin | F13: ='Ratio Analysis'!I17 -> 0.24147314 | G13: ='Ratio Analysis'!J17 -> 0.29782378 | H13: ='Ratio Analysis'!K17 -> 0.30288744 | I13: ='Ratio Analysis'!L17 -> 0.29821412
B14: Gross Profit Margin | F14: ='Historical & Forecasted FS'!I15 -> 0.38233248 | G14: ='Historical & Forecasted FS'!J15 -> 0.4177936 | H14: ='Historical & Forecasted FS'!K15 -> 0.43309631 | I14: ='Historical & Forecasted FS'!L15 -> 0.4413113
B15: ='Ratio Analysis'!B19 -> Net Profit Margin | F15: ='Ratio Analysis'!I19 -> 0.20913611 | G15: ='Ratio Analysis'!J19 -> 0.25881793 | H15: ='Ratio Analysis'!K19 -> 0.25309641 | I15: ='Ratio Analysis'!L19 -> 0.25306234
B16: Earnings per share ($) | F16: ='Historical & Forecasted FS'!I52 -> 3.3817401 | G16: ='Historical & Forecasted FS'!J52 -> 5.7637568 | H16: ='Historical & Forecasted FS'!K52 -> 6.2598218 | I16: ='Historical & Forecasted FS'!L52 -> 6.2375961
B17: Dividends per share ($) | F17: ='Historical & Forecasted FS'!I55 -> 0.8 | G17: ='Historical & Forecasted FS'!J55 -> 0.85 | H17: ='Historical & Forecasted FS'!K55 -> 0.9 | I17: ='Historical & Forecasted FS'!L55 -> 0.94
B18: ='Ratio Analysis'!B28 -> Self Sustained Growth Rate | F18: ='Ratio Analysis'!I28 -> 0.56254166 | G18: ='Ratio Analysis'!J28 -> 1.2569939 | H18: ='Ratio Analysis'!K28 -> 1.502328 | I18: ='Ratio Analysis'!L28 -> 1.4603688
B20: Key Financial Ratios and Multiples | F20: ='Ratio Analysis'!I7 -> 2020 | G20: ='Ratio Analysis'!J7 -> 2021 | H20: ='Ratio Analysis'!K7 -> 2022 | I20: ='Ratio Analysis'!L7 -> 2023 | K20: Valuation
B21: ='Ratio Analysis'!B27 -> Return on Equity% | F21: ='Ratio Analysis'!I27 -> 0.73685562 | G21: ='Ratio Analysis'!J27 -> 1.4744333 | H21: ='Ratio Analysis'!K27 -> 1.7545929 | I21: ='Ratio Analysis'!L27 -> 1.7194951 | K21: Overvalued
B22: ='Ratio Analysis'!B25 -> Return on Capital Employed | F22: ='Ratio Analysis'!I25 -> 0.30338313 | G22: ='Ratio Analysis'!J25 -> 0.48309913 | H22: ='Ratio Analysis'!K25 -> 0.60087135 | I22: ='Ratio Analysis'!L25 -> 0.55144615
B23: ='Ratio Analysis'!B28 -> Self Sustained Growth Rate | F23: ='Ratio Analysis'!I28 -> 0.56254166 | G23: ='Ratio Analysis'!J28 -> 1.2569939 | H23: ='Ratio Analysis'!K28 -> 1.502328 | I23: ='Ratio Analysis'!L28 -> 1.4603688
B24: Debt/Equity | F24: ='Ratio Analysis'!I30 -> 1.8714397 | G24: ='Ratio Analysis'!J30 -> 2.1639246 | H24: ='Ratio Analysis'!K30 -> 2.6144616 | I24: ='Ratio Analysis'!L30 -> 1.994175 | L24: $ | M24: =DCF!E40 -> 124.93382
B25: ='Ratio Analysis'!B47 -> CFO/Total Assets | F25: ='Ratio Analysis'!I47 -> 0.24907993 | G25: ='Ratio Analysis'!J47 -> 0.29640287 | H25: ='Ratio Analysis'!K47 -> 0.34627716 | I25: ='Ratio Analysis'!L47 -> 0.31352334
B26: ='Ratio Analysis'!B35 -> Inventory Turnover | F26: ='Ratio Analysis'!I42 -> 8.7903178 | G26: ='Ratio Analysis'!J42 -> 9.1181021 | H26: ='Ratio Analysis'!K42 -> 9.4096741 | I26: ='Ratio Analysis'!L42 -> 9.610915
B28: MOAT | K28: 5 year Average Financials
B36: Insights | K36: 5 Year Average Revenue Distribution
R38: 2019 | S38: 2020 | T38: 2021 | U38: 2022 | V38: 2023 | W38: Avg
Q39: iPhone | R39: 142381 | S39: 137781 | T39: 191973 | U39: 205489 | V39: 200583 | W39: =AVERAGE(R39:V39) -> 175641.4
Q40: Mac | R40: 25740 | S40: 28622 | T40: 35190 | U40: 40177 | V40: 29357 | W40: =AVERAGE(R40:V40) -> 31817.2
Q41: iPad | R41: 21280 | S41: 23724 | T41: 31862 | U41: 29292 | V41: 28300 | W41: =AVERAGE(R41:V41) -> 26891.6
Q42: Wearables, Home and Accessories | R42: 24482 | S42: 30620 | T42: 38367 | U42: 41241 | V42: 39845 | W42: =AVERAGE(R42:V42) -> 34911
Q43: Services | R43: 46291 | S43: 53768 | T43: 68425 | U43: 78129 | V43: 85200 | W43: =AVERAGE(R43:V43) -> 66362.6
Q44: Total net sales | R44: 260174 | S44: 274515 | T44: 365817 | U44: 394328 | V44: 383285 | W44: =AVERAGE(R44:V44) -> 335623.8
K48: Shareholding Pattern
Q50: Institutional investors | R50: 0.5756
Q51: Insiders | R51: 0.0522
Q52: Public Companies and Individual investors | R52: =100%-R50-R51 -> 0.3722

Sheet Financials>

Sheet Historical & Forecasted FS
B4: in millions ($)
B5: ="Historical Financial Statement -"&'Data Sheet'!$A$4 -> Historical Financial Statement -Apple Inc. | N5: ="Forecasted Financial Statement " & "-" &'Data Sheet'!$A$4 -> Forecasted Financial Statement -Apple Inc.
B6: Years | C6: 2014 | D6: =C6+1 -> 2015 | E6: =D6+1 -> 2016 | F6: =E6+1 -> 2017 | G6: =F6+1 -> 2018 | H6: 2019 | I6: =H6+1 -> 2020 | J6: =I6+1 -> 2021 | K6: =J6+1 -> 2022 | L6: =K6+1 -> 2023 | M6: LTM | N6: =L6+1 -> 2024 | O6: =N6+1 -> 2025 | P6: =O6+1 -> 2026 | Q6: =P6+1 -> 2027 | R6: =Q6+1 -> 2028
A7: # | B7: Income Statement | C7: 1 | D7: 2 | E7: 3 | F7: 4 | G7: 5 | H7: 6 | I7: 7 | J7: 8 | K7: 9 | L7: 10 | N7: 11 | O7: 12 | P7: 13 | Q7: 14 | R7: 15
B8: Sales | C8: =IFERROR('Data Sheet'!B20,0) -> 182795 | D8: =IFERROR('Data Sheet'!C20,0) -> 233715 | E8: =IFERROR('Data Sheet'!D20,0) -> 215639 | F8: =IFERROR('Data Sheet'!E20,0) -> 229234 | G8: =IFERROR('Data Sheet'!F20,0) -> 265595 | H8: =IFERROR('Data Sheet'!G20,0) -> 260174 | I8: =IFERROR('Data Sheet'!H20,0) -> 274515 | J8: =IFERROR('Data Sheet'!I20,0) -> 365817 | ... L8: =IFERROR('Data Sheet'!K20,0) -> 383285 | M8: ='Data Sheet'!L20 -> 385706 | N8: =L8*(1+N9) -> 410114.95 | O8: =N8*(1+O9) -> 451126.45 | P8: =O8*(1+P9) -> 500750.35 | Q8: =P8*(1+Q9) -> 558336.64 | R8: =Q8*(1+R9) -> 625337.04
B9: Sales Growth | C9: - | D9: =D8/C8-1 -> 0.27856342 | E9: =E8/D8-1 -> -0.077342062 | F9: =F8/E8-1 -> 0.063045182 | G9: =G8/F8-1 -> 0.15861958 | H9: =H8/G8-1 -> -0.020410776 | I9: =I8/H8-1 -> 0.055120804 | J9: =J8/I8-1 -> 0.33259385 | K9: =K8/J8-1 -> 0.077937876 | ... M9: =M8/L8-1 -> 0.0063164486 | N9: 0.07 | O9: 0.1 | P9: 0.11 | Q9: 0.115 | R9: 0.12
B11: COGS | C11: =IFERROR('Data Sheet'!B22,0) -> 112258 | D11: =IFERROR('Data Sheet'!C22,0) -> 140089 | E11: =IFERROR('Data Sheet'!D22,0) -> 131376 | F11: =IFERROR('Data Sheet'!E22,0) -> 141048 | G11: =IFERROR('Data Sheet'!F22,0) -> 163756 | H11: =IFERROR('Data Sheet'!G22,0) -> 161782 | I11: =IFERROR('Data Sheet'!H22,0) -> 169559 | J11: =IFERROR('Data Sheet'!I22,0) -> 212981 | ... L11: =IFERROR('Data Sheet'!K22,0) -> 214137 | M11: ='Data Sheet'!L22 -> 212035 | N11: =N8*N12 -> 227203.68 | O11: =O8*O12 -> 249924.05 | P11: =P8*P12 -> 277415.7 | Q11: =Q8*Q12 -> 309318.5 | R11: =R8*R12 -> 346436.72
B12: COGS % Sales | C12: =C11/C8 -> 0.61411964 | D12: =D11/D8 -> 0.59940098 | E12: =E11/E8 -> 0.60924044 | F12: =F11/F8 -> 0.6153014 | G12: =G11/G8 -> 0.61656281 | H12: =H11/H8 -> 0.62182232 | I12: =I11/I8 -> 0.61766752 | J12: =J11/J8 -> 0.5822064 | ... M12: =M11/M8 -> 0.54973218 | N12: 0.554 | O12: 0.554 | P12: 0.554 | Q12: 0.554 | R12: 0.554
B14: Gross Profit | C14: =IFERROR(C8-C11,0) -> 70537 | D14: =IFERROR(D8-D11,0) -> 93626 | E14: =IFERROR(E8-E11,0) -> 84263 | F14: =IFERROR(F8-F11,0) -> 88186 | G14: =IFERROR(G8-G11,0) -> 101839 | H14: =IFERROR(H8-H11,0) -> 98392 | I14: =IFERROR(I8-I11,0) -> 104956 | J14: =IFERROR(J8-J11,0) -> 152836 | ... R14: =IFERROR(R8-R11,0) -> 278900.32
B15: Gross Profit % Sales | C15: =C14/C8 -> 0.38588036 | D15: =D14/D8 -> 0.40059902 | E15: =E14/E8 -> 0.39075956 | F15: =F14/F8 -> 0.3846986 | G15: =G14/G8 -> 0.38343719 | H15: =H14/H8 -> 0.37817768 | I15: =I14/I8 -> 0.38233248 | J15: =J14/J8 -> 0.4177936 | ... R15: =R14/R8 -> 0.446
B17: SG&A Expenses | C17: =IFERROR('Data Sheet'!B25,0) -> 11993 | D17: =IFERROR('Data Sheet'!C25,0) -> 14329 | E17: =IFERROR('Data Sheet'!D25,0) -> 14194 | F17: =IFERROR('Data Sheet'!E25,0) -> 15261 | G17: =IFERROR('Data Sheet'!F25,0) -> 16705 | H17: =IFERROR('Data Sheet'!G25,0) -> 18245 | I17: =IFERROR('Data Sheet'!H25,0) -> 19916 | J17: =IFERROR('Data Sheet'!I25,0) -> 21973 | ... M17: =IFERROR('Data Sheet'!L25,0) -> 25111 | N17: =FORECAST(N7,$C$17:$L$17,$C$7:$L$7) -> 26471.067 | O17: =FORECAST(O7,$C$17:$L$17,$C$7:$L$7) -> 27963.224 | P17: =FORECAST(P7,$C$17:$L$17,$C$7:$L$7) -> 29455.382 | Q17: =FORECAST(Q7,$C$17:$L$17,$C$7:$L$7) -> 30947.539 | R17: =FORECAST(R7,$C$17:$L$17,$C$7:$L$7) -> 32439.697
B18: SG&A % Sales | C18: =C17/C8 -> 0.065609016 | D18: =D17/D8 -> 0.061309715 | E18: =E17/E8 -> 0.065822973 | F18: =F17/F8 -> 0.066573894 | G18: =G17/G8 -> 0.062896515 | H18: =H17/H8 -> 0.070126146 | I18: =I17/I8 -> 0.07254977 | J18: =J17/J8 -> 0.060065552 | ... R18: =R17/R8 -> 0.05187554
B20: R&D Expenses | C20: =IFERROR('Data Sheet'!B26,0) -> 6041 | D20: =IFERROR('Data Sheet'!C26,0) -> 8067 | E20: =IFERROR('Data Sheet'!D26,0) -> 10045 | F20: =IFERROR('Data Sheet'!E26,0) -> 11581 | G20: =IFERROR('Data Sheet'!F26,0) -> 14236 | H20: =IFERROR('Data Sheet'!G26,0) -> 16217 | I20: =IFERROR('Data Sheet'!H26,0) -> 18752 | J20: =IFERROR('Data Sheet'!I26,0) -> 21914 | ... M20: =IFERROR('Data Sheet'!L26,0) -> 29902 | N20: =FORECAST(N7,$C$20:$L$20,$C$7:$L$7) -> 30468.333 | O20: =FORECAST(O7,$C$20:$L$20,$C$7:$L$7) -> 33044.048 | P20: =FORECAST(P7,$C$20:$L$20,$C$7:$L$7) -> 35619.764 | Q20: =FORECAST(Q7,$C$20:$L$20,$C$7:$L$7) -> 38195.479 | R20: =FORECAST(R7,$C$20:$L$20,$C$7:$L$7) -> 40771.194
B21: R&D % Sales | C21: =C20/C8 -> 0.03304795 | D21: =D20/D8 -> 0.034516398 | E21: =E20/E8 -> 0.046582483 | F21: =F20/F8 -> 0.050520429 | G21: =G20/G8 -> 0.053600407 | H21: =H20/H8 -> 0.062331363 | I21: =I20/I8 -> 0.068309564 | J21: =J20/J8 -> 0.059904269 | ... R21: =R20/R8 -> 0.065198751
B23: EBIT | C23: =IFERROR(C14-SUM(C20,C17),0) -> 52503 | D23: =IFERROR(D14-SUM(D20,D17),0) -> 71230 | E23: =IFERROR(E14-SUM(E20,E17),0) -> 60024 | F23: =IFERROR(F14-SUM(F20,F17),0) -> 61344 | G23: =IFERROR(G14-SUM(G20,G17),0) -> 70898 | H23: =IFERROR(H14-SUM(H20,H17),0) -> 63930 | I23: =IFERROR(I14-SUM(I20,I17),0) -> 66288 | J23: =IFERROR(J14-SUM(J20,J17),0) -> 108949 | ... R23: =IFERROR(R14-SUM(R20,R17),0) -> 205689.43
B24: EBIT Margins | C24: =C23/C8 -> 0.28722339 | D24: =D23/D8 -> 0.30477291 | E24: =E23/E8 -> 0.2783541 | F24: =F23/F8 -> 0.26760428 | G24: =G23/G8 -> 0.26694027 | H24: =H23/H8 -> 0.24572017 | I24: =I23/I8 -> 0.24147314 | J24: =J23/J8 -> 0.29782378 | ... R24: =R23/R8 -> 0.32892571
B26: Dep & Amm | C26: =IFERROR('Data Sheet'!B216,0) -> 6846 | D26: =IFERROR('Data Sheet'!C216,0) -> 9957 | E26: =IFERROR('Data Sheet'!D216,0) -> 10505 | F26: =IFERROR('Data Sheet'!E216,0) -> 10157 | G26: =IFERROR('Data Sheet'!F216,0) -> 10903 | H26: =IFERROR('Data Sheet'!G216,0) -> 12547 | I26: =IFERROR('Data Sheet'!H216,0) -> 11056 | J26: =IFERROR('Data Sheet'!I216,0) -> 11284 | ... M26: =IFERROR('Data Sheet'!L216,0) -> 11451 | N26: =FORECAST(N7,$C$26:$L$26,$C$7:$L$7) -> 12531.867 | O26: =FORECAST(O7,$C$26:$L$26,$C$7:$L$7) -> 12885.333 | P26: 12885 | Q26: 12885 | R26: 12885
B27: Dep & Amm % Sales | C27: =C26/C8 -> 0.03745179 | D27: =D26/D8 -> 0.042603171 | E27: =E26/E8 -> 0.048715678 | F27: =F26/F8 -> 0.044308436 | G27: =G26/G8 -> 0.041051225 | H27: =H26/H8 -> 0.048225418 | I27: =I26/I8 -> 0.040274666 | J27: =J26/J8 -> 0.030846024 | ... R27: =R26/R8 -> 0.020604888
B29: EBITDA | C29: =IFERROR(C23+C26,0) -> 59349 | D29: =IFERROR(D23+D26,0) -> 81187 | E29: =IFERROR(E23+E26,0) -> 70529 | F29: =IFERROR(F23+F26,0) -> 71501 | G29: =IFERROR(G23+G26,0) -> 81801 | H29: =IFERROR(H23+H26,0) -> 76477 | I29: =IFERROR(I23+I26,0) -> 77344 | J29: =IFERROR(J23+J26,0) -> 120233 | ... R29: =IFERROR(R23+R26,0) -> 218574.43
B30: EBITDA Margins | C30: =C29/C8 -> 0.32467518 | D30: =D29/D8 -> 0.34737608 | E30: =E29/E8 -> 0.32706978 | F30: =F29/F8 -> 0.31191272 | G30: =G29/G8 -> 0.30799149 | H30: =H29/H8 -> 0.29394559 | I30: =I29/I8 -> 0.28174781 | J30: =J29/J8 -> 0.3286698 | ... R30: =R29/R8 -> 0.3495306
B32: Other operating expenses | C32: =IFERROR('Data Sheet'!B38,0) -> -431 | D32: =IFERROR('Data Sheet'!C38,0) -> -903 | E32: =IFERROR('Data Sheet'!D38,0) -> -1195 | F32: =IFERROR('Data Sheet'!E38,0) -> -133 | G32: =IFERROR('Data Sheet'!F38,0) -> -441 | H32: =IFERROR('Data Sheet'!G38,0) -> 422 | I32: =IFERROR('Data Sheet'!H38,0) -> -87 | J32: =IFERROR('Data Sheet'!I38,0) -> 60 | ... M32: =IFERROR('Data Sheet'!L38,0) -> -39 | N32: =FORECAST(N7,$C$32:$L$32,$C$7:$L$7) -> 82.933333 | O32: =FORECAST(O7,$C$32:$L$32,$C$7:$L$7) -> 158.33939 | P32: =FORECAST(P7,$C$32:$L$32,$C$7:$L$7) -> 233.74545 | Q32: =FORECAST(Q7,$C$32:$L$32,$C$7:$L$7) -> 309.15152 | R32: =FORECAST(R7,$C$32:$L$32,$C$7:$L$7) -> 384.55758
B33: Other Op Ex % Sales | C33: =C32/C11 -> -0.00383937 | D33: =D32/D11 -> -0.0064459022 | E33: =E32/E11 -> -0.0090960297 | F33: =F32/F11 -> -0.00094294141 | G33: =G32/G11 -> -0.0026930311 | H33: =H32/H11 -> 0.0026084484 | I33: =I32/I11 -> -0.00051309574 | J33: =J32/J11 -> 0.00028171527 | ... R33: =R32/R11 -> 0.001110037
B35: Net Interest Expense | C35: =IFERROR('Data Sheet'!B36,0) -> 1411 | D35: =IFERROR('Data Sheet'!C36,0) -> 2188 | E35: =IFERROR('Data Sheet'!D36,0) -> 2543 | F35: =IFERROR('Data Sheet'!E36,0) -> 2878 | G35: =IFERROR('Data Sheet'!F36,0) -> 2446 | H35: =IFERROR('Data Sheet'!G36,0) -> 1385 | I35: =IFERROR('Data Sheet'!H36,0) -> 890 | J35: =IFERROR('Data Sheet'!I36,0) -> 198 | ... M35: =IFERROR('Data Sheet'!L36,0) -> -183 | N35: =FORECAST(N7,$C$35:$L$35,$C$7:$L$7) -> -273.46667 | O35: =FORECAST(O7,$C$35:$L$35,$C$7:$L$7) -> -571.3697 | P35: =FORECAST(P7,$C$35:$L$35,$C$7:$L$7) -> -869.27273 | Q35: =FORECAST(Q7,$C$35:$L$35,$C$7:$L$7) -> -1167.1758 | R35: =FORECAST(R7,$C$35:$L$35,$C$7:$L$7) -> -1465.0788
B36: Interest % Sales | C36: =C35/C8 -> 0.0077190295 | D36: =D35/D8 -> 0.0093618296 | E36: =E35/E8 -> 0.011792858 | F36: =F35/F8 -> 0.012554857 | G36: =G35/G8 -> 0.0092095107 | H36: =H35/H8 -> 0.0053233605 | I36: =I35/I8 -> 0.0032420815 | J36: =J35/J8 -> 0.00054125423 | ... R36: =R35/R8 -> -0.0023428626
B38: Dep & Amm | C38: =IFERROR('Data Sheet'!B216,0) -> 6846 | D38: =IFERROR('Data Sheet'!C216,0) -> 9957 | E38: =IFERROR('Data Sheet'!D216,0) -> 10505 | F38: =IFERROR('Data Sheet'!E216,0) -> 10157 | G38: =IFERROR('Data Sheet'!F216,0) -> 10903 | H38: =IFERROR('Data Sheet'!G216,0) -> 12547 | I38: =IFERROR('Data Sheet'!H216,0) -> 11056 | J38: =IFERROR('Data Sheet'!I216,0) -> 11284 | ... M38: =IFERROR('Data Sheet'!L216,0) -> 11451 | N38: =FORECAST(N7,$C$38:$L$38,$C$7:$L$7) -> 12531.867 | O38: =FORECAST(O7,$C$38:$L$38,$C$7:$L$7) -> 12885.333 | P38: =FORECAST(P7,$C$38:$L$38,$C$7:$L$7) -> 13238.8 | Q38: =FORECAST(Q7,$C$38:$L$38,$C$7:$L$7) -> 13592.267 | R38: =FORECAST(R7,$C$38:$L$38,$C$7:$L$7) -> 13945.733
B39: Dep & Amm % Sales | C39: =C38/C8 -> 0.03745179 | D39: =D38/D8 -> 0.042603171 | E39: =E38/E8 -> 0.048715678 | F39: =F38/F8 -> 0.044308436 | G39: =G38/G8 -> 0.041051225 | H39: =H38/H8 -> 0.048225418 | I39: =I38/I8 -> 0.040274666 | J39: =J38/J8 -> 0.030846024 | ... R39: =R38/R8 -> 0.022301147
B41: EBT | C41: =IFERROR(C29+C32+C35-C38,0) -> 53483 | D41: =IFERROR(D29+D32+D35-D38,0) -> 72515 | E41: =IFERROR(E29+E32+E35-E38,0) -> 61372 | F41: =IFERROR(F29+F32+F35-F38,0) -> 64089 | G41: =IFERROR(G29+G32+G35-G38,0) -> 72903 | H41: =IFERROR(H29+H32+H35-H38,0) -> 65737 | I41: =IFERROR(I29+I32+I35-I38,0) -> 67091 | J41: =IFERROR(J29+J32+J35-J38,0) -> 109207 | ... R41: =IFERROR(R29+R32+R35-R38,0) -> 203548.18
B42: EBT Margins | C42: =C41/C8 -> 0.29258459 | D42: =D41/D8 -> 0.31027106 | E42: =E41/E8 -> 0.28460529 | F42: =F41/F8 -> 0.27957895 | G42: =G41/G8 -> 0.27448935 | H42: =H41/H8 -> 0.25266552 | I42: =I41/I8 -> 0.2443983 | J42: =J41/J8 -> 0.29852905 | ... R42: =R41/R8 -> 0.32550155
B44: Tax | C44: =IFERROR('Data Sheet'!B45,0) -> 13973 | D44: =IFERROR('Data Sheet'!C45,0) -> 19121 | E44: =IFERROR('Data Sheet'!D45,0) -> 15685 | F44: =IFERROR('Data Sheet'!E45,0) -> 15738 | G44: =IFERROR('Data Sheet'!F45,0) -> 13372 | H44: =IFERROR('Data Sheet'!G45,0) -> 10481 | I44: =IFERROR('Data Sheet'!H45,0) -> 9680 | J44: =IFERROR('Data Sheet'!I45,0) -> 14527 | ... M44: =IFERROR('Data Sheet'!L45,0) -> 17523 | N44: =N41*N45 -> 18515.012 | O44: =O41*O45 -> 20575.924 | P44: =P41*P45 -> 23150.171 | Q44: =Q41*Q45 -> 26247.208 | R44: =R41*R45 -> 29962.291
B45: Effective Tax Rate | C45: =C44/C41 -> 0.26126059 | D45: =D44/D41 -> 0.26368338 | E45: =E44/E41 -> 0.25557257 | F45: =F44/F41 -> 0.24556476 | G45: =G44/G41 -> 0.18342181 | H45: =H44/H41 -> 0.15943837 | I45: =I44/I41 -> 0.14428165 | J45: =J44/J41 -> 0.13302261 | ... M45: =M44/M41 -> 0.14795333 | N45: 0.1472 | O45: 0.1472 | P45: 0.1472 | Q45: 0.1472 | R45: 0.1472
B47: Net profit | C47: =IFERROR(C41-C44,0) -> 39510 | D47: =IFERROR(D41-D44,0) -> 53394 | E47: =IFERROR(E41-E44,0) -> 45687 | F47: =IFERROR(F41-F44,0) -> 48351 | G47: =IFERROR(G41-G44,0) -> 59531 | H47: =IFERROR(H41-H44,0) -> 55256 | I47: =IFERROR(I41-I44,0) -> 57411 | J47: =IFERROR(J41-J44,0) -> 94680 | ... R47: =IFERROR(R41-R44,0) -> 173585.88
B48: Net Margins | C48: =C47/C8 -> 0.21614377 | D48: =D47/D8 -> 0.22845774 | E48: =E47/E8 -> 0.21186798 | F48: =F47/F8 -> 0.21092421 | G48: =G47/G8 -> 0.22414202 | H48: =H47/H8 -> 0.21238095 | I48: =I47/I8 -> 0.20913611 | J48: =J47/J8 -> 0.25881793 | ... R48: =R47/R8 -> 0.27758772
B50: No. of Equity Shares | C50: =IFERROR('Data Sheet'!B183,0) -> 23464.644 | D50: =IFERROR('Data Sheet'!C183,0) -> 22315.012 | E50: =IFERROR('Data Sheet'!D183,0) -> 21344.664 | F50: =IFERROR('Data Sheet'!E183,0) -> 20504.804 | G50: =IFERROR('Data Sheet'!F183,0) -> 19019.944 | H50: =IFERROR('Data Sheet'!G183,0) -> 17772.944 | I50: =IFERROR('Data Sheet'!H183,0) -> 16976.763 | J50: =IFERROR('Data Sheet'!I183,0) -> 16426.786 | ... M50: =IFERROR('Data Sheet'!L183,0) -> 15460.223 | N50: 15460 | O50: =N50 -> 15460 | P50: =O50 -> 15460 | Q50: =P50 -> 15460 | R50: =Q50 -> 15460
B52: Earnings per share | C52: =IFERROR(C47/C50,0) -> 1.6838099 | D52: =IFERROR(D47/D50,0) -> 2.392739 | E52: =IFERROR(E47/E50,0) -> 2.1404413 | F52: =IFERROR(F47/F50,0) -> 2.3580328 | G52: =IFERROR(G47/G50,0) -> 3.1299251 | H52: =IFERROR(H47/H50,0) -> 3.1089953 | I52: =IFERROR(I47/I50,0) -> 3.3817401 | J52: =IFERROR(J47/J50,0) -> 5.7637568 | ... M52: =IFERROR(M47/M50,0) -> 6.5272668 | N52: =N47/DCF!$E$39 -> 6.93607 | O52: =O47/DCF!$E$39 -> 7.7081259 | P52: =P47/DCF!$E$39 -> 8.6724872 | Q52: =Q47/DCF!$E$39 -> 9.8326949 | R52: =R47/DCF!$E$39 -> 11.224435
B53: EPS Growth % | C53: - | D53: =D52/C52-1 -> 0.42102681 | E53: =E52/D52-1 -> -0.10544307 | F53: =F52/E52-1 -> 0.10165731 | G53: =G52/F52-1 -> 0.32734588 | H53: =H52/G52-1 -> -0.0066869835 | I53: =I52/H52-1 -> 0.087727617 | J53: =J52/I52-1 -> 0.70437605 | K53: =K52/J52-1 -> 0.086066263 | ... M53: =M52/L52-1 -> 0.046439472 | N53: =N52/L52-1 -> 0.11197805 | O53: =O52/N52-1 -> 0.11131029 | P53: =P52/O52-1 -> 0.12510969 | Q53: =Q52/P52-1 -> 0.13378028 | R53: =R52/Q52-1 -> 0.14154206
B55: Dividend per share | C55: =IFERROR('Data Sheet'!B72,0) -> 0.46 | D55: =IFERROR('Data Sheet'!C72,0) -> 0.5 | E55: =IFERROR('Data Sheet'!D72,0) -> 0.55 | F55: =IFERROR('Data Sheet'!E72,0) -> 0.6 | G55: =IFERROR('Data Sheet'!F72,0) -> 0.68 | H55: =IFERROR('Data Sheet'!G72,0) -> 0.75 | I55: =IFERROR('Data Sheet'!H72,0) -> 0.8 | J55: =IFERROR('Data Sheet'!I72,0) -> 0.85 | ... M55: =IFERROR('Data Sheet'!L72,0) -> 0.95 | N55: 0.97 | O55: 0.98 | P55: 0.99 | Q55: =P55 -> 0.99 | R55: =Q55 -> 0.99
B56: Dividend payout ratio | C56: =IFERROR(C55/C52,0) -> 0.27318998 | D56: =IFERROR(D55/D52,0) -> 0.20896554 | E56: =IFERROR(E55/E52,0) -> 0.25695636 | F56: =IFERROR(F55/F52,0) -> 0.25444939 | G56: =IFERROR(G55/G52,0) -> 0.2172576 | H56: =IFERROR(H55/H52,0) -> 0.24123549 | I56: =IFERROR(I55/I52,0) -> 0.2365646 | J56: =IFERROR(J55/J52,0) -> 0.14747326 | ... R56: =IFERROR(R55/R52,0) -> 0.088200432
B58: Retained Earnings | C58: =IFERROR(1-C56,0) -> 0.72681002 | D58: =IFERROR(1-D56,0) -> 0.79103446 | E58: =IFERROR(1-E56,0) -> 0.74304364 | F58: =IFERROR(1-F56,0) -> 0.74555061 | G58: =IFERROR(1-G56,0) -> 0.7827424 | H58: =IFERROR(1-H56,0) -> 0.75876451 | I58: =IFERROR(1-I56,0) -> 0.7634354 | J58: =IFERROR(1-J56,0) -> 0.85252674 | ... R58: =IFERROR(1-R56,0) -> 0.91179957
B60: in millions ($)
B61: ="Historical Financial Statement -"&'Data Sheet'!$A$4 -> Historical Financial Statement -Apple Inc. | N61: ="Forecasted Financial Statement " & "-" &'Data Sheet'!$A$4 -> Forecasted Financial Statement -Apple Inc.
B62: Years | C62: 2014 | D62: =C62+1 -> 2015 | E62: =D62+1 -> 2016 | F62: =E62+1 -> 2017 | G62: =F62+1 -> 2018 | H62: 2019 | I62: =H62+1 -> 2020 | J62: =I62+1 -> 2021 | K62: =J62+1 -> 2022 | L62: =K62+1 -> 2023 | M62: LTM | N62: =L62+1 -> 2024 | O62: =N62+1 -> 2025 | P62: =O62+1 -> 2026 | Q62: =P62+1 -> 2027 | R62: =Q62+1 -> 2028
A63: # | B63: Balance Sheet
B64: Cash And Equivalents | C64: =IFERROR('Data Sheet'!B130,0) -> 13844 | D64: =IFERROR('Data Sheet'!C130,0) -> 21120 | E64: =IFERROR('Data Sheet'!D130,0) -> 20484 | F64: =IFERROR('Data Sheet'!E130,0) -> 20289 | G64: =IFERROR('Data Sheet'!F130,0) -> 25913 | H64: =IFERROR('Data Sheet'!G130,0)+1380 -> 50224 | I64: =IFERROR('Data Sheet'!H130,0)-I69 -> 39789 | J64: =IFERROR('Data Sheet'!I130,0)-J69 -> 35929 | K64: =IFERROR('Data Sheet'!J130,0)-K69 -> 24977 | L64: =IFERROR('Data Sheet'!K130,0)-L69 -> 30737 | M64: =IFERROR('Data Sheet'!L130,0)-M69 -> 55007 | N64: =L64*(1+N9) -> 32888.59 | O64: =N64*(1+O9) -> 36177.449 | P64: =O64*(1+P9) -> 40156.968 | Q64: =P64*(1+Q9) -> 44775.02 | R64: =Q64*(1+R9) -> 50148.022
B65: Short Term Investments | C65: =IFERROR('Data Sheet'!B131,0) -> 11233 | D65: =IFERROR('Data Sheet'!C131,0) -> 20481 | E65: =IFERROR('Data Sheet'!D131,0) -> 46671 | F65: =IFERROR('Data Sheet'!E131,0) -> 53892 | G65: =IFERROR('Data Sheet'!F131,0) -> 40388 | H65: =IFERROR('Data Sheet'!G131,0) -> 51713 | I65: =IFERROR('Data Sheet'!H131,0) -> 52927 | J65: =IFERROR('Data Sheet'!I131,0) -> 27699 | ... M65: =IFERROR('Data Sheet'!L131,0) -> 32340 | N65: =L65*(1+N9) -> 33801.3 | O65: =N65*(1+O9) -> 37181.43 | P65: =O65*(1+P9) -> 41271.387 | Q65: =P65*(1+Q9) -> 46017.597 | R65: =Q65*(1+R9) -> 51539.708
B66: Trading Asset Securities | C66: =IFERROR('Data Sheet'!B132,0) -> 81 | D66: =IFERROR('Data Sheet'!C132,0) -> 394 | E66: =IFERROR('Data Sheet'!D132,0) -> - | F66: =IFERROR('Data Sheet'!E132,0) -> - | G66: =IFERROR('Data Sheet'!F132,0) -> - | I66: =IFERROR('Data Sheet'!H132,0) -> - | J66: =IFERROR('Data Sheet'!I132,0) -> - | K66: =IFERROR('Data Sheet'!J132,0) -> - | L66: =IFERROR('Data Sheet'!K132,0) -> - | M66: =IFERROR('Data Sheet'!L132,0) -> - | N66: - | O66: - | P66: - | Q66: - | R66: -
B67: Accounts Receivable | C67: =IFERROR('Data Sheet'!B135,0) -> 17460 | D67: =IFERROR('Data Sheet'!C135,0) -> 16849 | E67: =IFERROR('Data Sheet'!D135,0) -> 15754 | F67: =IFERROR('Data Sheet'!E135,0) -> 17874 | G67: =IFERROR('Data Sheet'!F135,0) -> 23186 | H67: =IFERROR('Data Sheet'!G135,0) -> 22926 | I67: =IFERROR('Data Sheet'!H135,0) -> 16120 | J67: =IFERROR('Data Sheet'!I135,0) -> 26278 | ... M67: =IFERROR('Data Sheet'!L135,0) -> 23194 | N67: =L67*(1+N9) -> 31573.56 | O67: =N67*(1+O9) -> 34730.916 | P67: =O67*(1+P9) -> 38551.317 | Q67: =P67*(1+Q9) -> 42984.718 | R67: =Q67*(1+R9) -> 48142.884
B68: Other Receivables | C68: =IFERROR('Data Sheet'!B136,0) -> 9759 | D68: =IFERROR('Data Sheet'!C136,0) -> 13494 | E68: =IFERROR('Data Sheet'!D136,0) -> 13545 | F68: =IFERROR('Data Sheet'!E136,0) -> 17799 | G68: =IFERROR('Data Sheet'!F136,0) -> 25809 | H68: =IFERROR('Data Sheet'!G136,0) -> 22878 | I68: =IFERROR('Data Sheet'!H136,0) -> 21325 | J68: =IFERROR('Data Sheet'!I136,0) -> 25228 | ... M68: =IFERROR('Data Sheet'!L136,0) -> 26908 | N68: =L68*(1+N9) -> 33680.39 | O68: =N68*(1+O9) -> 37048.429 | P68: =O68*(1+P9) -> 41123.756 | Q68: =P68*(1+Q9) -> 45852.988 | R68: =Q68*(1+R9) -> 51355.347
B69: Restricted Cash | C69: =IFERROR('Data Sheet'!B140,0) -> 4318 | D69: =IFERROR('Data Sheet'!C140,0) -> - | E69: =IFERROR('Data Sheet'!D140,0) -> - | F69: =IFERROR('Data Sheet'!E140,0) -> - | G69: =IFERROR('Data Sheet'!F140,0) -> - | H69: =IFERROR('Data Sheet'!G140,0)-1380 -> -1357 | I69: -1773 | J69: -989 | K69: -1331 | L69: -772 | M69: -14247 | N69: - | O69: - | P69: - | Q69: - | R69: -
B70: Inventory | C70: =IFERROR('Data Sheet'!B139,0) -> 2111 | D70: =IFERROR('Data Sheet'!C139,0) -> 2349 | E70: =IFERROR('Data Sheet'!D139,0) -> 2132 | F70: =IFERROR('Data Sheet'!E139,0) -> 4855 | G70: =IFERROR('Data Sheet'!F139,0) -> 3956 | H70: =IFERROR('Data Sheet'!G139,0) -> 4106 | I70: =IFERROR('Data Sheet'!H139,0) -> 4061 | J70: =IFERROR('Data Sheet'!I139,0) -> 6580 | ... M70: =IFERROR('Data Sheet'!L139,0) -> 6511 | N70: =L70*(1+(N11/L11-1)) -> 6717.3189 | O70: =N70*(1+(O11/N11-1)) -> 7389.0508 | P70: 6100 | Q70: 6256 | R70: =Q70*(1+(R11/Q11-1)) -> 7006.72
B71: Other Current Assets | C71: =IFERROR('Data Sheet'!B141,0) -> 9725 | D71: =IFERROR('Data Sheet'!C141,0) -> 14691 | E71: =IFERROR('Data Sheet'!D141,0) -> 8283 | F71: =IFERROR('Data Sheet'!E141,0) -> 13936 | G71: =IFERROR('Data Sheet'!F141,0) -> 12087 | H71: =IFERROR('Data Sheet'!G141,0) -> 12329 | I71: =IFERROR('Data Sheet'!H141,0) -> 11264 | J71: =IFERROR('Data Sheet'!I141,0) -> 14111 | ... M71: =IFERROR('Data Sheet'!L141,0) -> 13979 | N71: =L71*(1+N9) -> 15723.65 | O71: =N71*(1+O9) -> 17296.015 | P71: =O71*(1+P9) -> 19198.577 | Q71: =P71*(1+Q9) -> 21406.413 | R71: =Q71*(1+R9) -> 23975.183
B72: Total Current Assets | C72: =IFERROR(SUM(C64:C71),0) -> 68531 | D72: =IFERROR(SUM(D64:D71),0) -> 89378 | E72: =IFERROR(SUM(E64:E71),0) -> 106869 | F72: =IFERROR(SUM(F64:F71),0) -> 128645 | G72: =IFERROR(SUM(G64:G71),0) -> 131339 | H72: =IFERROR(SUM(H64:H71),0) -> 162819 | I72: =IFERROR(SUM(I64:I71),0) -> 143713 | J72: =IFERROR(SUM(J64:J71),0) -> 134836 | ... R72: =IFERROR(SUM(R64:R71),0) -> 232167.86
B74: Gross Property, Plant & Equipment | C74: =IFERROR('Data Sheet'!B144,0) -> 39015 | D74: =IFERROR('Data Sheet'!C144,0) -> 49257 | E74: =IFERROR('Data Sheet'!D144,0) -> 61245 | F74: =IFERROR('Data Sheet'!E144,0) -> 75076 | G74: =IFERROR('Data Sheet'!F144,0) -> 90403 | H74: =IFERROR('Data Sheet'!G144,0) -> 95957 | I74: =IFERROR('Data Sheet'!H144,0) -> 112096 | J74: =IFERROR('Data Sheet'!I144,0) -> 119810 | ... M74: =IFERROR('Data Sheet'!L144,0) -> 116176 | N74: =L74*(1+N9+3%) -> 137786 | O74: =N74*(1+O9) -> 151564.6 | P74: =O74*(1+P9) -> 168236.71 | Q74: =P74*(1+Q9) -> 187583.93 | R74: =Q74*(1+R9) -> 210094
B75: Accumulated Depreciation | C75: =IFERROR('Data Sheet'!B145,0) -> -18391 | D75: =IFERROR('Data Sheet'!C145,0) -> -26786 | E75: =IFERROR('Data Sheet'!D145,0) -> -34235 | F75: =IFERROR('Data Sheet'!E145,0) -> -41293 | G75: =IFERROR('Data Sheet'!F145,0) -> -49099 | H75: =IFERROR('Data Sheet'!G145,0) -> -58579 | I75: =IFERROR('Data Sheet'!H145,0) -> -66760 | J75: =IFERROR('Data Sheet'!I145,0) -> -70283 | ... M75: =IFERROR('Data Sheet'!L145,0) -> -72510 | N75: =L75*(1+N39) -> -73050 | O75: =N75*(1+O39) -> -75136.496 | P75: =O75*(1+P39) -> -77122.949 | Q75: =P75*(1+Q39) -> -79000.446 | R75: =Q75*(1+R39) -> -80762.247
B76: Net Property, Plant & Equipment | C76: =IFERROR(SUM(C74:C75),0) -> 20624 | D76: =IFERROR(SUM(D74:D75),0) -> 22471 | E76: =IFERROR(SUM(E74:E75),0) -> 27010 | F76: =IFERROR(SUM(F74:F75),0) -> 33783 | G76: =IFERROR(SUM(G74:G75),0) -> 41304 | H76: =IFERROR(SUM(H74:H75),0) -> 37378 | I76: =IFERROR(SUM(I74:I75),0) -> 45336 | J76: =IFERROR(SUM(J74:J75),0) -> 49527 | ... M76: =IFERROR(SUM(M74:M75),0) -> 43666 | N76: =SUM(N74:N75) -> 64736 | O76: =SUM(O74:O75) -> 76428.104 | P76: =SUM(P74:P75) -> 91113.757 | Q76: =SUM(Q74:Q75) -> 108583.48 | R76: =SUM(R74:R75) -> 129331.75
B77: Long-term Investments | C77: =IFERROR('Data Sheet'!B148,0) -> 130162 | D77: =IFERROR('Data Sheet'!C148,0) -> 164065 | E77: =IFERROR('Data Sheet'!D148,0) -> 170430 | F77: =IFERROR('Data Sheet'!E148,0) -> 194714 | G77: =IFERROR('Data Sheet'!F148,0) -> 170799 | H77: =IFERROR('Data Sheet'!G148,0) -> 105341 | I77: =IFERROR('Data Sheet'!H148,0) -> 100887 | J77: =IFERROR('Data Sheet'!I148,0) -> 127877 | ... M77: =IFERROR('Data Sheet'!L148,0) -> 99475 | N77: =L77*(1+N9) -> 107582.08 | O77: =N77*(1+O9) -> 118340.29 | P77: =O77*(1+P9) -> 131357.72 | Q77: =P77*(1+Q9) -> 146463.86 | R77: =Q77*(1+R9) -> 164039.52
B78: Goodwill | C78: =IFERROR('Data Sheet'!B149,0) -> 4616 | D78: =IFERROR('Data Sheet'!C149,0) -> 5116 | E78: =IFERROR('Data Sheet'!D149,0) -> 5414 | F78: =IFERROR('Data Sheet'!E149,0) -> - | G78: =IFERROR('Data Sheet'!F149,0) -> - | H78: =IFERROR('Data Sheet'!G149,0) -> - | I78: =IFERROR('Data Sheet'!H149,0) -> - | J78: =IFERROR('Data Sheet'!I149,0) -> - | ... M78: =IFERROR('Data Sheet'!L149,0) -> - | N78: - | O78: - | P78: - | Q78: - | R78: -
B79: Other Intangibles | C79: =IFERROR('Data Sheet'!B150,0) -> 4142 | D79: =IFERROR('Data Sheet'!C150,0) -> 3893 | E79: =IFERROR('Data Sheet'!D150,0) -> 3206 | F79: =IFERROR('Data Sheet'!E150,0) -> - | G79: =IFERROR('Data Sheet'!F150,0) -> - | H79: =IFERROR('Data Sheet'!G150,0) -> - | I79: =IFERROR('Data Sheet'!H150,0) -> - | J79: =IFERROR('Data Sheet'!I150,0) -> - | ... M79: =IFERROR('Data Sheet'!L150,0) -> - | N79: - | O79: - | P79: - | Q79: - | R79: -
B80: Other Long-Term Assets | C80: =IFERROR('Data Sheet'!B151,0) -> 3764 | D80: =IFERROR('Data Sheet'!C151,0) -> 5422 | E80: =IFERROR('Data Sheet'!D151,0) -> 8757 | F80: =IFERROR('Data Sheet'!E151,0) -> 18177 | G80: =IFERROR('Data Sheet'!F151,0) -> 22283 | H80: =IFERROR('Data Sheet'!G151,0) -> 32978 | I80: =IFERROR('Data Sheet'!H151,0) -> 33952 | J80: =IFERROR('Data Sheet'!I151,0) -> 38762 | ... M80: =IFERROR('Data Sheet'!L151,0) -> 66681 | N80: =L80*(1+N9) -> 57883.79 | O80: =N80*(1+O9) -> 63672.169 | P80: =O80*(1+P9) -> 70676.108 | Q80: =P80*(1+Q9) -> 78803.86 | R80: =Q80*(1+R9) -> 88260.323
B81: Total Non-Current Assets | C81: =IFERROR(SUM(C76:C80),0) -> 163308 | D81: =IFERROR(SUM(D76:D80),0) -> 200967 | E81: =IFERROR(SUM(E76:E80),0) -> 214817 | F81: =IFERROR(SUM(F76:F80),0) -> 246674 | G81: =IFERROR(SUM(G76:G80),0) -> 234386 | H81: =IFERROR(SUM(H76:H80),0) -> 175697 | I81: =IFERROR(SUM(I76:I80),0) -> 180175 | J81: =IFERROR(SUM(J76:J80),0) -> 216166 | ... R81: =IFERROR(SUM(R76:R80),0) -> 381631.6
B82: Total Assets | C82: =IFERROR(C81+C72,0) -> 231839 | D82: =IFERROR(D81+D72,0) -> 290345 | E82: =IFERROR(E81+E72,0) -> 321686 | F82: =IFERROR(F81+F72,0) -> 375319 | G82: =IFERROR(G81+G72,0) -> 365725 | H82: =IFERROR(H81+H72,0) -> 338516 | I82: =IFERROR(I81+I72,0) -> 323888 | J82: =IFERROR(J81+J72,0) -> 351002 | ... R82: =IFERROR(R81+R72,0) -> 613799.46
B84: Accounts Payable | C84: =IFERROR('Data Sheet'!B155,0) -> 30196 | D84: =IFERROR('Data Sheet'!C155,0) -> 35490 | E84: =IFERROR('Data Sheet'!D155,0) -> 37294 | F84: =IFERROR('Data Sheet'!E155,0) -> 44242 | G84: =IFERROR('Data Sheet'!F155,0) -> 55888 | H84: =IFERROR('Data Sheet'!G155,0) -> 46236 | I84: =IFERROR('Data Sheet'!H155,0) -> 42296 | J84: =IFERROR('Data Sheet'!I155,0) -> 54763 | ... M84: =IFERROR('Data Sheet'!L155,0) -> 58146 | N84: =L84*(1+(N11/L11-1)) -> 66431.536 | O84: =N84*(1+(O11/N11-1)) -> 73074.689 | P84: =O84*(1+(P11/O11-1)) -> 81112.905 | Q84: =P84*(1+(Q11/P11-1)) -> 90440.889 | R84: =Q84*(1+(R11/Q11-1)) -> 101293.8
B85: Short-term Borrowings | C85: =IFERROR('Data Sheet'!B156,0) -> 18372 | D85: =IFERROR('Data Sheet'!C156,0) -> 23169 | E85: =IFERROR('Data Sheet'!D156,0) -> 21864 | F85: =IFERROR('Data Sheet'!E156,0) -> - | G85: =IFERROR('Data Sheet'!F156,0) -> - | H85: =IFERROR('Data Sheet'!G156,0) -> 5980 | I85: =IFERROR('Data Sheet'!H156,0) -> 4996 | J85: =IFERROR('Data Sheet'!I156,0) -> 6000 | ... M85: =IFERROR('Data Sheet'!L156,0) -> 1998 | N85: =M85 -> 1998 | O85: =N85 -> 1998 | P85: =O85 -> 1998 | Q85: =P85 -> 1998 | R85: =Q85 -> 1998
B86: Curr. Port. of LT Debt | C86: =IFERROR('Data Sheet'!B157,0) -> 6308 | D86: =IFERROR('Data Sheet'!C157,0) -> 8499 | E86: =IFERROR('Data Sheet'!D157,0) -> 8105 | F86: =IFERROR('Data Sheet'!E157,0) -> 11977 | G86: =IFERROR('Data Sheet'!F157,0) -> 11964 | H86: =IFERROR('Data Sheet'!G157,0) -> 10260 | I86: =IFERROR('Data Sheet'!H157,0) -> 8773 | J86: =IFERROR('Data Sheet'!I157,0) -> 9613 | ... M86: =IFERROR('Data Sheet'!L157,0) -> 10954 | N86: =L86 -> 9822 | O86: =N86 -> 9822 | P86: =O86 -> 9822 | Q86: =P86 -> 9822 | R86: =Q86 -> 9822
B87: Curr. Port. of Leases | C87: =IFERROR('Data Sheet'!B158,0) -> - | D87: =IFERROR('Data Sheet'!C158,0) -> 2513 | E87: =IFERROR('Data Sheet'!D158,0) -> 3500 | F87: =IFERROR('Data Sheet'!E158,0) -> 6496 | G87: =IFERROR('Data Sheet'!F158,0) -> 8784 | H87: =IFERROR('Data Sheet'!G158,0) -> - | I87: =IFERROR('Data Sheet'!H158,0) -> 1460 | J87: =IFERROR('Data Sheet'!I158,0) -> 1528 | ... L87: =IFERROR('Data Sheet'!K158,0) -> 1575 | M87: 0 | N87: =L87 -> 1575 | O87: =N87 -> 1575 | P87: =O87 -> 1575 | Q87: =P87 -> 1575 | R87: =Q87 -> 1575
B88: Unearned Revenue, Current | C88: =IFERROR('Data Sheet'!B159,0) -> 8491 | D88: =IFERROR('Data Sheet'!C159,0) -> 8940 | E88: =IFERROR('Data Sheet'!D159,0) -> 8080 | F88: =IFERROR('Data Sheet'!E159,0) -> 7548 | G88: =IFERROR('Data Sheet'!F159,0) -> 5966 | H88: =IFERROR('Data Sheet'!G159,0) -> 5522 | I88: =IFERROR('Data Sheet'!H159,0) -> 6643 | J88: =IFERROR('Data Sheet'!I159,0) -> 7612 | ... M88: =IFERROR('Data Sheet'!L159,0) -> 8264 | N88: =L88 -> 8061 | O88: =N88 -> 8061 | P88: =O88 -> 8061 | Q88: =P88 -> 8061 | R88: =Q88 -> 8061
B89: Other Current Liabilities | C89: =IFERROR('Data Sheet'!B160,0) -> 81 | D89: =IFERROR('Data Sheet'!C160,0) -> 1999 | E89: =IFERROR('Data Sheet'!D160,0) -> 163 | F89: =IFERROR('Data Sheet'!E160,0) -> 30551 | G89: =IFERROR('Data Sheet'!F160,0) -> 33327 | H89: =IFERROR('Data Sheet'!G160,0) -> 37720 | I89: =IFERROR('Data Sheet'!H160,0) -> 41224 | J89: =IFERROR('Data Sheet'!I160,0) -> 45965 | ... M89: =IFERROR('Data Sheet'!L160,0) -> 54611 | N89: =L89 -> 57254 | O89: =N89 -> 57254 | P89: =O89 -> 57254 | Q89: =P89 -> 57254 | R89: =Q89 -> 57254
B90: Total Current Liabilities | C90: =IFERROR(SUM(C84:C89),0) -> 63448 | D90: =IFERROR(SUM(D84:D89),0) -> 80610 | E90: =IFERROR(SUM(E84:E89),0) -> 79006 | F90: =IFERROR(SUM(F84:F89),0) -> 100814 | G90: =IFERROR(SUM(G84:G89),0) -> 115929 | H90: =IFERROR(SUM(H84:H89),0) -> 105718 | I90: =IFERROR(SUM(I84:I89),0) -> 105392 | J90: =IFERROR(SUM(J84:J89),0) -> 125481 | ... R90: =IFERROR(SUM(R84:R89),0) -> 180003.8
B92: Long-Term Debt | C92: =IFERROR('Data Sheet'!B163,0) -> 28987 | D92: =IFERROR('Data Sheet'!C163,0) -> 53329 | E92: =IFERROR('Data Sheet'!D163,0) -> 75427 | F92: =IFERROR('Data Sheet'!E163,0) -> 97207 | G92: =IFERROR('Data Sheet'!F163,0) -> 93735 | H92: =IFERROR('Data Sheet'!G163,0) -> 91807 | I92: =IFERROR('Data Sheet'!H163,0) -> 98667 | J92: =IFERROR('Data Sheet'!I163,0) -> 109106 | ... M92: =IFERROR('Data Sheet'!L163,0) -> 95088 | N92: =L92 -> 95281 | O92: =N92 -> 95281 | P92: =O92*(1+P9) -> 105761.91 | Q92: =P92*(1+Q9) -> 117924.53 | R92: =Q92*(1+R9) -> 132075.47
B93: Long-Term Leases | C93: =IFERROR('Data Sheet'!B164,0) -> - | D93: =IFERROR('Data Sheet'!C164,0) -> - | E93: =IFERROR('Data Sheet'!D164,0) -> - | F93: =IFERROR('Data Sheet'!E164,0) -> - | G93: =IFERROR('Data Sheet'!F164,0) -> - | H93: =IFERROR('Data Sheet'!G164,0) -> - | I93: =IFERROR('Data Sheet'!H164,0) -> 8382 | J93: =IFERROR('Data Sheet'!I164,0) -> 10275 | ... M93: =IFERROR('Data Sheet'!L164,0) -> - | N93: =L93 -> 11267 | O93: =N93 -> 11267 | P93: =O93 -> 11267 | Q93: =P93 -> 11267 | R93: =Q93 -> 11267
B94: Unearned Revenue, Non-Current | C94: =IFERROR('Data Sheet'!B165,0) -> 3031 | D94: =IFERROR('Data Sheet'!C165,0) -> 3624 | E94: =IFERROR('Data Sheet'!D165,0) -> 2930 | F94: =IFERROR('Data Sheet'!E165,0) -> 2836 | G94: =IFERROR('Data Sheet'!F165,0) -> - | H94: =IFERROR('Data Sheet'!G165,0) -> - | I94: =IFERROR('Data Sheet'!H165,0) -> - | J94: =IFERROR('Data Sheet'!I165,0) -> - | ... M94: =IFERROR('Data Sheet'!L165,0) -> - | N94: - | O94: - | P94: - | Q94: - | R94: -
B95: Def. Tax Liability, Non-Curr. | C95: =IFERROR('Data Sheet'!B166,0) -> 20259 | D95: =IFERROR('Data Sheet'!C166,0) -> 24062 | E95: =IFERROR('Data Sheet'!D166,0) -> 26019 | F95: =IFERROR('Data Sheet'!E166,0) -> 31504 | G95: =IFERROR('Data Sheet'!F166,0) -> - | H95: =IFERROR('Data Sheet'!G166,0) -> - | I95: =IFERROR('Data Sheet'!H166,0) -> - | J95: =IFERROR('Data Sheet'!I166,0) -> - | ... M95: =IFERROR('Data Sheet'!L166,0) -> - | N95: - | O95: - | P95: - | Q95: - | R95: -
B96: Other Non-Current Liabilities | C96: =IFERROR('Data Sheet'!B167,0) -> 4567 | D96: =IFERROR('Data Sheet'!C167,0) -> 9365 | E96: =IFERROR('Data Sheet'!D167,0) -> 10055 | F96: =IFERROR('Data Sheet'!E167,0) -> 8911 | G96: =IFERROR('Data Sheet'!F167,0) -> 48914 | H96: =IFERROR('Data Sheet'!G167,0) -> 50503 | I96: =IFERROR('Data Sheet'!H167,0) -> 46108 | J96: =IFERROR('Data Sheet'!I167,0) -> 43050 | ... M96: =IFERROR('Data Sheet'!L167,0) -> 50353 | N96: =L96 -> 38581 | O96: =N96 -> 38581 | P96: =O96 -> 38581 | Q96: =P96 -> 38581 | R96: =Q96 -> 38581
B97: Total Non-Current Liabilities | C97: =IFERROR(SUM(C92:C96),0) -> 56844 | D97: =IFERROR(SUM(D92:D96),0) -> 90380 | E97: =IFERROR(SUM(E92:E96),0) -> 114431 | F97: =IFERROR(SUM(F92:F96),0) -> 140458 | G97: =IFERROR(SUM(G92:G96),0) -> 142649 | H97: =IFERROR(SUM(H92:H96),0) -> 142310 | I97: =IFERROR(SUM(I92:I96),0) -> 153157 | J97: =IFERROR(SUM(J92:J96),0) -> 162431 | ... R97: =IFERROR(SUM(R92:R96),0) -> 181923.47
B98: Total Liabilities | C98: =IFERROR(C97+C90,0) -> 120292 | D98: =IFERROR(D97+D90,0) -> 170990 | E98: =IFERROR(E97+E90,0) -> 193437 | F98: =IFERROR(F97+F90,0) -> 241272 | G98: =IFERROR(G97+G90,0) -> 258578 | H98: =IFERROR(H97+H90,0) -> 248028 | I98: =IFERROR(I97+I90,0) -> 258549 | J98: =IFERROR(J97+J90,0) -> 287912 | ... R98: =IFERROR(R97+R90,0) -> 361927.27
B100: Common Stock | C100: =IFERROR('Data Sheet'!B170,0) -> 23313 | D100: =IFERROR('Data Sheet'!C170,0) -> 27416 | E100: =IFERROR('Data Sheet'!D170,0) -> 31251 | F100: =IFERROR('Data Sheet'!E170,0) -> 35867 | G100: =IFERROR('Data Sheet'!F170,0) -> 40201 | H100: =IFERROR('Data Sheet'!G170,0) -> 45174 | I100: =IFERROR('Data Sheet'!H170,0) -> 50779 | J100: =IFERROR('Data Sheet'!I170,0) -> 57365 | ... M100: =IFERROR('Data Sheet'!L170,0) -> 75236 | N100: =L100*(1+12%) -> 82669.44 | O100: =N100*(12%+1) -> 92589.773 | P100: =O100*(12%+1) -> 103700.55 | Q100: =P100*(12%+1)+15000 -> 131144.61 | R100: =Q100*(12%+1)+15000 -> 161881.96
B101: Additional Paid In Capital | C101: =IFERROR('Data Sheet'!B171,0) -> - | D101: =IFERROR('Data Sheet'!C171,0) -> - | E101: =IFERROR('Data Sheet'!D171,0) -> - | F101: =IFERROR('Data Sheet'!E171,0) -> - | G101: =IFERROR('Data Sheet'!F171,0) -> - | H101: =IFERROR('Data Sheet'!G171,0) -> - | I101: =IFERROR('Data Sheet'!H171,0) -> - | J101: =IFERROR('Data Sheet'!I171,0) -> - | ... M101: =IFERROR('Data Sheet'!L171,0) -> - | N101: - | O101: - | P101: - | Q101: - | R101: -
B102: Retained Earnings | C102: =IFERROR('Data Sheet'!B172,0) -> 87152 | D102: =IFERROR('Data Sheet'!C172,0) -> 92284 | E102: =IFERROR('Data Sheet'!D172,0) -> 96364 | F102: =IFERROR('Data Sheet'!E172,0) -> 98330 | G102: =IFERROR('Data Sheet'!F172,0) -> 70400 | H102: =IFERROR('Data Sheet'!G172,0) -> 45898 | I102: =IFERROR('Data Sheet'!H172,0) -> 14966 | J102: =IFERROR('Data Sheet'!I172,0) -> 5562 | ... M102: =IFERROR('Data Sheet'!L172,0) -> 8242 | N102: =MEDIAN(C102:L102)-38692 -> 19457 | O102: =58149-11960 -> 46189 | P102: =O102+21274 -> 67463 | Q102: =P102+12141 -> 79604 | R102: =Q102+16315 -> 95919
B103: Treasury Stock | C103: =IFERROR('Data Sheet'!B173,0) -> - | D103: =IFERROR('Data Sheet'!C173,0) -> - | E103: =IFERROR('Data Sheet'!D173,0) -> - | F103: =IFERROR('Data Sheet'!E173,0) -> - | G103: =IFERROR('Data Sheet'!F173,0) -> - | H103: =IFERROR('Data Sheet'!G173,0) -> - | I103: =IFERROR('Data Sheet'!H173,0) -> - | J103: =IFERROR('Data Sheet'!I173,0) -> - | ... M103: =IFERROR('Data Sheet'!L173,0) -> - | N103: - | O103: - | P103: - | Q103: - | R103: -
B104: Comprehensive Inc. and Other | C104: =IFERROR('Data Sheet'!B174,0) -> 1082 | D104: =IFERROR('Data Sheet'!C174,0) -> -345 | E104: =IFERROR('Data Sheet'!D174,0) -> 634 | F104: =IFERROR('Data Sheet'!E174,0) -> -150 | G104: =IFERROR('Data Sheet'!F174,0) -> -3454 | H104: =IFERROR('Data Sheet'!G174,0) -> -584 | I104: =IFERROR('Data Sheet'!H174,0) -> -406 | J104: =IFERROR('Data Sheet'!I174,0) -> 163 | ... M104: =IFERROR('Data Sheet'!L174,0) -> -9378 | N104: =L104 -> -11452 | O104: =N104 -> -11452 | P104: =O104 -> -11452 | Q104: =P104 -> -11452 | R104: =Q104 -> -11452
B105: Total Common Equity | C105: =IFERROR(SUM(C100:C104),0) -> 111547 | D105: =IFERROR(SUM(D100:D104),0) -> 119355 | E105: =IFERROR(SUM(E100:E104),0) -> 128249 | F105: =IFERROR(SUM(F100:F104),0) -> 134047 | G105: =IFERROR(SUM(G100:G104),0) -> 107147 | H105: =IFERROR(SUM(H100:H104),0) -> 90488 | I105: =IFERROR(SUM(I100:I104),0) -> 65339 | J105: =IFERROR(SUM(J100:J104),0) -> 63090 | ... R105: =IFERROR(SUM(R100:R104),0) -> 246348.96
B106: Total Equity | C106: =IFERROR(C105,0) -> 111547 | D106: =IFERROR(D105,0) -> 119355 | E106: =IFERROR(E105,0) -> 128249 | F106: =IFERROR(F105,0) -> 134047 | G106: =IFERROR(G105,0) -> 107147 | H106: =IFERROR(H105,0) -> 90488 | I106: =IFERROR(I105,0) -> 65339 | J106: =IFERROR(J105,0) -> 63090 | ... R106: =IFERROR(R105,0) -> 246348.96
B107: Total Liabilities And Equity | C107: =IFERROR(C106+C98,0) -> 231839 | D107: =IFERROR(D106+D98,0) -> 290345 | E107: =IFERROR(E106+E98,0) -> 321686 | F107: =IFERROR(F106+F98,0) -> 375319 | G107: =IFERROR(G106+G98,0) -> 365725 | H107: =IFERROR(H106+H98,0) -> 338516 | I107: =IFERROR(I106+I98,0) -> 323888 | J107: =IFERROR(J106+J98,0) -> 351002 | ... R107: =IFERROR(R106+R98,0) -> 608276.23
B109: Check if A=L&E | C109: =IFERROR(C107=C82,0) -> TRUE | D109: =IFERROR(D107=D82,0) -> TRUE | E109: =IFERROR(E107=E82,0) -> TRUE | F109: =IFERROR(F107=F82,0) -> TRUE | G109: =IFERROR(G107=G82,0) -> TRUE | H109: =IFERROR(H107=H82,0) -> TRUE | I109: =IFERROR(I107=I82,0) -> TRUE | J109: =IFERROR(J107=J82,0) -> TRUE | ... M109: =IFERROR(M107=M82,0) -> TRUE | N109: TRUE | O109: TRUE | P109: TRUE | Q109: TRUE | R109: TRUE
B111: in millions ($)
B112: ="Historical Financial Statement -"&'Data Sheet'!$A$4 -> Historical Financial Statement -Apple Inc. | N112: ="Forecasted Financial Statement " & "-" &'Data Sheet'!$A$4 -> Forecasted Financial Statement -Apple Inc.
B113: Years | C113: 2014 | D113: =C113+1 -> 2015 | E113: =D113+1 -> 2016 | F113: =E113+1 -> 2017 | G113: =F113+1 -> 2018 | H113: 2019 | I113: =H113+1 -> 2020 | J113: =I113+1 -> 2021 | K113: =J113+1 -> 2022 | L113: =K113+1 -> 2023 | M113: LTM | N113: =L113+1 -> 2024 | O113: =N113+1 -> 2025 | P113: =O113+1 -> 2026 | Q113: =P113+1 -> 2027 | R113: =Q113+1 -> 2028
A114: # | B114: Statement of Cashflow
B115: Net Income | C115: =IFERROR(C47,0) -> 39510 | D115: =IFERROR(D47,0) -> 53394 | E115: =IFERROR(E47,0) -> 45687 | F115: =IFERROR(F47,0) -> 48351 | G115: =IFERROR(G47,0) -> 59531 | H115: =IFERROR(H47,0) -> 55256 | I115: =IFERROR(I47,0) -> 57411 | J115: =IFERROR(J47,0) -> 94680 | ... M115: =IFERROR(M47,0) -> 100913 | N115: =N47 -> 107266.32 | O115: =O47 -> 119206.17 | P115: =P47 -> 134120.01 | Q115: =Q47 -> 152062.63 | R115: =R47 -> 173585.88
B116: (+)Depreciation & Amort. | C116: =IFERROR(C38,0) -> 6846 | D116: =IFERROR(D38,0) -> 9957 | E116: =IFERROR(E38,0) -> 10505 | F116: =IFERROR(F38,0) -> 10157 | G116: =IFERROR(G38,0) -> 10903 | H116: =IFERROR(H38,0) -> 12547 | I116: =IFERROR(I38,0) -> 11056 | J116: =IFERROR(J38,0) -> 11284 | ... M116: =IFERROR(M38,0) -> 11451 | N116: =N38 -> 12531.867 | O116: =O38 -> 12885.333 | P116: =P38 -> 13238.8 | Q116: =Q38 -> 13592.267 | R116: =R38 -> 13945.733
B117: (+) Amort. Of Goodwill & Intangibles | C117: =IFERROR('Data Sheet'!B217,0) -> 1100 | D117: =IFERROR('Data Sheet'!C217,0) -> 1300 | E117: =IFERROR('Data Sheet'!D217,0) -> - | F117: =IFERROR('Data Sheet'!E217,0) -> - | G117: =IFERROR('Data Sheet'!F217,0) -> - | H117: =IFERROR('Data Sheet'!G217,0) -> - | I117: =IFERROR('Data Sheet'!H217,0) -> - | J117: =IFERROR('Data Sheet'!I217,0) -> - | ... M117: =IFERROR('Data Sheet'!L217,0) -> - | N117: - | O117: - | P117: - | Q117: - | R117: -
B118: Stock-Based Compensation | C118: ='Data Sheet'!B220 -> 2863 | D118: ='Data Sheet'!C220 -> 3586 | E118: ='Data Sheet'!D220 -> 4210 | F118: ='Data Sheet'!E220 -> 4840 | G118: ='Data Sheet'!F220 -> 5340 | H118: ='Data Sheet'!G220 -> 6068 | I118: ='Data Sheet'!H220 -> 6829 | J118: ='Data Sheet'!I220 -> 7906 | ... M118: ='Data Sheet'!L220 -> 10925 | N118: =N8*(L118/L8) -> 11591.31 | O118: =O8*(N118/N8) -> 12750.441 | P118: =P8*(O118/O8) -> 14152.99 | Q118: =Q8*(P118/P8) -> 15780.583 | R118: =R8*(Q118/Q8) -> 17674.253
B119: Other Operating Activities | C119: ='Data Sheet'!B221 -> 2347 | D119: ='Data Sheet'!C221 -> 1767 | E119: ='Data Sheet'!D221 -> 5424 | F119: ='Data Sheet'!E221 -> 5800 | G119: ='Data Sheet'!F221 -> -33034 | H119: ='Data Sheet'!G221 -> -992 | I119: ='Data Sheet'!H221 -> -312 | J119: ='Data Sheet'!I221 -> -4921 | ... M119: ='Data Sheet'!L221 -> -2899 | N119: - | O119: - | P119: - | Q119: - | R119: -
B120: Changes in Working Capital:
B121: Change in Acc. Receivable | C121: ='Data Sheet'!B222 -> -4232 | D121: ='Data Sheet'!C222 -> 417 | E121: ='Data Sheet'!D222 -> 527 | F121: ='Data Sheet'!E222 -> -2093 | G121: ='Data Sheet'!F222 -> -5322 | H121: ='Data Sheet'!G222 -> 245 | I121: ='Data Sheet'!H222 -> 6917 | J121: ='Data Sheet'!I222 -> -10125 | ... M121: ='Data Sheet'!L222 -> 592 | N121: =(N67+N68)-(L67+L68) -> 4268.95 | O121: =O67+O68-(N67+N68) -> 6525.395 | P121: =P67+P68-(O67+O68) -> 7895.728 | Q121: =Q67+Q68-(P67+P68) -> 9162.6334 | R121: =R67+R68-(Q67+Q68) -> 10660.525
B122: Change In Inventories | C122: ='Data Sheet'!B223 -> -76 | D122: ='Data Sheet'!C223 -> -238 | E122: ='Data Sheet'!D223 -> 217 | F122: ='Data Sheet'!E223 -> -2723 | G122: ='Data Sheet'!F223 -> 828 | H122: ='Data Sheet'!G223 -> -289 | I122: ='Data Sheet'!H223 -> -127 | J122: ='Data Sheet'!I223 -> -2642 | ... M122: ='Data Sheet'!L223 -> 52 | N122: =N70-L70 -> 386.31888 | O122: =O70-N70 -> 671.73189 | P122: =P70-O70 -> -1289.0508 | Q122: =Q70-P70 -> 156 | R122: =R70-Q70 -> 750.72
B123: Change in Acc. Payable | C123: ='Data Sheet'!B224 -> 5938 | D123: ='Data Sheet'!C224 -> 5001 | E123: ='Data Sheet'!D224 -> 2117 | F123: ='Data Sheet'!E224 -> 8966 | G123: ='Data Sheet'!F224 -> 9175 | H123: ='Data Sheet'!G224 -> -1923 | I123: ='Data Sheet'!H224 -> -4062 | J123: ='Data Sheet'!I224 -> 12326 | ... M123: ='Data Sheet'!L224 -> -356 | N123: =N84-L84 -> 3820.5357 | O123: =O84-N84 -> 6643.1536 | P123: =P84-O84 -> 8038.2158 | Q123: =Q84-P84 -> 9327.9841 | R123: =R84-Q84 -> 10852.907
B124: Change in Unearned Rev. | C124: ='Data Sheet'!B225 -> 1460 | D124: ='Data Sheet'!C225 -> 1042 | E124: ='Data Sheet'!D225 -> -1554 | F124: ='Data Sheet'!E225 -> -593 | G124: ='Data Sheet'!F225 -> -3 | H124: ='Data Sheet'!G225 -> -625 | I124: ='Data Sheet'!H225 -> 2081 | J124: ='Data Sheet'!I225 -> - | ... M124: ='Data Sheet'!L225 -> - | N124: =N88-L88 -> 0 | O124: =O88-N88 -> 0 | P124: =P88-O88 -> 0 | Q124: =Q88-P88 -> 0 | R124: =R88-Q88 -> 0
B125: Change in Other Net Operating Assets | C125: ='Data Sheet'!B226 -> 3957 | D125: ='Data Sheet'!C226 -> 5040 | E125: ='Data Sheet'!D226 -> -902 | F125: ='Data Sheet'!E226 -> -8480 | G125: ='Data Sheet'!F226 -> 30016 | H125: ='Data Sheet'!G226 -> -896 | I125: ='Data Sheet'!H226 -> 881 | J125: ='Data Sheet'!I226 -> -4470 | ... M125: ='Data Sheet'!L226 -> -4245 | N125: =N71-L71 -> 1028.65 | O125: =O71-N71 -> 1572.365 | P125: =P71-O71 -> 1902.5617 | Q125: =Q71-P71 -> 2207.8363 | R125: =R71-Q71 -> 2568.7696
B126: Cashflow from Operating activities | C126: =SUM(C115:C125) -> 59713 | D126: =SUM(D115:D125) -> 81266 | E126: =SUM(E115:E125) -> 66231 | F126: =SUM(F115:F125) -> 64225 | G126: =SUM(G115:G125) -> 77434 | H126: =SUM(H115:H125) -> 69391 | I126: =SUM(I115:I125) -> 80674 | J126: =SUM(J115:J125) -> 104038 | ... M126: =SUM(M115:M125) -> 116433 | N126: =N115+N116-N121-N122+N123-N124-N125+N118 -> 129526.12 | O126: =O115+O116-O121-O122+O123-O124-O125+O118 -> 142715.6 | P126: =P115+P116-P121-P122+P123-P124-P125+P118 -> 161040.78 | Q126: =Q115+Q116-Q121-Q122+Q123-Q124-Q125+Q118 -> 179236.99 | R126: =R115+R116-R121-R122+R123-R124-R125+R118 -> 202078.76
B128: Capital Expenditure | C128: =IFERROR('Data Sheet'!B229,0) -> -9571 | D128: =IFERROR('Data Sheet'!C229,0) -> -11247 | E128: =IFERROR('Data Sheet'!D229,0) -> -12734 | F128: =IFERROR('Data Sheet'!E229,0) -> -12451 | G128: =IFERROR('Data Sheet'!F229,0) -> -13313 | H128: =IFERROR('Data Sheet'!G229,0) -> -10495 | I128: =IFERROR('Data Sheet'!H229,0) -> -7309 | J128: =IFERROR('Data Sheet'!I229,0) -> -11085 | ... M128: =IFERROR('Data Sheet'!L229,0) -> -9564 | N128: -11258 | O128: -12768 | P128: -13282 | Q128: -15576 | R128: -18765
...

Sheet Specific Forecasts
B6: ="Sales Forecasting -"&'Data Sheet'!$A$4 -> Sales Forecasting -Apple Inc. | G6: ="EBITDA Forecasting -"&'Data Sheet'!$A$4 -> EBITDA Forecasting -Apple Inc. | L6: ="EPS Forecasting -"&'Data Sheet'!$A$4 -> EPS Forecasting -Apple Inc.
B7: Year Weight | C7: Year | D7: Sales | E7: Sales Growth | G7: Year Weight | H7: Year | I7: Sales | J7: EBITDA Growth | L7: Year Weight | M7: Year | N7: Sales | O7: EPS Growth
B8: 1 | C8: 2014 | D8: {=TRANSPOSE('Historical & Forecasted FS'!C8:L8)} -> 182795 | G8: 1 | H8: 2014 | I8: {=TRANSPOSE('Historical & Forecasted FS'!C29:L29)} -> 59349 | L8: 1 | M8: 2014 | N8: {=TRANSPOSE('Historical & Forecasted FS'!C52:L52)} -> 1.6838099
B9: =B8+1 -> 2 | C9: =C8+1 -> 2015 | D9: 233715 | E9: =D9/D8-1 -> 0.27856342 | G9: =G8+1 -> 2 | H9: =H8+1 -> 2015 | I9: 81187 | J9: =I9/I8-1 -> 0.36795902 | L9: =L8+1 -> 2 | M9: =M8+1 -> 2015 | N9: 2.392739 | O9: =N9/N8-1 -> 0.42102681
B10: =B9+1 -> 3 | C10: =C9+1 -> 2016 | D10: 215639 | E10: =D10/D9-1 -> -0.077342062 | G10: =G9+1 -> 3 | H10: =H9+1 -> 2016 | I10: 70529 | J10: =I10/I9-1 -> -0.13127717 | L10: =L9+1 -> 3 | M10: =M9+1 -> 2016 | N10: 2.1404413 | O10: =N10/N9-1 -> -0.10544307
B11: =B10+1 -> 4 | C11: =C10+1 -> 2017 | D11: 229234 | E11: =D11/D10-1 -> 0.063045182 | G11: =G10+1 -> 4 | H11: =H10+1 -> 2017 | I11: 71501 | J11: =I11/I10-1 -> 0.013781565 | L11: =L10+1 -> 4 | M11: =M10+1 -> 2017 | N11: 2.3580328 | O11: =N11/N10-1 -> 0.10165731
B12: =B11+1 -> 5 | C12: =C11+1 -> 2018 | D12: 265595 | E12: =D12/D11-1 -> 0.15861958 | G12: =G11+1 -> 5 | H12: =H11+1 -> 2018 | I12: 81801 | J12: =I12/I11-1 -> 0.14405393 | L12: =L11+1 -> 5 | M12: =M11+1 -> 2018 | N12: 3.1299251 | O12: =N12/N11-1 -> 0.32734588
B13: =B12+1 -> 6 | C13: =C12+1 -> 2019 | D13: 260174 | E13: =D13/D12-1 -> -0.020410776 | G13: =G12+1 -> 6 | H13: =H12+1 -> 2019 | I13: 76477 | J13: =I13/I12-1 -> -0.065084779 | L13: =L12+1 -> 6 | M13: =M12+1 -> 2019 | N13: 3.1089953 | O13: =N13/N12-1 -> -0.0066869835
B14: =B13+1 -> 7 | C14: =C13+1 -> 2020 | D14: 274515 | E14: =D14/D13-1 -> 0.055120804 | G14: =G13+1 -> 7 | H14: =H13+1 -> 2020 | I14: 77344 | J14: =I14/I13-1 -> 0.011336742 | L14: =L13+1 -> 7 | M14: =M13+1 -> 2020 | N14: 3.3817401 | O14: =N14/N13-1 -> 0.087727617
B15: =B14+1 -> 8 | C15: =C14+1 -> 2021 | D15: 365817 | E15: =D15/D14-1 -> 0.33259385 | G15: =G14+1 -> 8 | H15: =H14+1 -> 2021 | I15: 120233 | J15: =I15/I14-1 -> 0.55452265 | L15: =L14+1 -> 8 | M15: =M14+1 -> 2021 | N15: 5.7637568 | O15: =N15/N14-1 -> 0.70437605
B16: =B15+1 -> 9 | C16: =C15+1 -> 2022 | D16: 394328 | E16: =D16/D15-1 -> 0.077937876 | G16: =G15+1 -> 9 | H16: =H15+1 -> 2022 | I16: 130541 | J16: =I16/I15-1 -> 0.085733534 | L16: =L15+1 -> 9 | M16: =M15+1 -> 2022 | N16: 6.2598218 | O16: =N16/N15-1 -> 0.086066263
B17: =B16+1 -> 10 | C17: =C16+1 -> 2023 | D17: 383285 | E17: =D17/D16-1 -> -0.028004605 | G17: =G16+1 -> 10 | H17: =H16+1 -> 2023 | I17: 125820 | J17: =I17/I16-1 -> -0.036164883 | L17: =L16+1 -> 10 | M17: =M16+1 -> 2023 | N17: 6.2375961 | O17: =N17/N16-1 -> -0.003550537
B18: 11 | C18: 2024 | D18: =FORECAST(B18,$D$8:$D$17,$B$8:$B$17) -> 407510.13 | E18: =D18/D17-1 -> 0.063203969 | G18: 11 | H18: 2024 | I18: =FORECAST(G18,$I$8:$I$17,$G$8:$G$17) -> 129626.27 | J18: =I18/I17-1 -> 0.030251682 | L18: 11 | M18: 2024 | N18: =FORECAST(L18,$N$8:$N$17,$L$8:$L$17) -> 6.6197 | O18: =N18/N17-1 -> 0.061258198
B19: 12 | C19: 2025 | D19: =FORECAST(B19,$D$8:$D$17,$B$8:$B$17) -> 430601.12 | E19: =D19/D18-1 -> 0.056663592 | G19: 12 | H19: 2025 | I19: =FORECAST(G19,$I$8:$I$17,$G$8:$G$17) -> 136925.92 | J19: =I19/I18-1 -> 0.056313035 | L19: 12 | M19: 2025 | N19: =FORECAST(L19,$N$8:$N$17,$L$8:$L$17) -> 7.1604299 | O19: =N19/N18-1 -> 0.081684948
B20: 13 | C20: 2026 | D20: =FORECAST(B20,$D$8:$D$17,$B$8:$B$17) -> 453692.11 | E20: =D20/D19-1 -> 0.053625006 | G20: 13 | H20: 2026 | I20: =FORECAST(G20,$I$8:$I$17,$G$8:$G$17) -> 144225.56 | J20: =I20/I19-1 -> 0.053310934 | L20: 13 | M20: 2026 | N20: =FORECAST(L20,$N$8:$N$17,$L$8:$L$17) -> 7.7011597 | O20: =N20/N19-1 -> 0.075516395
B21: 14 | C21: 2027 | D21: =FORECAST(B21,$D$8:$D$17,$B$8:$B$17) -> 476783.1 | E21: =D21/D20-1 -> 0.050895723 | G21: 14 | H21: 2027 | I21: =FORECAST(G21,$I$8:$I$17,$G$8:$G$17) -> 151525.21 | J21: =I21/I20-1 -> 0.050612723 | L21: 14 | M21: 2027 | N21: =FORECAST(L21,$N$8:$N$17,$L$8:$L$17) -> 8.2418896 | O21: =N21/N20-1 -> 0.070214081
B22: 15 | C22: 2028 | D22: =FORECAST(B22,$D$8:$D$17,$B$8:$B$17) -> 499874.08 | E22: =D22/D21-1 -> 0.048430802 | G22: 15 | H22: 2028 | I22: =FORECAST(G22,$I$8:$I$17,$G$8:$G$17) -> 158824.86 | J22: =I22/I21-1 -> 0.048174481 | L22: 15 | M22: 2028 | N22: =FORECAST(L22,$N$8:$N$17,$L$8:$L$17) -> 8.7826194 | O22: =N22/N21-1 -> 0.06560751

Sheet Ratio Analysis
B6: ="Ratio Analysis -"&'Data Sheet'!A4 -> Ratio Analysis -Apple Inc. | N6: Based on FY - 10 year | P6: Apple Inc. Based on FY - 5year | Q6: S&P 500 - IT sector Based on CY - 5year
B7: Years | C7: 2014 | D7: =C7+1 -> 2015 | E7: =D7+1 -> 2016 | F7: =E7+1 -> 2017 | G7: =F7+1 -> 2018 | H7: 2019 | I7: =H7+1 -> 2020 | J7: =I7+1 -> 2021 | K7: =J7+1 -> 2022 | L7: =K7+1 -> 2023 | N7: Mean | O7: Median | P7: Mean | Q7: Mean
B9: ="Sales" & " " & "Growth" -> Sales Growth | C9: - | D9: =IFERROR('Historical & Forecasted FS'!D9,0) -> 0.27856342 | E9: =IFERROR('Historical & Forecasted FS'!E9,0) -> -0.077342062 | F9: =IFERROR('Historical & Forecasted FS'!F9,0) -> 0.063045182 | G9: =IFERROR('Historical & Forecasted FS'!G9,0) -> 0.15861958 | H9: =IFERROR('Historical & Forecasted FS'!H9,0) -> -0.020410776 | I9: =IFERROR('Historical & Forecasted FS'!I9,0) -> 0.055120804 | J9: =IFERROR('Historical & Forecasted FS'!J9,0) -> 0.33259385 | K9: =IFERROR('Historical & Forecasted FS'!K9,0) -> 0.077937876 | L9: =IFERROR('Historical & Forecasted FS'!L9,0) -> -0.028004605 | N9: =IFERROR(AVERAGE(D9:L9),0) -> 0.093347029 | O9: =IFERROR(MEDIAN(D9:L9),0) -> 0.063045182 | P9: =AVERAGE(H9:L9) -> 0.083447429 | Q9: 0.0878
B10: ="EBITDA" & " " & "Growth" -> EBITDA Growth | C10: - | D10: =IFERROR('Historical & Forecasted FS'!D29/'Historical & Forecasted FS'!C29-1,0) -> 0.36795902 | E10: =IFERROR('Historical & Forecasted FS'!E29/'Historical & Forecasted FS'!D29-1,0) -> -0.13127717 | F10: =IFERROR('Historical & Forecasted FS'!F29/'Historical & Forecasted FS'!E29-1,0) -> 0.013781565 | G10: =IFERROR('Historical & Forecasted FS'!G29/'Historical & Forecasted FS'!F29-1,0) -> 0.14405393 | H10: =IFERROR('Historical & Forecasted FS'!H29/'Historical & Forecasted FS'!G29-1,0) -> -0.065084779 | I10: =IFERROR('Historical & Forecasted FS'!I29/'Historical & Forecasted FS'!H29-1,0) -> 0.011336742 | J10: =IFERROR('Historical & Forecasted FS'!J29/'Historical & Forecasted FS'!I29-1,0) -> 0.55452265 | K10: =IFERROR('Historical & Forecasted FS'!K29/'Historical & Forecasted FS'!J29-1,0) -> 0.085733534 | L10: =IFERROR('Historical & Forecasted FS'!L29/'Historical & Forecasted FS'!K29-1,0) -> -0.036164883 | N10: =IFERROR(AVERAGE(D10:L10),0) -> 0.10498451 | O10: =IFERROR(MEDIAN(D10:L10),0) -> 0.013781565 | P10: =AVERAGE(H10:L10) -> 0.11006865 | Q10: 0.0974
B11: ="EBIT" & " " & "Growth" -> EBIT Growth | C11: - | D11: =IFERROR('Historical & Forecasted FS'!D23/'Historical & Forecasted FS'!C23-1,0) -> 0.35668438 | E11: =IFERROR('Historical & Forecasted FS'!E23/'Historical & Forecasted FS'!D23-1,0) -> -0.15732135 | F11: =IFERROR('Historical & Forecasted FS'!F23/'Historical & Forecasted FS'!E23-1,0) -> 0.021991204 | G11: =IFERROR('Historical & Forecasted FS'!G23/'Historical & Forecasted FS'!F23-1,0) -> 0.15574465 | H11: =IFERROR('Historical & Forecasted FS'!H23/'Historical & Forecasted FS'!G23-1,0) -> -0.098282039 | I11: =IFERROR('Historical & Forecasted FS'!I23/'Historical & Forecasted FS'!H23-1,0) -> 0.036884092 | J11: =IFERROR('Historical & Forecasted FS'!J23/'Historical & Forecasted FS'!I23-1,0) -> 0.64357048 | K11: =IFERROR('Historical & Forecasted FS'!K23/'Historical & Forecasted FS'!J23-1,0) -> 0.096265225 | L11: =IFERROR('Historical & Forecasted FS'!L23/'Historical & Forecasted FS'!K23-1,0) -> -0.04300175 | N11: =IFERROR(AVERAGE(D11:L11),0) -> 0.11250388 | O11: =IFERROR(MEDIAN(D11:L11),0) -> 0.036884092 | P11: =AVERAGE(H11:L11) -> 0.1270872 | Q11: 0.1016
B12: ="Net Profit" & " " & "Growth" -> Net Profit Growth | C12: - | D12: =IFERROR('Historical & Forecasted FS'!D47/'Historical & Forecasted FS'!C47-1,0) -> 0.35140471 | E12: =IFERROR('Historical & Forecasted FS'!E47/'Historical & Forecasted FS'!D47-1,0) -> -0.14434206 | F12: =IFERROR('Historical & Forecasted FS'!F47/'Historical & Forecasted FS'!E47-1,0) -> 0.058309804 | G12: =IFERROR('Historical & Forecasted FS'!G47/'Historical & Forecasted FS'!F47-1,0) -> 0.23122583 | H12: =IFERROR('Historical & Forecasted FS'!H47/'Historical & Forecasted FS'!G47-1,0) -> -0.071811325 | I12: =IFERROR('Historical & Forecasted FS'!I47/'Historical & Forecasted FS'!H47-1,0) -> 0.03900029 | J12: =IFERROR('Historical & Forecasted FS'!J47/'Historical & Forecasted FS'!I47-1,0) -> 0.64916131 | K12: =IFERROR('Historical & Forecasted FS'!K47/'Historical & Forecasted FS'!J47-1,0) -> 0.054108576 | L12: =IFERROR('Historical & Forecasted FS'!L47/'Historical & Forecasted FS'!K47-1,0) -> -0.028135427 | N12: =IFERROR(AVERAGE(D12:L12),0) -> 0.12654686 | O12: =IFERROR(MEDIAN(D12:L12),0) -> 0.054108576 | P12: =AVERAGE(H12:L12) -> 0.12846468 | Q12: 0.1037
B13: ="Dividend" & " " & "Growth" -> Dividend Growth | C13: - | D13: =IFERROR('Historical & Forecasted FS'!D55/'Historical & Forecasted FS'!C55-1,0) -> 0.086956522 | E13: =IFERROR('Historical & Forecasted FS'!E55/'Historical & Forecasted FS'!D55-1,0) -> 0.1 | F13: =IFERROR('Historical & Forecasted FS'!F55/'Historical & Forecasted FS'!E55-1,0) -> 0.090909091 | G13: =IFERROR('Historical & Forecasted FS'!G55/'Historical & Forecasted FS'!F55-1,0) -> 0.13333333 | H13: =IFERROR('Historical & Forecasted FS'!H55/'Historical & Forecasted FS'!G55-1,0) -> 0.10294118 | I13: =IFERROR('Historical & Forecasted FS'!I55/'Historical & Forecasted FS'!H55-1,0) -> 0.066666667 | J13: =IFERROR('Historical & Forecasted FS'!J55/'Historical & Forecasted FS'!I55-1,0) -> 0.0625 | K13: =IFERROR('Historical & Forecasted FS'!K55/'Historical & Forecasted FS'!J55-1,0) -> 0.058823529 | L13: =IFERROR('Historical & Forecasted FS'!L55/'Historical & Forecasted FS'!K55-1,0) -> 0.044444444 | N13: =IFERROR(AVERAGE(D13:L13),0) -> 0.082952751 | O13: =IFERROR(MEDIAN(D13:L13),0) -> 0.086956522 | P13: =AVERAGE(H13:L13) -> 0.067075163
B15: ="Gross" & " " & "Margin" -> Gross Margin | C15: =IFERROR('Historical & Forecasted FS'!C15,0) -> 0.38588036 | D15: =IFERROR('Historical & Forecasted FS'!D15,0) -> 0.40059902 | E15: =IFERROR('Historical & Forecasted FS'!E15,0) -> 0.39075956 | F15: =IFERROR('Historical & Forecasted FS'!F15,0) -> 0.3846986 | G15: =IFERROR('Historical & Forecasted FS'!G15,0) -> 0.38343719 | H15: =IFERROR('Historical & Forecasted FS'!H15,0) -> 0.37817768 | I15: =IFERROR('Historical & Forecasted FS'!I15,0) -> 0.38233248 | J15: =IFERROR('Historical & Forecasted FS'!J15,0) -> 0.4177936 | ... L15: =IFERROR('Historical & Forecasted FS'!L15,0) -> 0.4413113 | N15: =IFERROR(AVERAGE(C15:L15),0) -> 0.39980861 | O15: =IFERROR(MEDIAN(C15:L15),0) -> 0.38831996 | P15: =AVERAGE(H15:L15) -> 0.41054227 | Q15: ='Data Sheet'!G303 -> 0.497595
B16: ="EBITDA" & " " & "Margin" -> EBITDA Margin | C16: =IFERROR('Historical & Forecasted FS'!C30,0) -> 0.32467518 | D16: =IFERROR('Historical & Forecasted FS'!D30,0) -> 0.34737608 | E16: =IFERROR('Historical & Forecasted FS'!E30,0) -> 0.32706978 | F16: =IFERROR('Historical & Forecasted FS'!F30,0) -> 0.31191272 | G16: =IFERROR('Historical & Forecasted FS'!G30,0) -> 0.30799149 | H16: =IFERROR('Historical & Forecasted FS'!H30,0) -> 0.29394559 | I16: =IFERROR('Historical & Forecasted FS'!I30,0) -> 0.28174781 | J16: =IFERROR('Historical & Forecasted FS'!J30,0) -> 0.3286698 | ... L16: =IFERROR('Historical & Forecasted FS'!L30,0) -> 0.32826748 | N16: =IFERROR(AVERAGE(C16:L16),0) -> 0.31827027 | O16: =IFERROR(MEDIAN(C16:L16),0) -> 0.32587248 | P16: =AVERAGE(H16:L16) -> 0.31273548 | Q16: ='Data Sheet'!G305 -> 0.3162248
B17: ="EBIT" & " " & "Margin" -> EBIT Margin | C17: =IFERROR('Historical & Forecasted FS'!C24,0) -> 0.28722339 | D17: =IFERROR('Historical & Forecasted FS'!D24,0) -> 0.30477291 | E17: =IFERROR('Historical & Forecasted FS'!E24,0) -> 0.2783541 | F17: =IFERROR('Historical & Forecasted FS'!F24,0) -> 0.26760428 | G17: =IFERROR('Historical & Forecasted FS'!G24,0) -> 0.26694027 | H17: =IFERROR('Historical & Forecasted FS'!H24,0) -> 0.24572017 | I17: =IFERROR('Historical & Forecasted FS'!I24,0) -> 0.24147314 | J17: =IFERROR('Historical & Forecasted FS'!J24,0) -> 0.29782378 | ... L17: =IFERROR('Historical & Forecasted FS'!L24,0) -> 0.29821412 | N17: =IFERROR(AVERAGE(C17:L17),0) -> 0.27910136 | O17: =IFERROR(MEDIAN(C17:L17),0) -> 0.28278875 | P17: =AVERAGE(H17:L17) -> 0.27722373 | Q17: ='Data Sheet'!G307 -> 0.250949
B18: ="EBT" & " " & "Margin" -> EBT Margin | C18: =IFERROR('Historical & Forecasted FS'!C42,0) -> 0.29258459 | D18: =IFERROR('Historical & Forecasted FS'!D42,0) -> 0.31027106 | E18: =IFERROR('Historical & Forecasted FS'!E42,0) -> 0.28460529 | F18: =IFERROR('Historical & Forecasted FS'!F42,0) -> 0.27957895 | G18: =IFERROR('Historical & Forecasted FS'!G42,0) -> 0.27448935 | H18: =IFERROR('Historical & Forecasted FS'!H42,0) -> 0.25266552 | I18: =IFERROR('Historical & Forecasted FS'!I42,0) -> 0.2443983 | J18: =IFERROR('Historical & Forecasted FS'!J42,0) -> 0.29852905 | ... L18: =IFERROR('Historical & Forecasted FS'!L42,0) -> 0.29674002 | N18: =IFERROR(AVERAGE(C18:L18),0) -> 0.28359026 | O18: =IFERROR(MEDIAN(C18:L18),0) -> 0.28859494 | P18: =AVERAGE(H18:L18) -> 0.27887467 | Q18: ='Data Sheet'!G380/'Data Sheet'!G373 -> 0.246139
B19: ="Net Profit" & " " & "Margin" -> Net Profit Margin | C19: =IFERROR('Historical & Forecasted FS'!C48,0) -> 0.21614377 | D19: =IFERROR('Historical & Forecasted FS'!D48,0) -> 0.22845774 | E19: =IFERROR('Historical & Forecasted FS'!E48,0) -> 0.21186798 | F19: =IFERROR('Historical & Forecasted FS'!F48,0) -> 0.21092421 | G19: =IFERROR('Historical & Forecasted FS'!G48,0) -> 0.22414202 | H19: =IFERROR('Historical & Forecasted FS'!H48,0) -> 0.21238095 | I19: =IFERROR('Historical & Forecasted FS'!I48,0) -> 0.20913611 | J19: =IFERROR('Historical & Forecasted FS'!J48,0) -> 0.25881793 | ... L19: =IFERROR('Historical & Forecasted FS'!L48,0) -> 0.25306234 | N19: =IFERROR(AVERAGE(C19:L19),0) -> 0.22780295 | O19: =IFERROR(MEDIAN(C19:L19),0) -> 0.22014289 | P19: =AVERAGE(H19:L19) -> 0.23729875 | Q19: ='Data Sheet'!G311 -> 0.2046742
B21: ="SalesExpenses" & " " & "%Sales" -> SalesExpenses %Sales | C21: =IFERROR('Historical & Forecasted FS'!C18,0) -> 0.065609016 | D21: =IFERROR('Historical & Forecasted FS'!D18,0) -> 0.061309715 | E21: =IFERROR('Historical & Forecasted FS'!E18,0) -> 0.065822973 | F21: =IFERROR('Historical & Forecasted FS'!F18,0) -> 0.066573894 | G21: =IFERROR('Historical & Forecasted FS'!G18,0) -> 0.062896515 | H21: =IFERROR('Historical & Forecasted FS'!H18,0) -> 0.070126146 | I21: =IFERROR('Historical & Forecasted FS'!I18,0) -> 0.07254977 | J21: =IFERROR('Historical & Forecasted FS'!J18,0) -> 0.060065552 | ... L21: =IFERROR('Historical & Forecasted FS'!L18,0) -> 0.065048202 | N21: =IFERROR(AVERAGE(C21:L21),0) -> 0.065363916 | O21: =IFERROR(MEDIAN(C21:L21),0) -> 0.065328609 | P21: =AVERAGE(H21:L21) -> 0.06628541 | Q21: ='Data Sheet'!G375/'Data Sheet'!G373 -> 0.14879071
B22: ="Depreciation" & " " & "%Sales" -> Depreciation %Sales | C22: =IFERROR('Historical & Forecasted FS'!C27,0) -> 0.03745179 | D22: =IFERROR('Historical & Forecasted FS'!D27,0) -> 0.042603171 | E22: =IFERROR('Historical & Forecasted FS'!E27,0) -> 0.048715678 | F22: =IFERROR('Historical & Forecasted FS'!F27,0) -> 0.044308436 | G22: =IFERROR('Historical & Forecasted FS'!G27,0) -> 0.041051225 | H22: =IFERROR('Historical & Forecasted FS'!H27,0) -> 0.048225418 | I22: =IFERROR('Historical & Forecasted FS'!I27,0) -> 0.040274666 | J22: =IFERROR('Historical & Forecasted FS'!J27,0) -> 0.030846024 | ... L22: =IFERROR('Historical & Forecasted FS'!L27,0) -> 0.030053355 | N22: =IFERROR(AVERAGE(C22:L22),0) -> 0.039168906 | O22: =IFERROR(MEDIAN(C22:L22),0) -> 0.040662945 | P22: =AVERAGE(H22:L22) -> 0.035511752
B24: Financial Health Ratios:
B25: Return on Capital Employed | C25: =IFERROR('Historical & Forecasted FS'!C23/('Historical & Forecasted FS'!C97+'Historical & Forecasted FS'!C106),0) -> 0.3117922 | D25: =IFERROR('Historical & Forecasted FS'!D23/('Historical & Forecasted FS'!D97+'Historical & Forecasted FS'!D106),0) -> 0.33961904 | E25: =IFERROR('Historical & Forecasted FS'!E23/('Historical & Forecasted FS'!E97+'Historical & Forecasted FS'!E106),0) -> 0.24733806 | F25: =IFERROR('Historical & Forecasted FS'!F23/('Historical & Forecasted FS'!F97+'Historical & Forecasted FS'!F106),0) -> 0.22347134 | G25: =IFERROR('Historical & Forecasted FS'!G23/('Historical & Forecasted FS'!G97+'Historical & Forecasted FS'!G106),0) -> 0.2838236 | H25: =IFERROR('Historical & Forecasted FS'!H23/('Historical & Forecasted FS'!H97+'Historical & Forecasted FS'!H106),0) -> 0.27461576 | I25: =IFERROR('Historical & Forecasted FS'!I23/('Historical & Forecasted FS'!I97+'Historical & Forecasted FS'!I106),0) -> 0.30338313 | J25: =IFERROR('Historical & Forecasted FS'!J23/('Historical & Forecasted FS'!J97+'Historical & Forecasted FS'!J106),0) -> 0.48309913 | ... L25: =IFERROR('Historical & Forecasted FS'!L23/('Historical & Forecasted FS'!L97+'Historical & Forecasted FS'!L106),0) -> 0.55144615 | N25: =IFERROR(AVERAGE(C25:L25),0) -> 0.36194598 | O25: =IFERROR(MEDIAN(C25:L25),0) -> 0.30758766 | P25: =AVERAGE(H25:L25) -> 0.4426831 | Q25: ='Data Sheet'!G298 -> 0.2399538
B26: Retained Earnings% | C26: =IFERROR('Historical & Forecasted FS'!C58,0) -> 0.72681002 | D26: =IFERROR('Historical & Forecasted FS'!D58,0) -> 0.79103446 | E26: =IFERROR('Historical & Forecasted FS'!E58,0) -> 0.74304364 | F26: =IFERROR('Historical & Forecasted FS'!F58,0) -> 0.74555061 | G26: =IFERROR('Historical & Forecasted FS'!G58,0) -> 0.7827424 | H26: =IFERROR('Historical & Forecasted FS'!H58,0) -> 0.75876451 | I26: =IFERROR('Historical & Forecasted FS'!I58,0) -> 0.7634354 | J26: =IFERROR('Historical & Forecasted FS'!J58,0) -> 0.85252674 | ... L26: =IFERROR('Historical & Forecasted FS'!L58,0) -> 0.84930092 | N26: =IFERROR(AVERAGE(C26:L26),0) -> 0.78694346 | O26: =IFERROR(MEDIAN(C26:L26),0) -> 0.7730889 | P26: =AVERAGE(H26:L26) -> 0.8160507 | Q26: =1-'Data Sheet'!G396 -> 0.6115788
B27: Return on Equity% | C27: =IFERROR('Historical & Forecasted FS'!C47/('Historical & Forecasted FS'!C106),0) -> 0.35420047 | D27: =IFERROR('Historical & Forecasted FS'!D47/('Historical & Forecasted FS'!D106),0) -> 0.44735453 | E27: =IFERROR('Historical & Forecasted FS'!E47/('Historical & Forecasted FS'!E106),0) -> 0.3562367 | F27: =IFERROR('Historical & Forecasted FS'!F47/('Historical & Forecasted FS'!F106),0) -> 0.36070184 | G27: =IFERROR('Historical & Forecasted FS'!G47/('Historical & Forecasted FS'!G106),0) -> 0.55560118 | H27: ='Historical & Forecasted FS'!H47/(('Historical & Forecasted FS'!H106+'Historical & Forecasted FS'!G106)/2) -> 0.55917221 | I27: =IFERROR('Historical & Forecasted FS'!I47/(('Historical & Forecasted FS'!I106+'Historical & Forecasted FS'!H106)/2),0) -> 0.73685562 | J27: =IFERROR('Historical & Forecasted FS'!J47/(('Historical & Forecasted FS'!J106+'Historical & Forecasted FS'!I106)/2),0) -> 1.4744333 | K27: =IFERROR('Historical & Forecasted FS'!K47/(('Historical & Forecasted FS'!K106+'Historical & Forecasted FS'!J106)/2),0) -> 1.7545929 | L27: =IFERROR('Historical & Forecasted FS'!L47/(('Historical & Forecasted FS'!L106+'Historical & Forecasted FS'!K106)/2),0) -> 1.7194951 | N27: =IFERROR(AVERAGE(C27:L27),0) -> 0.83186439 | O27: =IFERROR(MEDIAN(C27:L27),0) -> 0.5573867 | P27: =AVERAGE(H27:L27) -> 1.2489098 | Q27: ='Data Sheet'!G299 -> 0.3119468
B28: Self Sustained Growth Rate | C28: =IFERROR(C27*C26,0) -> 0.25743645 | D28: =IFERROR(D27*D26,0) -> 0.35387285 | E28: =IFERROR(E27*E26,0) -> 0.26469941 | F28: =IFERROR(F27*F26,0) -> 0.26892148 | G28: =IFERROR(G27*G26,0) -> 0.43489261 | H28: =IFERROR(H27*H26,0) -> 0.42428003 | I28: =IFERROR(I27*I26,0) -> 0.56254166 | J28: =IFERROR(J27*J26,0) -> 1.2569939 | ... L28: =IFERROR(L27*L26,0) -> 1.4603688 | N28: =IFERROR(AVERAGE(C28:L28),0) -> 0.67863351 | O28: =IFERROR(MEDIAN(C28:L28),0) -> 0.42958632 | P28: =AVERAGE(H28:L28) -> 1.0413025 | Q28: =Q27*Q26 -> 0.19078005
B29: Interest Coverage Ratio | C29: =IFERROR('Historical & Forecasted FS'!C23/-'Data Sheet'!B34,0) -> 136.72656 | D29: =IFERROR('Historical & Forecasted FS'!D23/-'Data Sheet'!C34,0) -> 97.175989 | E29: =IFERROR('Historical & Forecasted FS'!E23/-'Data Sheet'!D34,0) -> 41.225275 | F29: =IFERROR('Historical & Forecasted FS'!F23/-'Data Sheet'!E34,0) -> 26.407232 | G29: =IFERROR('Historical & Forecasted FS'!G23/-'Data Sheet'!F34,0) -> 21.882099 | H29: =IFERROR('Historical & Forecasted FS'!H23/-'Data Sheet'!G34,0) -> 17.877517 | I29: =IFERROR('Historical & Forecasted FS'!I23/-'Data Sheet'!H34,0) -> 23.072746 | J29: =IFERROR('Historical & Forecasted FS'!J23/-'Data Sheet'!I34,0) -> 41.190548 | ... L29: =IFERROR('Historical & Forecasted FS'!L23/-'Data Sheet'!K34,0) -> 29.062039 | N29: =IFERROR(AVERAGE(C29:L29),0) -> 47.536958 | O29: =IFERROR(MEDIAN(C29:L29),0) -> 34.905806 | P29: =AVERAGE(H29:L29) -> 30.390485 | Q29: ='Data Sheet'!G351 -> 18.186367
B30: Debt/Equity | H30: =SUM('Historical & Forecasted FS'!H92:H93,'Historical & Forecasted FS'!H85:H87)/'Historical & Forecasted FS'!H106 -> 1.1940478 | I30: =SUM('Historical & Forecasted FS'!I92:I93,'Historical & Forecasted FS'!I85:I87)/'Historical & Forecasted FS'!I106 -> 1.8714397 | J30: =SUM('Historical & Forecasted FS'!J92:J93,'Historical & Forecasted FS'!J85:J87)/'Historical & Forecasted FS'!J106 -> 2.1639246 | K30: =SUM('Historical & Forecasted FS'!K92:K93,'Historical & Forecasted FS'!K85:K87)/'Historical & Forecasted FS'!K106 -> 2.6144616 | L30: =SUM('Historical & Forecasted FS'!L92:L93,'Historical & Forecasted FS'!L85:L87)/'Historical & Forecasted FS'!L106 -> 1.994175 | P30: =AVERAGE(H30:L30) -> 1.9676097 | Q30: ='Data Sheet'!G446/'Data Sheet'!G441 -> 0.72229341
B32: Working Capital Ratios:
B33: ="Receivable" & " " & "Turnover" -> Receivable Turnover | D33: =IFERROR('Historical & Forecasted FS'!D8/(('Historical & Forecasted FS'!D67+'Historical & Forecasted FS'!C67)/2),0) -> 13.624122 | E33: =IFERROR('Historical & Forecasted FS'!E8/(('Historical & Forecasted FS'!E67+'Historical & Forecasted FS'!D67)/2),0) -> 13.228169 | F33: =IFERROR('Historical & Forecasted FS'!F8/(('Historical & Forecasted FS'!F67+'Historical & Forecasted FS'!E67)/2),0) -> 13.63352 | G33: =IFERROR('Historical & Forecasted FS'!G8/(('Historical & Forecasted FS'!G67+'Historical & Forecasted FS'!F67)/2),0) -> 12.936922 | H33: =IFERROR('Historical & Forecasted FS'!H8/(('Historical & Forecasted FS'!H67+'Historical & Forecasted FS'!G67)/2),0) -> 11.284438 | I33: =IFERROR('Historical & Forecasted FS'!I8/(('Historical & Forecasted FS'!I67+'Historical & Forecasted FS'!H67)/2),0) -> 14.061107 | J33: =IFERROR('Historical & Forecasted FS'!J8/(('Historical & Forecasted FS'!J67+'Historical & Forecasted FS'!I67)/2),0) -> 17.256333 | K33: =IFERROR('Historical & Forecasted FS'!K8/(('Historical & Forecasted FS'!K67+'Historical & Forecasted FS'!J67)/2),0) -> 14.480849 | L33: =IFERROR('Historical & Forecasted FS'!L8/(('Historical & Forecasted FS'!L67+'Historical & Forecasted FS'!K67)/2),0) -> 13.287284 | N33: =IFERROR(AVERAGE(C33:L33),0) -> 13.754749 | O33: =IFERROR(MEDIAN(C33:L33),0) -> 13.624122 | P33: =AVERAGE(H33:L33) -> 14.074002 | Q33: ='Data Sheet'!G320 -> 7.2436786
B34: ="Payable" & " " & "Turnover" -> Payable Turnover | D34: ='Historical & Forecasted FS'!D11/(('Historical & Forecasted FS'!D84+'Historical & Forecasted FS'!C84)/2) -> 4.2654142 | E34: ='Historical & Forecasted FS'!E11/(('Historical & Forecasted FS'!E84+'Historical & Forecasted FS'!D84)/2) -> 3.6100242 | F34: ='Historical & Forecasted FS'!F11/(('Historical & Forecasted FS'!F84+'Historical & Forecasted FS'!E84)/2) -> 3.4597724 | G34: ='Historical & Forecasted FS'!G11/(('Historical & Forecasted FS'!G84+'Historical & Forecasted FS'!F84)/2) -> 3.2708679 | H34: ='Historical & Forecasted FS'!H11/(('Historical & Forecasted FS'!H84+'Historical & Forecasted FS'!G84)/2) -> 3.1683444 | I34: ='Historical & Forecasted FS'!I11/(('Historical & Forecasted FS'!I84+'Historical & Forecasted FS'!H84)/2) -> 3.8304568 | J34: ='Historical & Forecasted FS'!J11/(('Historical & Forecasted FS'!J84+'Historical & Forecasted FS'!I84)/2) -> 4.3886914 | K34: ='Historical & Forecasted FS'!K11/(('Historical & Forecasted FS'!K84+'Historical & Forecasted FS'!J84)/2) -> 3.7609314 | L34: ='Historical & Forecasted FS'!L11/(('Historical & Forecasted FS'!L84+'Historical & Forecasted FS'!K84)/2) -> 3.3795275 | N34: =IFERROR(AVERAGE(C34:L34),0) -> 3.6815589 | O34: =IFERROR(MEDIAN(C34:L34),0) -> 3.6100242 | P34: =AVERAGE(H34:L34) -> 3.7055903 | Q34: ='Data Sheet'!G374/'Data Sheet'!G428 -> 4.8710565
B35: ="Inventory" & " " & "Turnover" -> Inventory Turnover | D35: =IFERROR('Historical & Forecasted FS'!D11/(('Historical & Forecasted FS'!D70+'Historical & Forecasted FS'!C70)/2),0) -> 62.820179 | E35: =IFERROR('Historical & Forecasted FS'!E11/(('Historical & Forecasted FS'!E70+'Historical & Forecasted FS'!D70)/2),0) -> 58.636911 | F35: =IFERROR('Historical & Forecasted FS'!F11/(('Historical & Forecasted FS'!F70+'Historical & Forecasted FS'!E70)/2),0) -> 40.37441 | G35: =IFERROR('Historical & Forecasted FS'!G11/(('Historical & Forecasted FS'!G70+'Historical & Forecasted FS'!F70)/2),0) -> 37.170809 | H35: =IFERROR('Historical & Forecasted FS'!H11/(('Historical & Forecasted FS'!H70+'Historical & Forecasted FS'!G70)/2),0) -> 40.134458 | I35: =IFERROR('Historical & Forecasted FS'!I11/(('Historical & Forecasted FS'!I70+'Historical & Forecasted FS'!H70)/2),0) -> 41.522958 | J35: =IFERROR('Historical & Forecasted FS'!J11/(('Historical & Forecasted FS'!J70+'Historical & Forecasted FS'!I70)/2),0) -> 40.03026 | K35: =IFERROR('Historical & Forecasted FS'!K11/(('Historical & Forecasted FS'!K70+'Historical & Forecasted FS'!J70)/2),0) -> 38.789866 | L35: =IFERROR('Historical & Forecasted FS'!L11/(('Historical & Forecasted FS'!L70+'Historical & Forecasted FS'!K70)/2),0) -> 37.977654 | N35: =IFERROR(AVERAGE(C35:L35),0) -> 44.161945 | O35: =IFERROR(MEDIAN(C35:L35),0) -> 40.134458 | P35: =AVERAGE(H35:L35) -> 39.691039 | Q35: ='Data Sheet'!G321 -> 8.9695414
B36: ="Fixed Asset" & " " & "Turnover" -> Fixed Asset Turnover | C36: =IFERROR('Historical & Forecasted FS'!C8/'Historical & Forecasted FS'!C76,0) -> 8.8632176 | D36: =IFERROR('Historical & Forecasted FS'!D8/'Historical & Forecasted FS'!D76,0) -> 10.400739 | E36: =IFERROR('Historical & Forecasted FS'!E8/'Historical & Forecasted FS'!E76,0) -> 7.9836727 | F36: =IFERROR('Historical & Forecasted FS'!F8/'Historical & Forecasted FS'!F76,0) -> 6.7854838 | G36: =IFERROR('Historical & Forecasted FS'!G8/'Historical & Forecasted FS'!G76,0) -> 6.4302489 | H36: =IFERROR('Historical & Forecasted FS'!H8/'Historical & Forecasted FS'!H76,0) -> 6.9606185 | I36: =IFERROR('Historical & Forecasted FS'!I8/'Historical & Forecasted FS'!I76,0) -> 6.0551218 | J36: =IFERROR('Historical & Forecasted FS'!J8/AVERAGE('Historical & Forecasted FS'!J76,'Historical & Forecasted FS'!I76),0) -> 7.7125328 | K36: =IFERROR('Historical & Forecasted FS'!K8/AVERAGE('Historical & Forecasted FS'!K76,'Historical & Forecasted FS'!J76),0) -> 7.7273003 | L36: =IFERROR('Historical & Forecasted FS'!L8/AVERAGE('Historical & Forecasted FS'!L76,'Historical & Forecasted FS'!K76),0) -> 7.1702366 | N36: =IFERROR(AVERAGE(C36:L36),0) -> 7.6089172 | O36: =IFERROR(MEDIAN(C36:L36),0) -> 7.4413847 | P36: =AVERAGE(H36:L36) -> 7.125162 | Q36: ='Data Sheet'!G319 -> 4.2199338
B37: ="Capital" & " " & "Turnover" -> Capital Turnover | C37: =IFERROR('Historical & Forecasted FS'!C8/'Historical & Forecasted FS'!C106,0) -> 1.6387263 | D37: =IFERROR('Historical & Forecasted FS'!D8/AVERAGE('Historical & Forecasted FS'!D106,'Historical & Forecasted FS'!C106),0) -> 2.0243653 | E37: =IFERROR('Historical & Forecasted FS'!E8/AVERAGE('Historical & Forecasted FS'!E106,'Historical & Forecasted FS'!D106),0) -> 1.7418055 | F37: =IFERROR('Historical & Forecasted FS'!F8/AVERAGE('Historical & Forecasted FS'!F106,'Historical & Forecasted FS'!E106),0) -> 1.7479031 | G37: =IFERROR('Historical & Forecasted FS'!G8/AVERAGE('Historical & Forecasted FS'!G106,'Historical & Forecasted FS'!F106),0) -> 2.202335 | H37: =IFERROR('Historical & Forecasted FS'!H8/AVERAGE('Historical & Forecasted FS'!H106,'Historical & Forecasted FS'!G106),0) -> 2.6328737 | I37: =IFERROR('Historical & Forecasted FS'!I8/AVERAGE('Historical & Forecasted FS'!I106,'Historical & Forecasted FS'!H106),0) -> 3.5233304 | J37: =IFERROR('Historical & Forecasted FS'!J8/AVERAGE('Historical & Forecasted FS'!J106,'Historical & Forecasted FS'!I106),0) -> 5.6967975 | K37: =IFERROR('Historical & Forecasted FS'!K8/AVERAGE('Historical & Forecasted FS'!K106,'Historical & Forecasted FS'!J106),0) -> 6.9325082 | L37: =IFERROR('Historical & Forecasted FS'!L8/AVERAGE('Historical & Forecasted FS'!L106,'Historical & Forecasted FS'!K106),0) -> 6.7947491 | N37: =IFERROR(AVERAGE(C37:L37),0) -> 3.4935394 | O37: =IFERROR(MEDIAN(C37:L37),0) -> 2.4176044 | P37: =AVERAGE(H37:L37) -> 5.1160518 | Q37: ='Data Sheet'!G373/'Data Sheet'!G441 -> 1.4413536
B39: (In days)
B40: ="Receivable" & " " & "Days" -> Receivable Days | D40: =IFERROR(365/D33,0) -> 26.790717 | E40: =IFERROR(365/E33,0) -> 27.592632 | F40: =IFERROR(365/F33,0) -> 26.77225 | G40: =IFERROR(365/G33,0) -> 28.213822 | H40: =IFERROR(365/H33,0) -> 32.34543 | I40: =IFERROR(365/I33,0) -> 25.958126 | J40: =IFERROR(365/J33,0) -> 21.151655 | K40: =IFERROR(365/K33,0) -> 25.205704 | L40: =IFERROR(365/L33,0) -> 27.469872 | N40: =IFERROR(AVERAGE(C40:L40),0) -> 26.833357 | O40: =IFERROR(MEDIAN(C40:L40),0) -> 26.790717 | P40: =AVERAGE(H40:L40) -> 26.426158 | Q40: ='Data Sheet'!G338 -> 50.406202
B41: ="Payable" & " " & "Days" -> Payable Days | D41: =IFERROR(365/D34,0) -> 85.571994 | E41: =IFERROR(365/E34,0) -> 101.10736 | F41: =IFERROR(365/F34,0) -> 105.49827 | G41: =IFERROR(365/G34,0) -> 111.59118 | H41: =IFERROR(365/H34,0) -> 115.20212 | I41: =IFERROR(365/I34,0) -> 95.288896 | J41: =IFERROR(365/J34,0) -> 83.168299 | K41: =IFERROR(365/K34,0) -> 97.050428 | L41: =IFERROR(365/L34,0) -> 108.00326 | N41: =IFERROR(AVERAGE(C41:L41),0) -> 100.27576 | O41: =IFERROR(MEDIAN(C41:L41),0) -> 101.10736 | P41: =AVERAGE(H41:L41) -> 99.742602 | Q41: ='Data Sheet'!G340 -> 71.658703
B42: ="Inventory" & " " & "Days" -> Inventory Days | D42: =IFERROR(365/D35,0) -> 5.8102349 | E42: =IFERROR(365/E35,0) -> 6.2247481 | F42: =IFERROR(365/F35,0) -> 9.0403799 | G42: =IFERROR(365/G35,0) -> 9.8195333 | H42: =IFERROR(365/H35,0) -> 9.0944295 | I42: =IFERROR(365/I35,0) -> 8.7903178 | J42: =IFERROR(365/J35,0) -> 9.1181021 | K42: =IFERROR(365/K35,0) -> 9.4096741 | L42: =IFERROR(365/L35,0) -> 9.610915 | N42: =IFERROR(AVERAGE(C42:L42),0) -> 8.5464816 | O42: =IFERROR(MEDIAN(C42:L42),0) -> 9.0944295 | P42: =AVERAGE(H42:L42) -> 9.2046877 | Q42: ='Data Sheet'!G339 -> 42.19878
B43: ="Cash Conversion Cycle" -> Cash Conversion Cycle | D43: =IFERROR(SUM(D40,D42)-D41,0) -> -52.971041 | E43: =IFERROR(SUM(E40,E42)-E41,0) -> -67.289976 | F43: =IFERROR(SUM(F40,F42)-F41,0) -> -69.68564 | G43: =IFERROR(SUM(G40,G42)-G41,0) -> -73.557823 | H43: =IFERROR(SUM(H40,H42)-H41,0) -> -73.762264 | I43: =IFERROR(SUM(I40,I42)-I41,0) -> -60.540453 | J43: =IFERROR(SUM(J40,J42)-J41,0) -> -52.898542 | K43: =IFERROR(SUM(K40,K42)-K41,0) -> -62.43505 | L43: =IFERROR(SUM(L40,L42)-L41,0) -> -70.922477 | N43: =IFERROR(AVERAGE(C43:L43),0) -> -64.895918 | O43: =IFERROR(MEDIAN(C43:L43),0) -> -67.289976 | P43: =AVERAGE(H43:L43) -> -64.111757 | Q43: ='Data Sheet'!G341 -> 20.94628
B45: Cashflow Ratios:
B46: CFO/Sales | C46: =IFERROR('Historical & Forecasted FS'!C126/'Historical & Forecasted FS'!C8,0) -> 0.32666648 | D46: =IFERROR('Historical & Forecasted FS'!D126/'Historical & Forecasted FS'!D8,0) -> 0.3477141 | E46: =IFERROR('Historical & Forecasted FS'!E126/'Historical & Forecasted FS'!E8,0) -> 0.30713832 | F46: =IFERROR('Historical & Forecasted FS'!F126/'Historical & Forecasted FS'!F8,0) -> 0.28017223 | G46: =IFERROR('Historical & Forecasted FS'!G126/'Historical & Forecasted FS'!G8,0) -> 0.29154916 | H46: =IFERROR('Historical & Forecasted FS'!H126/'Historical & Forecasted FS'!H8,0) -> 0.26670997 | I46: =IFERROR('Historical & Forecasted FS'!I126/'Historical & Forecasted FS'!I8,0) -> 0.29387829 | J46: =IFERROR('Historical & Forecasted FS'!J126/'Historical & Forecasted FS'!J8,0) -> 0.28439903 | ... L46: =IFERROR('Historical & Forecasted FS'!L126/'Historical & Forecasted FS'!L8,0) -> 0.28840941 | N46: =IFERROR(AVERAGE(C46:L46),0) -> 0.2996407 | O46: =IFERROR(MEDIAN(C46:L46),0) -> 0.29271373 | P46: =AVERAGE(H46:L46) -> 0.28863335 | Q46: ='Data Sheet'!G461/'Data Sheet'!G373 -> 0.28668329
B47: CFO/Total Assets | C47: =IFERROR('Historical & Forecasted FS'!C126/'Historical & Forecasted FS'!C82,0) -> 0.25756236 | D47: =IFERROR('Historical & Forecasted FS'!D126/'Historical & Forecasted FS'!D82,0) -> 0.27989461 | E47: =IFERROR('Historical & Forecasted FS'!E126/'Historical & Forecasted FS'!E82,0) -> 0.20588711 | F47: =IFERROR('Historical & Forecasted FS'!F126/'Historical & Forecasted FS'!F82,0) -> 0.1711211 | G47: =IFERROR('Historical & Forecasted FS'!G126/'Historical & Forecasted FS'!G82,0) -> 0.21172739 | H47: =IFERROR('Historical & Forecasted FS'!H126/'Historical & Forecasted FS'!H82,0) -> 0.20498588 | I47: =IFERROR('Historical & Forecasted FS'!I126/'Historical & Forecasted FS'!I82,0) -> 0.24907993 | J47: =IFERROR('Historical & Forecasted FS'!J126/'Historical & Forecasted FS'!J82,0) -> 0.29640287 | ... L47: =IFERROR('Historical & Forecasted FS'!L126/'Historical & Forecasted FS'!L82,0) -> 0.31352334 | N47: =IFERROR(AVERAGE(C47:L47),0) -> 0.25364617 | O47: =IFERROR(MEDIAN(C47:L47),0) -> 0.25332114 | P47: =AVERAGE(H47:L47) -> 0.28205384 | Q47: ='Data Sheet'!G461/'Data Sheet'!G425 -> 0.16086545
B48: CFO/Total Debt | C48: =IFERROR('Historical & Forecasted FS'!C126/'Historical & Forecasted FS'!C97,0) -> 1.0504715 | D48: =IFERROR('Historical & Forecasted FS'!D126/'Historical & Forecasted FS'!D97,0) -> 0.89915911 | E48: =IFERROR('Historical & Forecasted FS'!E126/'Historical & Forecasted FS'!E97,0) -> 0.57878547 | F48: =IFERROR('Historical & Forecasted FS'!F126/'Historical & Forecasted FS'!F97,0) -> 0.45725413 | G48: =IFERROR('Historical & Forecasted FS'!G126/'Historical & Forecasted FS'!G97,0) -> 0.5428289 | H48: =IFERROR('Historical & Forecasted FS'!H126/'Historical & Forecasted FS'!H97,0) -> 0.48760453 | I48: =IFERROR('Historical & Forecasted FS'!I126/'Historical & Forecasted FS'!I97,0) -> 0.52674053 | J48: =IFERROR('Historical & Forecasted FS'!J126/'Historical & Forecasted FS'!J97,0) -> 0.64050581 | ... L48: =IFERROR('Historical & Forecasted FS'!L126/'Historical & Forecasted FS'!L97,0) -> 0.76168788 | N48: =IFERROR(AVERAGE(C48:L48),0) -> 0.67698196 | O48: =IFERROR(MEDIAN(C48:L48),0) -> 0.60964564 | P48: =AVERAGE(H48:L48) -> 0.6482641 | Q48: ='Data Sheet'!G461/'Data Sheet'!G446 -> 0.57208328

Sheet Common Size Statements
B6: ="Common Size Income Statement -"& " " &'Data Sheet'!$A$4 -> Common Size Income Statement - Apple Inc.
B8: Particulars | C8: ='Historical & Forecasted FS'!C6 -> 2014 | D8: ='Historical & Forecasted FS'!D6 -> 2015 | E8: ='Historical & Forecasted FS'!E6 -> 2016 | F8: ='Historical & Forecasted FS'!F6 -> 2017 | G8: ='Historical & Forecasted FS'!G6 -> 2018 | H8: ='Historical & Forecasted FS'!H6 -> 2019 | I8: ='Historical & Forecasted FS'!I6 -> 2020 | J8: ='Historical & Forecasted FS'!J6 -> 2021 | ... L8: ='Historical & Forecasted FS'!L6 -> 2023
B9: ='Historical & Forecasted FS'!B8 -> Sales | C9: ='Historical & Forecasted FS'!C8/'Historical & Forecasted FS'!C$8 -> 1 | D9: ='Historical & Forecasted FS'!D8/'Historical & Forecasted FS'!D$8 -> 1 | E9: ='Historical & Forecasted FS'!E8/'Historical & Forecasted FS'!E$8 -> 1 | F9: ='Historical & Forecasted FS'!F8/'Historical & Forecasted FS'!F$8 -> 1 | G9: ='Historical & Forecasted FS'!G8/'Historical & Forecasted FS'!G$8 -> 1 | H9: ='Historical & Forecasted FS'!H8/'Historical & Forecasted FS'!H$8 -> 1 | I9: ='Historical & Forecasted FS'!I8/'Historical & Forecasted FS'!I$8 -> 1 | J9: ='Historical & Forecasted FS'!J8/'Historical & Forecasted FS'!J$8 -> 1 | ... L9: ='Historical & Forecasted FS'!L8/'Historical & Forecasted FS'!L$8 -> 1
B10: ='Historical & Forecasted FS'!B11 -> COGS | C10: ='Historical & Forecasted FS'!C11/'Historical & Forecasted FS'!C$8 -> 0.61411964 | D10: ='Historical & Forecasted FS'!D11/'Historical & Forecasted FS'!D$8 -> 0.59940098 | E10: ='Historical & Forecasted FS'!E11/'Historical & Forecasted FS'!E$8 -> 0.60924044 | F10: ='Historical & Forecasted FS'!F11/'Historical & Forecasted FS'!F$8 -> 0.6153014 | G10: ='Historical & Forecasted FS'!G11/'Historical & Forecasted FS'!G$8 -> 0.61656281 | H10: ='Historical & Forecasted FS'!H11/'Historical & Forecasted FS'!H$8 -> 0.62182232 | I10: ='Historical & Forecasted FS'!I11/'Historical & Forecasted FS'!I$8 -> 0.61766752 | J10: ='Historical & Forecasted FS'!J11/'Historical & Forecasted FS'!J$8 -> 0.5822064 | ... L10: ='Historical & Forecasted FS'!L11/'Historical & Forecasted FS'!L$8 -> 0.5586887
B11: ='Historical & Forecasted FS'!B14 -> Gross Profit | C11: ='Historical & Forecasted FS'!C14/'Historical & Forecasted FS'!C$8 -> 0.38588036 | D11: ='Historical & Forecasted FS'!D14/'Historical & Forecasted FS'!D$8 -> 0.40059902 | E11: ='Historical & Forecasted FS'!E14/'Historical & Forecasted FS'!E$8 -> 0.39075956 | F11: ='Historical & Forecasted FS'!F14/'Historical & Forecasted FS'!F$8 -> 0.3846986 | G11: ='Historical & Forecasted FS'!G14/'Historical & Forecasted FS'!G$8 -> 0.38343719 | H11: ='Historical & Forecasted FS'!H14/'Historical & Forecasted FS'!H$8 -> 0.37817768 | I11: ='Historical & Forecasted FS'!I14/'Historical & Forecasted FS'!I$8 -> 0.38233248 | J11: ='Historical & Forecasted FS'!J14/'Historical & Forecasted FS'!J$8 -> 0.4177936 | ... L11: ='Historical & Forecasted FS'!L14/'Historical & Forecasted FS'!L$8 -> 0.4413113
B12: ='Historical & Forecasted FS'!B17 -> SG&A Expenses | C12: ='Historical & Forecasted FS'!C17/'Historical & Forecasted FS'!C$8 -> 0.065609016 | D12: ='Historical & Forecasted FS'!D17/'Historical & Forecasted FS'!D$8 -> 0.061309715 | E12: ='Historical & Forecasted FS'!E17/'Historical & Forecasted FS'!E$8 -> 0.065822973 | F12: ='Historical & Forecasted FS'!F17/'Historical & Forecasted FS'!F$8 -> 0.066573894 | G12: ='Historical & Forecasted FS'!G17/'Historical & Forecasted FS'!G$8 -> 0.062896515 | H12: ='Historical & Forecasted FS'!H17/'Historical & Forecasted FS'!H$8 -> 0.070126146 | I12: ='Historical & Forecasted FS'!I17/'Historical & Forecasted FS'!I$8 -> 0.07254977 | J12: ='Historical & Forecasted FS'!J17/'Historical & Forecasted FS'!J$8 -> 0.060065552 | ... L12: ='Historical & Forecasted FS'!L17/'Historical & Forecasted FS'!L$8 -> 0.065048202
B13: ='Historical & Forecasted FS'!B20 -> R&D Expenses | C13: ='Historical & Forecasted FS'!C20/'Historical & Forecasted FS'!C$8 -> 0.03304795 | D13: ='Historical & Forecasted FS'!D20/'Historical & Forecasted FS'!D$8 -> 0.034516398 | E13: ='Historical & Forecasted FS'!E20/'Historical & Forecasted FS'!E$8 -> 0.046582483 | F13: ='Historical & Forecasted FS'!F20/'Historical & Forecasted FS'!F$8 -> 0.050520429 | G13: ='Historical & Forecasted FS'!G20/'Historical & Forecasted FS'!G$8 -> 0.053600407 | H13: ='Historical & Forecasted FS'!H20/'Historical & Forecasted FS'!H$8 -> 0.062331363 | I13: ='Historical & Forecasted FS'!I20/'Historical & Forecasted FS'!I$8 -> 0.068309564 | J13: ='Historical & Forecasted FS'!J20/'Historical & Forecasted FS'!J$8 -> 0.059904269 | ... L13: ='Historical & Forecasted FS'!L20/'Historical & Forecasted FS'!L$8 -> 0.078048971
B14: ='Historical & Forecasted FS'!B23 -> EBIT | C14: ='Historical & Forecasted FS'!C23/'Historical & Forecasted FS'!C$8 -> 0.28722339 | D14: ='Historical & Forecasted FS'!D23/'Historical & Forecasted FS'!D$8 -> 0.30477291 | E14: ='Historical & Forecasted FS'!E23/'Historical & Forecasted FS'!E$8 -> 0.2783541 | F14: ='Historical & Forecasted FS'!F23/'Historical & Forecasted FS'!F$8 -> 0.26760428 | G14: ='Historical & Forecasted FS'!G23/'Historical & Forecasted FS'!G$8 -> 0.26694027 | H14: ='Historical & Forecasted FS'!H23/'Historical & Forecasted FS'!H$8 -> 0.24572017 | I14: ='Historical & Forecasted FS'!I23/'Historical & Forecasted FS'!I$8 -> 0.24147314 | J14: ='Historical & Forecasted FS'!J23/'Historical & Forecasted FS'!J$8 -> 0.29782378 | ... L14: ='Historical & Forecasted FS'!L23/'Historical & Forecasted FS'!L$8 -> 0.29821412
B15: ='Historical & Forecasted FS'!B26 -> Dep & Amm | C15: ='Historical & Forecasted FS'!C26/'Historical & Forecasted FS'!C$8 -> 0.03745179 | D15: ='Historical & Forecasted FS'!D26/'Historical & Forecasted FS'!D$8 -> 0.042603171 | E15: ='Historical & Forecasted FS'!E26/'Historical & Forecasted FS'!E$8 -> 0.048715678 | F15: ='Historical & Forecasted FS'!F26/'Historical & Forecasted FS'!F$8 -> 0.044308436 | G15: ='Historical & Forecasted FS'!G26/'Historical & Forecasted FS'!G$8 -> 0.041051225 | H15: ='Historical & Forecasted FS'!H26/'Historical & Forecasted FS'!H$8 -> 0.048225418 | I15: ='Historical & Forecasted FS'!I26/'Historical & Forecasted FS'!I$8 -> 0.040274666 | J15: ='Historical & Forecasted FS'!J26/'Historical & Forecasted FS'!J$8 -> 0.030846024 | ... L15: ='Historical & Forecasted FS'!L26/'Historical & Forecasted FS'!L$8 -> 0.030053355
B16: ='Historical & Forecasted FS'!B29 -> EBITDA | C16: ='Historical & Forecasted FS'!C29/'Historical & Forecasted FS'!C$8 -> 0.32467518 | D16: ='Historical & Forecasted FS'!D29/'Historical & Forecasted FS'!D$8 -> 0.34737608 | E16: ='Historical & Forecasted FS'!E29/'Historical & Forecasted FS'!E$8 -> 0.32706978 | F16: ='Historical & Forecasted FS'!F29/'Historical & Forecasted FS'!F$8 -> 0.31191272 | G16: ='Historical & Forecasted FS'!G29/'Historical & Forecasted FS'!G$8 -> 0.30799149 | H16: ='Historical & Forecasted FS'!H29/'Historical & Forecasted FS'!H$8 -> 0.29394559 | I16: ='Historical & Forecasted FS'!I29/'Historical & Forecasted FS'!I$8 -> 0.28174781 | J16: ='Historical & Forecasted FS'!J29/'Historical & Forecasted FS'!J$8 -> 0.3286698 | ... L16: ='Historical & Forecasted FS'!L29/'Historical & Forecasted FS'!L$8 -> 0.32826748
B17: ='Historical & Forecasted FS'!B32 -> Other operating expenses | C17: ='Historical & Forecasted FS'!C32/'Historical & Forecasted FS'!C$8 -> -0.0023578325 | D17: ='Historical & Forecasted FS'!D32/'Historical & Forecasted FS'!D$8 -> -0.0038636801 | E17: ='Historical & Forecasted FS'!E32/'Historical & Forecasted FS'!E$8 -> -0.0055416692 | F17: ='Historical & Forecasted FS'!F32/'Historical & Forecasted FS'!F$8 -> -0.00058019317 | G17: ='Historical & Forecasted FS'!G32/'Historical & Forecasted FS'!G$8 -> -0.0016604228 | H17: ='Historical & Forecasted FS'!H32/'Historical & Forecasted FS'!H$8 -> 0.0016219914 | I17: ='Historical & Forecasted FS'!I32/'Historical & Forecasted FS'!I$8 -> -0.00031692257 | J17: ='Historical & Forecasted FS'!J32/'Historical & Forecasted FS'!J$8 -> 0.00016401643 | ... L17: ='Historical & Forecasted FS'!L32/'Historical & Forecasted FS'!L$8 -> -0.0009966474
B18: ='Historical & Forecasted FS'!B35 -> Net Interest Expense | C18: ='Historical & Forecasted FS'!C35/'Historical & Forecasted FS'!C$8 -> 0.0077190295 | D18: ='Historical & Forecasted FS'!D35/'Historical & Forecasted FS'!D$8 -> 0.0093618296 | E18: ='Historical & Forecasted FS'!E35/'Historical & Forecasted FS'!E$8 -> 0.011792858 | F18: ='Historical & Forecasted FS'!F35/'Historical & Forecasted FS'!F$8 -> 0.012554857 | G18: ='Historical & Forecasted FS'!G35/'Historical & Forecasted FS'!G$8 -> 0.0092095107 | H18: ='Historical & Forecasted FS'!H35/'Historical & Forecasted FS'!H$8 -> 0.0053233605 | I18: ='Historical & Forecasted FS'!I35/'Historical & Forecasted FS'!I$8 -> 0.0032420815 | J18: ='Historical & Forecasted FS'!J35/'Historical & Forecasted FS'!J$8 -> 0.00054125423 | ... L18: ='Historical & Forecasted FS'!L35/'Historical & Forecasted FS'!L$8 -> -0.0004774515
B19: ='Historical & Forecasted FS'!B38 -> Dep & Amm | C19: ='Historical & Forecasted FS'!C38/'Historical & Forecasted FS'!C$8 -> 0.03745179 | D19: ='Historical & Forecasted FS'!D38/'Historical & Forecasted FS'!D$8 -> 0.042603171 | E19: ='Historical & Forecasted FS'!E38/'Historical & Forecasted FS'!E$8 -> 0.048715678 | F19: ='Historical & Forecasted FS'!F38/'Historical & Forecasted FS'!F$8 -> 0.044308436 | G19: ='Historical & Forecasted FS'!G38/'Historical & Forecasted FS'!G$8 -> 0.041051225 | H19: ='Historical & Forecasted FS'!H38/'Historical & Forecasted FS'!H$8 -> 0.048225418 | I19: ='Historical & Forecasted FS'!I38/'Historical & Forecasted FS'!I$8 -> 0.040274666 | J19: ='Historical & Forecasted FS'!J38/'Historical & Forecasted FS'!J$8 -> 0.030846024 | ... L19: ='Historical & Forecasted FS'!L38/'Historical & Forecasted FS'!L$8 -> 0.030053355
B20: ='Historical & Forecasted FS'!B41 -> EBT | C20: ='Historical & Forecasted FS'!C41/'Historical & Forecasted FS'!C$8 -> 0.29258459 | D20: ='Historical & Forecasted FS'!D41/'Historical & Forecasted FS'!D$8 -> 0.31027106 | E20: ='Historical & Forecasted FS'!E41/'Historical & Forecasted FS'!E$8 -> 0.28460529 | F20: ='Historical & Forecasted FS'!F41/'Historical & Forecasted FS'!F$8 -> 0.27957895 | G20: ='Historical & Forecasted FS'!G41/'Historical & Forecasted FS'!G$8 -> 0.27448935 | H20: ='Historical & Forecasted FS'!H41/'Historical & Forecasted FS'!H$8 -> 0.25266552 | I20: ='Historical & Forecasted FS'!I41/'Historical & Forecasted FS'!I$8 -> 0.2443983 | J20: ='Historical & Forecasted FS'!J41/'Historical & Forecasted FS'!J$8 -> 0.29852905 | ... L20: ='Historical & Forecasted FS'!L41/'Historical & Forecasted FS'!L$8 -> 0.29674002
B21: ='Historical & Forecasted FS'!B44 -> Tax | C21: ='Historical & Forecasted FS'!C44/'Historical & Forecasted FS'!C$8 -> 0.076440822 | D21: ='Historical & Forecasted FS'!D44/'Historical & Forecasted FS'!D$8 -> 0.08181332 | E21: ='Historical & Forecasted FS'!E44/'Historical & Forecasted FS'!E$8 -> 0.072737306 | F21: ='Historical & Forecasted FS'!F44/'Historical & Forecasted FS'!F$8 -> 0.068654737 | G21: ='Historical & Forecasted FS'!G44/'Historical & Forecasted FS'!G$8 -> 0.050347333 | H21: ='Historical & Forecasted FS'!H44/'Historical & Forecasted FS'!H$8 -> 0.040284579 | I21: ='Historical & Forecasted FS'!I44/'Historical & Forecasted FS'!I$8 -> 0.03526219 | J21: ='Historical & Forecasted FS'!J44/'Historical & Forecasted FS'!J$8 -> 0.039711112 | ... L21: ='Historical & Forecasted FS'!L44/'Historical & Forecasted FS'!L$8 -> 0.043677681
B22: ='Historical & Forecasted FS'!B47 -> Net profit | C22: ='Historical & Forecasted FS'!C47/'Historical & Forecasted FS'!C$8 -> 0.21614377 | D22: ='Historical & Forecasted FS'!D47/'Historical & Forecasted FS'!D$8 -> 0.22845774 | E22: ='Historical & Forecasted FS'!E47/'Historical & Forecasted FS'!E$8 -> 0.21186798 | F22: ='Historical & Forecasted FS'!F47/'Historical & Forecasted FS'!F$8 -> 0.21092421 | G22: ='Historical & Forecasted FS'!G47/'Historical & Forecasted FS'!G$8 -> 0.22414202 | H22: ='Historical & Forecasted FS'!H47/'Historical & Forecasted FS'!H$8 -> 0.21238095 | I22: ='Historical & Forecasted FS'!I47/'Historical & Forecasted FS'!I$8 -> 0.20913611 | J22: ='Historical & Forecasted FS'!J47/'Historical & Forecasted FS'!J$8 -> 0.25881793 | ... L22: ='Historical & Forecasted FS'!L47/'Historical & Forecasted FS'!L$8 -> 0.25306234
B24: ="Common Size Balance Sheet -"& " " &'Data Sheet'!$A$4 -> Common Size Balance Sheet - Apple Inc.
B26: Particulars | C26: =C8 -> 2014 | D26: =D8 -> 2015 | E26: =E8 -> 2016 | F26: =F8 -> 2017 | G26: =G8 -> 2018 | H26: =H8 -> 2019 | I26: =I8 -> 2020 | J26: =J8 -> 2021 | ... L26: =L8 -> 2023
B27: ='Historical & Forecasted FS'!B64 -> Cash And Equivalents | C27: ='Historical & Forecasted FS'!C64/'Historical & Forecasted FS'!C$82 -> 0.059713853 | D27: ='Historical & Forecasted FS'!D64/'Historical & Forecasted FS'!D$82 -> 0.072741049 | E27: ='Historical & Forecasted FS'!E64/'Historical & Forecasted FS'!E$82 -> 0.063677002 | F27: ='Historical & Forecasted FS'!F64/'Historical & Forecasted FS'!F$82 -> 0.054058015 | G27: ='Historical & Forecasted FS'!G64/'Historical & Forecasted FS'!G$82 -> 0.070853784 | H27: ='Historical & Forecasted FS'!H64/'Historical & Forecasted FS'!H$82 -> 0.14836522 | I27: ='Historical & Forecasted FS'!I64/'Historical & Forecasted FS'!I$82 -> 0.12284802 | J27: ='Historical & Forecasted FS'!J64/'Historical & Forecasted FS'!J$82 -> 0.10236124 | ... L27: ='Historical & Forecasted FS'!L64/'Historical & Forecasted FS'!L$82 -> 0.087176636
B28: ='Historical & Forecasted FS'!B65 -> Short Term Investments | C28: ='Historical & Forecasted FS'!C65/'Historical & Forecasted FS'!C$82 -> 0.048451727 | D28: ='Historical & Forecasted FS'!D65/'Historical & Forecasted FS'!D$82 -> 0.070540219 | E28: ='Historical & Forecasted FS'!E65/'Historical & Forecasted FS'!E$82 -> 0.14508247 | F28: ='Historical & Forecasted FS'!F65/'Historical & Forecasted FS'!F$82 -> 0.14358985 | G28: ='Historical & Forecasted FS'!G65/'Historical & Forecasted FS'!G$82 -> 0.1104327 | H28: ='Historical & Forecasted FS'!H65/'Historical & Forecasted FS'!H$82 -> 0.15276383 | I28: ='Historical & Forecasted FS'!I65/'Historical & Forecasted FS'!I$82 -> 0.16341143 | J28: ='Historical & Forecasted FS'!J65/'Historical & Forecasted FS'!J$82 -> 0.07891408 | ... L28: ='Historical & Forecasted FS'!L65/'Historical & Forecasted FS'!L$82 -> 0.089595925
B29: ='Historical & Forecasted FS'!B67 -> Accounts Receivable | C29: ='Historical & Forecasted FS'!C67/'Historical & Forecasted FS'!C$82 -> 0.075310884 | D29: ='Historical & Forecasted FS'!D67/'Historical & Forecasted FS'!D$82 -> 0.058030963 | E29: ='Historical & Forecasted FS'!E67/'Historical & Forecasted FS'!E$82 -> 0.048973222 | F29: ='Historical & Forecasted FS'!F67/'Historical & Forecasted FS'!F$82 -> 0.047623488 | G29: ='Historical & Forecasted FS'!G67/'Historical & Forecasted FS'!G$82 -> 0.063397361 | H29: ='Historical & Forecasted FS'!H67/'Historical & Forecasted FS'!H$82 -> 0.067725012 | I29: ='Historical & Forecasted FS'!I67/'Historical & Forecasted FS'!I$82 -> 0.049770291 | J29: ='Historical & Forecasted FS'!J67/'Historical & Forecasted FS'!J$82 -> 0.07486567 | ... L29: ='Historical & Forecasted FS'!L67/'Historical & Forecasted FS'!L$82 -> 0.083690932
B30: ='Historical & Forecasted FS'!B68 -> Other Receivables | C30: ='Historical & Forecasted FS'!C68/'Historical & Forecasted FS'!C$82 -> 0.042093867 | D30: ='Historical & Forecasted FS'!D68/'Historical & Forecasted FS'!D$82 -> 0.046475744 | E30: ='Historical & Forecasted FS'!E68/'Historical & Forecasted FS'!E$82 -> 0.042106278 | F30: ='Historical & Forecasted FS'!F68/'Historical & Forecasted FS'!F$82 -> 0.047423658 | G30: ='Historical & Forecasted FS'!G68/'Historical & Forecasted FS'!G$82 -> 0.070569417 | H30: ='Historical & Forecasted FS'!H68/'Historical & Forecasted FS'!H$82 -> 0.067583216 | I30: ='Historical & Forecasted FS'!I68/'Historical & Forecasted FS'!I$82 -> 0.065840661 | J30: ='Historical & Forecasted FS'!J68/'Historical & Forecasted FS'!J$82 -> 0.071874234 | ... L30: ='Historical & Forecasted FS'!L68/'Historical & Forecasted FS'!L$82 -> 0.089275433
B31: ='Historical & Forecasted FS'!B70 -> Inventory | C31: ='Historical & Forecasted FS'!C70/'Historical & Forecasted FS'!C$82 -> 0.0091054568 | D31: ='Historical & Forecasted FS'!D70/'Historical & Forecasted FS'!D$82 -> 0.0080903752 | E31: ='Historical & Forecasted FS'!E70/'Historical & Forecasted FS'!E$82 -> 0.0066275809 | F31: ='Historical & Forecasted FS'!F70/'Historical & Forecasted FS'!F$82 -> 0.012935663 | G31: ='Historical & Forecasted FS'!G70/'Historical & Forecasted FS'!G$82 -> 0.010816871 | H31: ='Historical & Forecasted FS'!H70/'Historical & Forecasted FS'!H$82 -> 0.012129412 | I31: ='Historical & Forecasted FS'!I70/'Historical & Forecasted FS'!I$82 -> 0.012538285 | J31: ='Historical & Forecasted FS'!J70/'Historical & Forecasted FS'!J$82 -> 0.018746332 | ... L31: ='Historical & Forecasted FS'!L70/'Historical & Forecasted FS'!L$82 -> 0.017956056
B32: ='Historical & Forecasted FS'!B71 -> Other Current Assets | C32: ='Historical & Forecasted FS'!C71/'Historical & Forecasted FS'!C$82 -> 0.041947213 | D32: ='Historical & Forecasted FS'!D71/'Historical & Forecasted FS'!D$82 -> 0.050598426 | E32: ='Historical & Forecasted FS'!E71/'Historical & Forecasted FS'!E$82 -> 0.025748711 | F32: ='Historical & Forecasted FS'!F71/'Historical & Forecasted FS'!F$82 -> 0.03713108 | G32: ='Historical & Forecasted FS'!G71/'Historical & Forecasted FS'!G$82 -> 0.033049422 | H32: ='Historical & Forecasted FS'!H71/'Historical & Forecasted FS'!H$82 -> 0.03642073 | I32: ='Historical & Forecasted FS'!I71/'Historical & Forecasted FS'!I$82 -> 0.034777454 | J32: ='Historical & Forecasted FS'!J71/'Historical & Forecasted FS'!J$82 -> 0.04020205 | ... L32: ='Historical & Forecasted FS'!L71/'Historical & Forecasted FS'!L$82 -> 0.04167813
B33: ='Historical & Forecasted FS'!B72 -> Total Current Assets | C33: ='Historical & Forecasted FS'!C72/'Historical & Forecasted FS'!C$82 -> 0.29559738 | D33: ='Historical & Forecasted FS'!D72/'Historical & Forecasted FS'!D$82 -> 0.30783378 | E33: ='Historical & Forecasted FS'!E72/'Historical & Forecasted FS'!E$82 -> 0.33221527 | F33: ='Historical & Forecasted FS'!F72/'Historical & Forecasted FS'!F$82 -> 0.34276176 | G33: ='Historical & Forecasted FS'!G72/'Historical & Forecasted FS'!G$82 -> 0.35911956 | H33: ='Historical & Forecasted FS'!H72/'Historical & Forecasted FS'!H$82 -> 0.48097874 | I33: ='Historical & Forecasted FS'!I72/'Historical & Forecasted FS'!I$82 -> 0.44371202 | J33: ='Historical & Forecasted FS'!J72/'Historical & Forecasted FS'!J$82 -> 0.38414596 | ... L33: ='Historical & Forecasted FS'!L72/'Historical & Forecasted FS'!L$82 -> 0.40718356
B35: ='Historical & Forecasted FS'!B74 -> Gross Property, Plant & Equipment | C35: ='Historical & Forecasted FS'!C74/'Historical & Forecasted FS'!C$82 -> 0.16828489 | D35: ='Historical & Forecasted FS'!D74/'Historical & Forecasted FS'!D$82 -> 0.1696499 | E35: ='Historical & Forecasted FS'!E74/'Historical & Forecasted FS'!E$82 -> 0.19038752 | F35: ='Historical & Forecasted FS'!F74/'Historical & Forecasted FS'!F$82 -> 0.20003251 | G35: ='Historical & Forecasted FS'!G74/'Historical & Forecasted FS'!G$82 -> 0.24718846 | H35: ='Historical & Forecasted FS'!H74/'Historical & Forecasted FS'!H$82 -> 0.28346371 | I35: ='Historical & Forecasted FS'!I74/'Historical & Forecasted FS'!I$82 -> 0.34609495 | J35: ='Historical & Forecasted FS'!J74/'Historical & Forecasted FS'!J$82 -> 0.34133709 | ... L35: ='Historical & Forecasted FS'!L74/'Historical & Forecasted FS'!L$82 -> 0.35526387
B36: ='Historical & Forecasted FS'!B75 -> Accumulated Depreciation | C36: ='Historical & Forecasted FS'!C75/'Historical & Forecasted FS'!C$82 -> -0.079326602 | D36: ='Historical & Forecasted FS'!D75/'Historical & Forecasted FS'!D$82 -> -0.092255765 | E36: ='Historical & Forecasted FS'!E75/'Historical & Forecasted FS'!E$82 -> -0.10642366 | F36: ='Historical & Forecasted FS'!F75/'Historical & Forecasted FS'!F$82 -> -0.11002108 | G36: ='Historical & Forecasted FS'!G75/'Historical & Forecasted FS'!G$82 -> -0.13425114 | H36: ='Historical & Forecasted FS'!H75/'Historical & Forecasted FS'!H$82 -> -0.17304647 | I36: ='Historical & Forecasted FS'!I75/'Historical & Forecasted FS'!I$82 -> -0.20612063 | J36: ='Historical & Forecasted FS'!J75/'Historical & Forecasted FS'!J$82 -> -0.20023533 | ... L36: ='Historical & Forecasted FS'!L75/'Historical & Forecasted FS'!L$82 -> -0.20104202
B37: ='Historical & Forecasted FS'!B76 -> Net Property, Plant & Equipment | C37: ='Historical & Forecasted FS'!C76/'Historical & Forecasted FS'!C$82 -> 0.088958286 | D37: ='Historical & Forecasted FS'!D76/'Historical & Forecasted FS'!D$82 -> 0.077394135 | E37: ='Historical & Forecasted FS'!E76/'Historical & Forecasted FS'!E$82 -> 0.083963865 | F37: ='Historical & Forecasted FS'!F76/'Historical & Forecasted FS'!F$82 -> 0.09001143 | G37: ='Historical & Forecasted FS'!G76/'Historical & Forecasted FS'!G$82 -> 0.11293732 | H37: ='Historical & Forecasted FS'!H76/'Historical & Forecasted FS'!H$82 -> 0.11041723 | I37: ='Historical & Forecasted FS'!I76/'Historical & Forecasted FS'!I$82 -> 0.13997431 | J37: ='Historical & Forecasted FS'!J76/'Historical & Forecasted FS'!J$82 -> 0.14110176 | ... L37: ='Historical & Forecasted FS'!L76/'Historical & Forecasted FS'!L$82 -> 0.15422184
B38: ='Historical & Forecasted FS'!B77 -> Long-term Investments | C38: ='Historical & Forecasted FS'!C77/'Historical & Forecasted FS'!C$82 -> 0.56143272 | D38: ='Historical & Forecasted FS'!D77/'Historical & Forecasted FS'!D$82 -> 0.56506914 | E38: ='Historical & Forecasted FS'!E77/'Historical & Forecasted FS'!E$82 -> 0.52980235 | F38: ='Historical & Forecasted FS'!F77/'Historical & Forecasted FS'!F$82 -> 0.51879601 | G38: ='Historical & Forecasted FS'!G77/'Historical & Forecasted FS'!G$82 -> 0.46701483 | H38: ='Historical & Forecasted FS'!H77/'Historical & Forecasted FS'!H$82 -> 0.3111847 | I38: ='Historical & Forecasted FS'!I77/'Historical & Forecasted FS'!I$82 -> 0.3114873 | J38: ='Historical & Forecasted FS'!J77/'Historical & Forecasted FS'!J$82 -> 0.36431986 | ... L38: ='Historical & Forecasted FS'!L77/'Historical & Forecasted FS'!L$82 -> 0.28516406
B39: ='Historical & Forecasted FS'!B80 -> Other Long-Term Assets | C39: ='Historical & Forecasted FS'!C80/'Historical & Forecasted FS'!C$82 -> 0.016235405 | D39: ='Historical & Forecasted FS'!D80/'Historical & Forecasted FS'!D$82 -> 0.018674336 | E39: ='Historical & Forecasted FS'!E80/'Historical & Forecasted FS'!E$82 -> 0.027222198 | F39: ='Historical & Forecasted FS'!F80/'Historical & Forecasted FS'!F$82 -> 0.048430802 | G39: ='Historical & Forecasted FS'!G80/'Historical & Forecasted FS'!G$82 -> 0.060928293 | H39: ='Historical & Forecasted FS'!H80/'Historical & Forecasted FS'!H$82 -> 0.097419324 | I39: ='Historical & Forecasted FS'!I80/'Historical & Forecasted FS'!I$82 -> 0.10482636 | J39: ='Historical & Forecasted FS'!J80/'Historical & Forecasted FS'!J$82 -> 0.11043242 | ... L39: ='Historical & Forecasted FS'!L80/'Historical & Forecasted FS'!L$82 -> 0.15343054
B40: ='Historical & Forecasted FS'!B81 -> Total Non-Current Assets | C40: ='Historical & Forecasted FS'!C81/'Historical & Forecasted FS'!C$82 -> 0.70440262 | D40: ='Historical & Forecasted FS'!D81/'Historical & Forecasted FS'!D$82 -> 0.69216622 | E40: ='Historical & Forecasted FS'!E81/'Historical & Forecasted FS'!E$82 -> 0.66778473 | F40: ='Historical & Forecasted FS'!F81/'Historical & Forecasted FS'!F$82 -> 0.65723824 | G40: ='Historical & Forecasted FS'!G81/'Historical & Forecasted FS'!G$82 -> 0.64088044 | H40: ='Historical & Forecasted FS'!H81/'Historical & Forecasted FS'!H$82 -> 0.51902126 | I40: ='Historical & Forecasted FS'!I81/'Historical & Forecasted FS'!I$82 -> 0.55628798 | J40: ='Historical & Forecasted FS'!J81/'Historical & Forecasted FS'!J$82 -> 0.61585404 | ... L40: ='Historical & Forecasted FS'!L81/'Historical & Forecasted FS'!L$82 -> 0.59281644
B41: ='Historical & Forecasted FS'!B82 -> Total Assets | C41: ='Historical & Forecasted FS'!C82/'Historical & Forecasted FS'!C$82 -> 1 | D41: ='Historical & Forecasted FS'!D82/'Historical & Forecasted FS'!D$82 -> 1 | E41: ='Historical & Forecasted FS'!E82/'Historical & Forecasted FS'!E$82 -> 1 | F41: ='Historical & Forecasted FS'!F82/'Historical & Forecasted FS'!F$82 -> 1 | G41: ='Historical & Forecasted FS'!G82/'Historical & Forecasted FS'!G$82 -> 1 | H41: ='Historical & Forecasted FS'!H82/'Historical & Forecasted FS'!H$82 -> 1 | I41: ='Historical & Forecasted FS'!I82/'Historical & Forecasted FS'!I$82 -> 1 | J41: ='Historical & Forecasted FS'!J82/'Historical & Forecasted FS'!J$82 -> 1 | ... L41: ='Historical & Forecasted FS'!L82/'Historical & Forecasted FS'!L$82 -> 1
B43: ='Historical & Forecasted FS'!B84 -> Accounts Payable | C43: ='Historical & Forecasted FS'!C84/'Historical & Forecasted FS'!C$82 -> 0.13024556 | D43: ='Historical & Forecasted FS'!D84/'Historical & Forecasted FS'!D$82 -> 0.12223389 | E43: ='Historical & Forecasted FS'!E84/'Historical & Forecasted FS'!E$82 -> 0.11593293 | F43: ='Historical & Forecasted FS'!F84/'Historical & Forecasted FS'!F$82 -> 0.11787839 | G43: ='Historical & Forecasted FS'!G84/'Historical & Forecasted FS'!G$82 -> 0.15281427 | H43: ='Historical & Forecasted FS'!H84/'Historical & Forecasted FS'!H$82 -> 0.13658439 | I43: ='Historical & Forecasted FS'!I84/'Historical & Forecasted FS'!I$82 -> 0.13058835 | J43: ='Historical & Forecasted FS'!J84/'Historical & Forecasted FS'!J$82 -> 0.15601905 | ... L43: ='Historical & Forecasted FS'!L84/'Historical & Forecasted FS'!L$82 -> 0.17757805
B44: ='Historical & Forecasted FS'!B85 -> Short-term Borrowings | C44: ='Historical & Forecasted FS'!C85/'Historical & Forecasted FS'!C$82 -> 0.079244648 | D44: ='Historical & Forecasted FS'!D85/'Historical & Forecasted FS'!D$82 -> 0.079798171 | E44: ='Historical & Forecasted FS'!E85/'Historical & Forecasted FS'!E$82 -> 0.067966899 | F44: - | G44: - | H44: ='Historical & Forecasted FS'!H85/'Historical & Forecasted FS'!H$82 -> 0.017665339 | I44: ='Historical & Forecasted FS'!I85/'Historical & Forecasted FS'!I$82 -> 0.015425085 | J44: ='Historical & Forecasted FS'!J85/'Historical & Forecasted FS'!J$82 -> 0.01709392 | K44: ='Historical & Forecasted FS'!K85/'Historical & Forecasted FS'!K$82 -> 0.02829726 | L44: ='Historical & Forecasted FS'!L85/'Historical & Forecasted FS'!L$82 -> 0.016974727
B45: ='Historical & Forecasted FS'!B86 -> Curr. Port. of LT Debt | C45: ='Historical & Forecasted FS'!C86/'Historical & Forecasted FS'!C$82 -> 0.027208537 | D45: ='Historical & Forecasted FS'!D86/'Historical & Forecasted FS'!D$82 -> 0.029272073 | E45: ='Historical & Forecasted FS'!E86/'Historical & Forecasted FS'!E$82 -> 0.025195377 | F45: ='Historical & Forecasted FS'!F86/'Historical & Forecasted FS'!F$82 -> 0.031911521 | G45: ='Historical & Forecasted FS'!G86/'Historical & Forecasted FS'!G$82 -> 0.032713104 | H45: ='Historical & Forecasted FS'!H86/'Historical & Forecasted FS'!H$82 -> 0.030308759 | I45: ='Historical & Forecasted FS'!I86/'Historical & Forecasted FS'!I$82 -> 0.027086524 | J45: ='Historical & Forecasted FS'!J86/'Historical & Forecasted FS'!J$82 -> 0.027387308 | ... L45: ='Historical & Forecasted FS'!L86/'Historical & Forecasted FS'!L$82 -> 0.02785727
B46: ='Historical & Forecasted FS'!B87 -> Curr. Port. of Leases | C46: - | D46: ='Historical & Forecasted FS'!D87/'Historical & Forecasted FS'!D$82 -> 0.0086552205 | E46: ='Historical & Forecasted FS'!E87/'Historical & Forecasted FS'!E$82 -> 0.010880175 | F46: ='Historical & Forecasted FS'!F87/'Historical & Forecasted FS'!F$82 -> 0.017307943 | G46: ='Historical & Forecasted FS'!G87/'Historical & Forecasted FS'!G$82 -> 0.024018046 | H46: - | I46: ='Historical & Forecasted FS'!I87/'Historical & Forecasted FS'!I$82 -> 0.0045077311 | J46: ='Historical & Forecasted FS'!J87/'Historical & Forecasted FS'!J$82 -> 0.0043532515 | K46: ='Historical & Forecasted FS'!K87/'Historical & Forecasted FS'!K$82 -> 0.0047143201 | L46: ='Historical & Forecasted FS'!L87/'Historical & Forecasted FS'!L$82 -> 0.0044670333
B47: ='Historical & Forecasted FS'!B88 -> Unearned Revenue, Current | C47: ='Historical & Forecasted FS'!C88/'Historical & Forecasted FS'!C$82 -> 0.036624554 | D47: ='Historical & Forecasted FS'!D88/'Historical & Forecasted FS'!D$82 -> 0.030790956 | E47: ='Historical & Forecasted FS'!E88/'Historical & Forecasted FS'!E$82 -> 0.025117661 | F47: ='Historical & Forecasted FS'!F88/'Historical & Forecasted FS'!F$82 -> 0.020110892 | G47: ='Historical & Forecasted FS'!G88/'Historical & Forecasted FS'!G$82 -> 0.016312803 | H47: ='Historical & Forecasted FS'!H88/'Historical & Forecasted FS'!H$82 -> 0.016312375 | I47: ='Historical & Forecasted FS'!I88/'Historical & Forecasted FS'!I$82 -> 0.020510176 | J47: ='Historical & Forecasted FS'!J88/'Historical & Forecasted FS'!J$82 -> 0.021686486 | ... L47: ='Historical & Forecasted FS'!L88/'Historical & Forecasted FS'!L$82 -> 0.022862702
B48: ='Historical & Forecasted FS'!B89 -> Other Current Liabilities | C48: ='Historical & Forecasted FS'!C89/'Historical & Forecasted FS'!C$82 -> 0.00034938039 | D48: ='Historical & Forecasted FS'!D89/'Historical & Forecasted FS'!D$82 -> 0.0068849128 | E48: ='Historical & Forecasted FS'!E89/'Historical & Forecasted FS'!E$82 -> 0.0005067053 | F48: ='Historical & Forecasted FS'!F89/'Historical & Forecasted FS'!F$82 -> 0.081400089 | G48: ='Historical & Forecasted FS'!G89/'Historical & Forecasted FS'!G$82 -> 0.091125846 | H48: ='Historical & Forecasted FS'!H89/'Historical & Forecasted FS'!H$82 -> 0.11142752 | I48: ='Historical & Forecasted FS'!I89/'Historical & Forecasted FS'!I$82 -> 0.12727857 | J48: ='Historical & Forecasted FS'!J89/'Historical & Forecasted FS'!J$82 -> 0.13095367 | ... L48: ='Historical & Forecasted FS'!L89/'Historical & Forecasted FS'!L$82 -> 0.16238446
B49: ='Historical & Forecasted FS'!B90 -> Total Current Liabilities | C49: ='Historical & Forecasted FS'!C90/'Historical & Forecasted FS'!C$82 -> 0.27367268 | D49: ='Historical & Forecasted FS'!D90/'Historical & Forecasted FS'!D$82 -> 0.27763523 | E49: ='Historical & Forecasted FS'!E90/'Historical & Forecasted FS'!E$82 -> 0.24559975 | F49: ='Historical & Forecasted FS'!F90/'Historical & Forecasted FS'!F$82 -> 0.26860884 | G49: ='Historical & Forecasted FS'!G90/'Historical & Forecasted FS'!G$82 -> 0.31698407 | H49: ='Historical & Forecasted FS'!H90/'Historical & Forecasted FS'!H$82 -> 0.31229838 | I49: ='Historical & Forecasted FS'!I90/'Historical & Forecasted FS'!I$82 -> 0.32539643 | J49: ='Historical & Forecasted FS'!J90/'Historical & Forecasted FS'!J$82 -> 0.35749369 | ... L49: ='Historical & Forecasted FS'!L90/'Historical & Forecasted FS'!L$82 -> 0.41212424
B51: ='Historical & Forecasted FS'!B92 -> Long-Term Debt | C51: ='Historical & Forecasted FS'!C92/'Historical & Forecasted FS'!C$82 -> 0.12503073 | D51: ='Historical & Forecasted FS'!D92/'Historical & Forecasted FS'!D$82 -> 0.18367459 | E51: ='Historical & Forecasted FS'!E92/'Historical & Forecasted FS'!E$82 -> 0.23447399 | F51: ='Historical & Forecasted FS'!F92/'Historical & Forecasted FS'!F$82 -> 0.25899835 | G51: ='Historical & Forecasted FS'!G92/'Historical & Forecasted FS'!G$82 -> 0.25629913 | H51: ='Historical & Forecasted FS'!H92/'Historical & Forecasted FS'!H$82 -> 0.27120432 | I51: ='Historical & Forecasted FS'!I92/'Historical & Forecasted FS'!I$82 -> 0.30463308 | J51: ='Historical & Forecasted FS'!J92/'Historical & Forecasted FS'!J$82 -> 0.31084153 | ... L51: ='Historical & Forecasted FS'!L92/'Historical & Forecasted FS'!L$82 -> 0.27023708
B52: ='Historical & Forecasted FS'!B93 -> Long-Term Leases | C52: - | D52: - | E52: - | F52: - | G52: - | H52: - | I52: ='Historical & Forecasted FS'!I93/'Historical & Forecasted FS'!I$82 -> 0.025879316 | J52: ='Historical & Forecasted FS'!J93/'Historical & Forecasted FS'!J$82 -> 0.029273337 | K52: ='Historical & Forecasted FS'!K93/'Historical & Forecasted FS'!K$82 -> 0.030468739 | L52: ='Historical & Forecasted FS'!L93/'Historical & Forecasted FS'!L$82 -> 0.031955596
B53: ='Historical & Forecasted FS'!B94 -> Unearned Revenue, Non-Current | C53: ='Historical & Forecasted FS'!C94/'Historical & Forecasted FS'!C$82 -> 0.013073728 | D53: ='Historical & Forecasted FS'!D94/'Historical & Forecasted FS'!D$82 -> 0.012481703 | E53: ='Historical & Forecasted FS'!E94/'Historical & Forecasted FS'!E$82 -> 0.0091082609 | F53: ='Historical & Forecasted FS'!F94/'Historical & Forecasted FS'!F$82 -> 0.0075562388 | G53: - | H53: - | I53: - | J53: - | K53: - | L53: -
B54: ='Historical & Forecasted FS'!B95 -> Def. Tax Liability, Non-Curr. | C54: ='Historical & Forecasted FS'!C95/'Historical & Forecasted FS'!C$82 -> 0.087383917 | D54: ='Historical & Forecasted FS'!D95/'Historical & Forecasted FS'!D$82 -> 0.082873823 | E54: ='Historical & Forecasted FS'!E95/'Historical & Forecasted FS'!E$82 -> 0.080883222 | F54: ='Historical & Forecasted FS'!F95/'Historical & Forecasted FS'!F$82 -> 0.083939262 | G54: - | H54: - | I54: - | J54: - | K54: - | L54: -
B55: ='Historical & Forecasted FS'!B96 -> Other Non-Current Liabilities | C55: ='Historical & Forecasted FS'!C96/'Historical & Forecasted FS'!C$82 -> 0.019699015 | D55: ='Historical & Forecasted FS'!D96/'Historical & Forecasted FS'!D$82 -> 0.032254731 | E55: ='Historical & Forecasted FS'!E96/'Historical & Forecasted FS'!E$82 -> 0.031257189 | F55: ='Historical & Forecasted FS'!F96/'Historical & Forecasted FS'!F$82 -> 0.02374247 | G55: ='Historical & Forecasted FS'!G96/'Historical & Forecasted FS'!G$82 -> 0.1337453 | H55: ='Historical & Forecasted FS'!H96/'Historical & Forecasted FS'!H$82 -> 0.1491894 | I55: ='Historical & Forecasted FS'!I96/'Historical & Forecasted FS'!I$82 -> 0.14235785 | J55: ='Historical & Forecasted FS'!J96/'Historical & Forecasted FS'!J$82 -> 0.12264887 | ... L55: ='Historical & Forecasted FS'!L96/'Historical & Forecasted FS'!L$82 -> 0.10942388
B56: ='Historical & Forecasted FS'!B97 -> Total Non-Current Liabilities | C56: ='Historical & Forecasted FS'!C97/'Historical & Forecasted FS'!C$82 -> 0.24518739 | D56: ='Historical & Forecasted FS'!D97/'Historical & Forecasted FS'!D$82 -> 0.31128485 | E56: ='Historical & Forecasted FS'!E97/'Historical & Forecasted FS'!E$82 -> 0.35572266 | F56: ='Historical & Forecasted FS'!F97/'Historical & Forecasted FS'!F$82 -> 0.37423632 | G56: ='Historical & Forecasted FS'!G97/'Historical & Forecasted FS'!G$82 -> 0.39004443 | H56: ='Historical & Forecasted FS'!H97/'Historical & Forecasted FS'!H$82 -> 0.42039372 | I56: ='Historical & Forecasted FS'!I97/'Historical & Forecasted FS'!I$82 -> 0.47287025 | J56: ='Historical & Forecasted FS'!J97/'Historical & Forecasted FS'!J$82 -> 0.46276374 | ... L56: ='Historical & Forecasted FS'!L97/'Historical & Forecasted FS'!L$82 -> 0.41161656
B57: ='Historical & Forecasted FS'!B98 -> Total Liabilities | C57: ='Historical & Forecasted FS'!C98/'Historical & Forecasted FS'!C$82 -> 0.51886007 | D57: ='Historical & Forecasted FS'!D98/'Historical & Forecasted FS'!D$82 -> 0.58892008 | E57: ='Historical & Forecasted FS'!E98/'Historical & Forecasted FS'!E$82 -> 0.60132241 | F57: ='Historical & Forecasted FS'!F98/'Historical & Forecasted FS'!F$82 -> 0.64284515 | G57: ='Historical & Forecasted FS'!G98/'Historical & Forecasted FS'!G$82 -> 0.70702851 | H57: ='Historical & Forecasted FS'!H98/'Historical & Forecasted FS'!H$82 -> 0.7326921 | I57: ='Historical & Forecasted FS'!I98/'Historical & Forecasted FS'!I$82 -> 0.79826668 | J57: ='Historical & Forecasted FS'!J98/'Historical & Forecasted FS'!J$82 -> 0.82025743 | ... L57: ='Historical & Forecasted FS'!L98/'Historical & Forecasted FS'!L$82 -> 0.82374079

Sheet DCF>

Sheet WACC
B6: ="Weighted Average Cost of Capital -"& " " &'Data Sheet'!$A$4 -> Weighted Average Cost of Capital - Apple Inc.
B8: All figures are in USD unless stated otherwise.
B10: Peer comps
G11: Debt/ | H11: Debt/ | I11: Levered | J11: Unlevered
B12: Name of the Comp | C12: Country | D12: Total Debt | E12: Total Equity | F12: Tax Rate 1 | G12: Equity | H12: Capital | I12: Beta 2 | J12: Beta 3
B14: Apple | C14: USA | D14: 108040 | E14: 2806903.7 | F14: 0.1472 | G14: =D14/E14 -> 0.038490811 | H14: =D14/(D14+E14) -> 0.037064181 | I14: ='Regression Beta'!K15 -> 1.1694004 | J14: =I14/(1+(1-F14)*G14) -> 1.1322349
B15: Samsung | C15: USA | D15: 9286 | E15: 393026 | F15: 0.1472 | G15: =D15/E15 -> 0.023626936 | H15: =D15/(D15+E15) -> 0.023081588 | I15: ='Regression Beta'!K23 -> 0.8770317 | J15: =I15/(1+(1-F15)*G15) -> 0.85970937
B16: Microsoft | C16: USA | D16: 111358 | E16: 3082474.5 | F16: 0.1472 | G16: =D16/E16 -> 0.036126171 | H16: =D16/(D16+E16) -> 0.034866575 | I16: ='Regression Beta'!K31 -> 0.91416833 | J16: =I16/(1+(1-F16)*G16) -> 0.88684603
B17: Alphabet | C17: USA | D17: 29867 | E17: 2093387.6 | F17: 0.1472 | G17: =D17/E17 -> 0.014267305 | H17: =D17/(D17+E17) -> 0.014066613 | I17: ='Regression Beta'!K39 -> 1.0383109 | J17: =I17/(1+(1-F17)*G17) -> 1.0258295
B18: Amazon | C18: USA | D18: 161574 | E18: 1936876 | F18: 0.1472 | G18: =D18/E18 -> 0.083419899 | H18: =D18/(D18+E18) -> 0.076996831 | I18: ='Regression Beta'!K47 -> 1.1214972 | J18: =I18/(1+(1-F18)*G18) -> 1.0470123
E20: Average | F20: =AVERAGE(F14:F18) -> 0.1472 | G20: =AVERAGE(G14:G18) -> 0.039186224 | H20: =AVERAGE(H14:H18) -> 0.037215158 | I20: =AVERAGE(I14:I18) -> 1.0240817 | J20: =AVERAGE(J14:J18) -> 0.99032641
E21: Median | F21: =MEDIAN(F14:F18) -> 0.1472 | G21: =MEDIAN(G14:G18) -> 0.036126171 | H21: =MEDIAN(H14:H18) -> 0.034866575 | I21: =MEDIAN(I14:I18) -> 1.0383109 | J21: =MEDIAN(J14:J18) -> 1.0258295
B23: Cost of Debt | E23: Capital Structure
B25: Pre-Tax Cost of Debt | C25: =-'Data Sheet'!L34/WACC!D14 -> 0.036403184 | I25: Current | J25: Target
B26: Tax Rate | C26: =F18 -> 0.1472 | E26: Total Debt | H26: =D14 -> 108040 | I26: =H26/$H$28 -> 0.037064181 | J26: =H20 -> 0.037215158
B27: Post-Tax Cost of Debt | C27: =C25*(1-C26) -> 0.031044635 | E27: Market Capitalization | H27: =E14 -> 2806903.7 | I27: =H27/$H$28 -> 0.96293582 | J27: =J28-J26 -> 0.96278484
E28: Total Capital | H28: =SUM(H26:H27) -> 2914943.7 | I28: =H28/$H$28 -> 1 | J28: =I28 -> 1
E30: Debt/Equity | I30: =I26/I27 -> 0.038490811 | J30: =J26/J27 -> 0.03865366
B32: Cost of Equity | E32: Levered Beta
B34: Risk-Free Rate | C34: 0.045 | E34: Comps Median Unlevered Beta | J34: =J21 -> 1.0258295
B35: Equity-Risk Premium | C35: 0.046 | E35: Target Debt/ Equity | J35: =J30 -> 0.03865366
B36: Levered Beta 4 | C36: =J37 -> 1.0596448 | E36: Tax Rate | J36: =F18 -> 0.1472
B37: Cost of Equity | C37: =C34+C36*(C35) -> 0.093743661 | E37: Levered Beta | J37: =J34*(1+(1-J36)*J35) -> 1.0596448
B39: Notes: | E39: Weighted Average Cost of Capital
B40: 1. Tax Rate considered as the marginal tax rate for the country
B41: 2. Levered beta is based on 5-year monthly data from Yahoo Finance | I41: Total Cost | J41: Total Weight
B42: 3. Unlevered Beta = Levered Beta/(1+(1-Tax Rate)*Debt/Equity) | E42: Debt | I42: =C27 -> 0.031044635 | J42: =J26 -> 0.037215158
B43: 4. Levered Beta = Unlevered Beta*(1+(1-Tax Rate)*Debt/Equity) | E43: Equity | I43: =C37 -> 0.093743661 | J43: =J27 -> 0.96278484
B44: 5. Risk-Free Rate is 10-year US treasury bond yield | E44: Weighted Average Cost of Capital | J44: =SUMPRODUCT(I42:I43,J42:J43) -> 0.091410307
B45: 6. Equity-Risk Premium is the US market premium + Sovereign CDS Spread of US, as provided by Ashwath Damodaran

Sheet Regression Beta
B6: ="Regression Beta - 5 Years Monthly -"& " "&'Data Sheet'!$A$4 -> Regression Beta - 5 Years Monthly - Apple Inc.
B8: Apple Monthly Returns | F8: S&P500 Monthly Returns | J8: Beta Drifting | M8: Samsung Monthly Returns | Q8: Microsoft Monthly Returns | U8: Alphabet Monthly Returns | Y8: Amazon Monthly Returns
B9: Date | C9: Closing Price | D9: Returns | F9: Date | G9: Closing Price | H9: Returns | J9: Apple | M9: Date | N9: Closing Price | O9: Returns | Q9: Date | R9: Closing Price | S9: Returns | U9: Date | V9: Closing Price | W9: Returns | Y9: Date | Z9: Closing Price | AA9: Returns
B10: 43617 | C10: 47.753017 | F10: 43617 | G10: 2941.76 | J10: Levered Raw Beta | K10: =SLOPE(D11:D69,$H$11:$H$69) -> 1.2258672 | M10: 43617 | N10: 30.554236 | Q10: 43617 | R10: 127.98755 | U10: 43617 | V10: 54.045502 | Y10: 43617 | Z10: 94.681503
B11: 43647 | C11: 51.401073 | D11: =C11/C10-1 -> 0.076394252 | F11: 43647 | G11: 2980.3799 | H11: =G11/G10-1 -> 0.013128152 | J11: Raw Beta Weight | K11: 0.75 | M11: 43647 | N11: 29.71174 | O11: =N11/N10-1 -> -0.02757378 | Q11: 43647 | R11: 130.19452 | S11: =R11/R10-1 -> 0.01724363 | U11: 43647 | V11: 60.834 | W11: =V11/V10-1 -> 0.12560709 | Y11: 43647 | Z11: 93.338997 | AA11: =Z11/Z10-1 -> -0.014179179
B12: 43678 | C12: 50.363598 | D12: =C12/C11-1 -> -0.020183917 | F12: 43678 | G12: 2926.46 | H12: =G12/G11-1 -> -0.018091627 | J12: Market Beta | K12: 1 | M12: 43678 | N12: 28.827269 | O12: =N12/N11-1 -> -0.029768386 | Q12: 43678 | R12: 131.71364 | S12: =R12/R11-1 -> 0.011668072 | U12: 43678 | V12: 59.404999 | W12: =V12/V11-1 -> -0.02349017 | Y12: 43678 | Z12: 88.814499 | AA12: =Z12/Z11-1 -> -0.048473823
B13: 43709 | C13: 54.243526 | D13: =C13/C12-1 -> 0.07703834 | F13: 43709 | G13: 2976.74 | H13: =G13/G12-1 -> 0.017181178 | J13: Market Beta Weight | K13: 0.25 | M13: 43709 | N13: 32.13585 | O13: =N13/N12-1 -> 0.11477259 | Q13: 43709 | R13: 133.27379 | S13: =R13/R12-1 -> 0.011845015 | U13: 43709 | V13: 60.950001 | W13: =V13/V12-1 -> 0.026007946 | Y13: 43709 | Z13: 86.795502 | AA13: =Z13/Z12-1 -> -0.022732741
B14: 43739 | C14: 60.247433 | D14: =C14/C13-1 -> 0.11068431 | F14: 43739 | G14: 3037.5601 | H14: =G14/G13-1 -> 0.020431771 | M14: 43739 | N14: 33.259632 | O14: =N14/N13-1 -> 0.034969746 | Q14: 43739 | R14: 137.43411 | S14: =R14/R13-1 -> 0.031216378 | U14: 43739 | V14: 63.005501 | W14: =V14/V13-1 -> 0.033724364 | Y14: 43739 | Z14: 88.833 | AA14: =Z14/Z13-1 -> 0.023474696
B15: 43770 | C15: 64.725533 | D15: =C15/C14-1 -> 0.074328478 | F15: 43770 | G15: 3140.98 | H15: =G15/G14-1 -> 0.034047037 | J15: Adjusted Beta | K15: =K10*K11+(K12*K13) -> 1.1694004 | M15: 43770 | N15: 33.193637 | O15: =N15/N14-1 -> -0.001984263 | Q15: 43770 | R15: 145.11247 | S15: =R15/R14-1 -> 0.05586939 | U15: 43770 | V15: 65.248001 | W15: =V15/V14-1 -> 0.03559213 | Y15: 43770 | Z15: 90.040001 | AA15: =Z15/Z14-1 -> 0.013587304
B16: 43800 | C16: 71.332909 | D16: =C16/C15-1 -> 0.10208299 | F16: 43800 | G16: 3230.78 | H16: =G16/G15-1 -> 0.028589819 | M16: 43800 | N16: 36.82316 | O16: =N16/N15-1 -> 0.10934396 | Q16: 43800 | R16: 151.68518 | S16: =R16/R15-1 -> 0.045293887 | U16: 43800 | V16: 66.850998 | W16: =V16/V15-1 -> 0.024567756 | Y16: 43800 | Z16: 92.391998 | AA16: =Z16/Z15-1 -> 0.02612169
B17: 43831 | C17: 75.185593 | D17: =C17/C16-1 -> 0.05400991 | F17: 43831 | G17: 3225.52 | H17: =G17/G16-1 -> -0.0016280926 | J17: Samsung | M17: 43831 | N17: 37.458468 | O17: =N17/N16-1 -> 0.017252928 | Q17: 43831 | R17: 163.73729 | S17: =R17/R16-1 -> 0.079454749 | U17: 43831 | V17: 71.711502 | W17: =V17/V16-1 -> 0.072706529 | Y17: 43831 | Z17: 100.436 | AA17: =Z17/Z16-1 -> 0.087063806
B18: 43862 | C18: 66.404114 | D18: =C18/C17-1 -> -0.11679736 | F18: 43862 | G18: 2954.22 | H18: =G18/G17-1 -> -0.084110484 | J18: Levered Raw Beta | K18: =SLOPE(O11:O69,$H$11:$H$69) -> 0.83604227 | M18: 43862 | N18: 35.997317 | O18: =N18/N17-1 -> -0.039007208 | Q18: 43862 | R18: 155.83079 | S18: =R18/R17-1 -> -0.048287681 | U18: 43862 | V18: 66.966499 | W18: =V18/V17-1 -> -0.066167949 | Y18: 43862 | Z18: 94.1875 | AA18: =Z18/Z17-1 -> -0.06221372
B19: 43891 | C19: 61.918247 | D19: =C19/C18-1 -> -0.067554052 | F19: 43891 | G19: 2584.5901 | H19: =G19/G18-1 -> -0.12511928 | J19: Raw Beta Weight | K19: 0.75 | M19: 43891 | N19: 31.713509 | O19: =N19/N18-1 -> -0.11900353 | Q19: 43891 | R19: 152.10918 | S19: =R19/R18-1 -> -0.02388243 | U19: 43891 | V19: 58.140499 | W19: =V19/V18-1 -> -0.13179724 | Y19: 43891 | Z19: 97.486 | AA19: =Z19/Z18-1 -> 0.035020571
B20: 43922 | C20: 71.538727 | D20: =C20/C19-1 -> 0.15537391 | F20: 43922 | G20: 2912.4299 | H20: =G20/G19-1 -> 0.12684404 | J20: Market Beta | K20: 1 | M20: 43922 | N20: 33.453047 | O20: =N20/N19-1 -> 0.054851629 | Q20: 43922 | R20: 172.84563 | S20: =R20/R19-1 -> 0.13632609 | U20: 43922 | V20: 67.432999 | W20: =V20/V19-1 -> 0.15982835 | Y20: 43922 | Z20: 123.7 | AA20: =Z20/Z19-1 -> 0.26890012
B21: 43952 | C21: 77.416687 | D21: =C21/C20-1 -> 0.082164727 | F21: 43952 | G21: 3044.3101 | H21: =G21/G20-1 -> 0.04528182 | J21: Market Beta Weight | K21: 0.25 | M21: 43952 | N21: 33.921386 | O21: =N21/N20-1 -> 0.013999893 | Q21: 43952 | R21: 176.74214 | S21: =R21/R20-1 -> 0.022543324 | U21: 43952 | V21: 71.445999 | W21: =V21/V20-1 -> 0.059510923 | Y21: 43952 | Z21: 122.1185 | AA21: =Z21/Z20-1 -> -0.01278494
B22: 43983 | C22: 89.067291 | D22: =C22/C21-1 -> 0.15049215 | F22: 43983 | G22: 3100.29 | H22: =G22/G21-1 -> 0.018388396 | M22: 43983 | N22: 35.326415 | O22: =N22/N21-1 -> 0.041420146 | Q22: 43983 | R22: 196.82927 | S22: =R22/R21-1 -> 0.11365216 | U22: 43983 | V22: 70.680496 | W22: =V22/V21-1 -> -0.010714428 | Y22: 43983 | Z22: 137.94099 | AA22: =Z22/Z21-1 -> 0.12956672
B23: 44013 | C23: 103.77511 | D23: =C23/C22-1 -> 0.16513152 | F23: 44013 | G23: 3271.1201 | H23: =G23/G22-1 -> 0.055101321 | J23: Adjusted Beta | K23: =K18*K19+(K20*K21) -> 0.8770317 | M23: 44013 | N23: 38.99763 | O23: =N23/N22-1 -> 0.10392266 | Q23: 44013 | R23: 198.28008 | S23: =R23/R22-1 -> 0.0073708855 | U23: 44013 | V23: 74.148003 | W23: =V23/V22-1 -> 0.049058895 | Y23: 44013 | Z23: 158.23399 | AA23: =Z23/Z22-1 -> 0.14711363
B24: 44044 | C24: 126.02241 | D24: =C24/C23-1 -> 0.21437993 | F24: 44044 | G24: 3500.3101 | H24: =G24/G23-1 -> 0.070064667 | M24: 44044 | N24: 36.370847 | O24: =N24/N23-1 -> -0.067357509 | Q24: 44044 | R24: 218.12642 | S24: =R24/R23-1 -> 0.10009248 | U24: 44044 | V24: 81.709 | W24: =V24/V23-1 -> 0.10197169 | Y24: 44044 | Z24: 172.548 | AA24: =Z24/Z23-1 -> 0.09046103
B25: 44075 | C25: 113.30572 | D25: =C25/C24-1 -> -0.10090817 | F25: 44075 | G25: 3363 | H25: =G25/G24-1 -> -0.03922797 | J25: Microsoft | M25: 44075 | N25: 39.199696 | O25: =N25/N24-1 -> 0.077777938 | Q25: 44075 | R25: 203.91715 | S25: =R25/R24-1 -> -0.06514238 | U25: 44075 | V25: 73.480003 | W25: =V25/V24-1 -> -0.10071102 | Y25: 44075 | Z25: 157.43649 | AA25: =Z25/Z24-1 -> -0.087578591
B26: 44105 | C26: 106.50603 | D26: =C26/C25-1 -> -0.060011888 | F26: 44105 | G26: 3269.96 | H26: =G26/G25-1 -> -0.027665786 | J26: Levered Raw Beta | K26: =SLOPE(S11:S69,$H$11:$H$69) -> 0.88555778 | M26: 44105 | N26: 38.35655 | O26: =N26/N25-1 -> -0.021508998 | Q26: 44105 | R26: 196.29683 | S26: =R26/R25-1 -> -0.037369668 | U26: 44105 | V26: 81.050499 | W26: =V26/V25-1 -> 0.10302798 | Y26: 44105 | Z26: 151.80749 | AA26: =Z26/Z25-1 -> -0.035754087
B27: 44136 | C27: 116.47565 | D27: =C27/C26-1 -> 0.093606158 | F27: 44136 | G27: 3621.6299 | H27: =G27/G26-1 -> 0.10754564 | J27: Raw Beta Weight | K27: 0.75 | M27: 44136 | N27: 45.201096 | O27: =N27/N26-1 -> 0.1784453 | Q27: 44136 | R27: 207.54315 | S27: =R27/R26-1 -> 0.057292433 | U27: 44136 | V27: 88.037003 | W27: =V27/V26-1 -> 0.086199395 | Y27: 44136 | Z27: 158.40199 | AA27: =Z27/Z26-1 -> 0.043439871
B28: 44166 | C28: 130.04471 | D28: =C28/C27-1 -> 0.11649698 | F28: 44166 | G28: 3756.0701 | H28: =G28/G27-1 -> 0.037121459 | J28: Market Beta | K28: 1 | M28: 44166 | N28: 54.891882 | O28: =N28/N27-1 -> 0.21439271 | Q28: 44166 | R28: 216.20311 | S28: =R28/R27-1 -> 0.04172606 | U28: 44166 | V28: 87.594002 | W28: =V28/V27-1 -> -0.0050319864 | Y28: 44166 | Z28: 162.8465 | AA28: =Z28/Z27-1 -> 0.028058384
B29: 44197 | C29: 129.32924 | D29: =C29/C28-1 -> -0.0055017156 | F29: 44197 | G29: 3714.24 | H29: =G29/G28-1 -> -0.011136661 | J29: Market Beta Weight | K29: 0.25 | M29: 44197 | N29: 56.968067 | O29: =N29/N28-1 -> 0.037823182 | Q29: 44197 | R29: 225.47646 | S29: =R29/R28-1 -> 0.042891825 | U29: 44197 | V29: 91.787003 | W29: =V29/V28-1 -> 0.047868586 | Y29: 44197 | Z29: 160.31 | AA29: =Z29/Z28-1 -> -0.015576012
B30: 44228 | C30: 118.84254 | D30: =C30/C29-1 -> -0.081085314 | F30: 44228 | G30: 3811.1499 | H30: =G30/G29-1 -> 0.026091451 | M30: 44228 | N30: 57.315428 | O30: =N30/N29-1 -> 0.006097462 | Q30: 44228 | R30: 225.88469 | S30: =R30/R29-1 -> 0.0018105349 | U30: 44228 | V30: 101.843 | W30: =V30/V29-1 -> 0.10955798 | Y30: 44228 | Z30: 154.6465 | AA30: =Z30/Z29-1 -> -0.035328414
B31: 44256 | C31: 119.89371 | D31: =C31/C30-1 -> 0.0088450653 | F31: 44256 | G31: 3972.8899 | H31: =G31/G30-1 -> 0.042438633 | J31: Adjusted Beta | K31: =K26*K27+(K28*K29) -> 0.91416833 | M31: 44256 | N31: 56.551222 | O31: =N31/N30-1 -> -0.01333334 | Q31: 44256 | R31: 229.70778 | S31: =R31/R30-1 -> 0.016924963 | U31: 44256 | V31: 103.4315 | W31: =V31/V30-1 -> 0.015597547 | Y31: 44256 | Z31: 154.70399 | AA31: =Z31/Z30-1 -> 0.00037178339
B32: 44287 | C32: 129.03174 | D32: =C32/C31-1 -> 0.07621777 | F32: 44287 | G32: 4181.1699 | H32: =G32/G31-1 -> 0.052425321 | M32: 44287 | N32: 56.872313 | O32: =N32/N31-1 -> 0.0056778724 | Q32: 44287 | R32: 245.69582 | S32: =R32/R31-1 -> 0.069601635 | U32: 44287 | V32: 120.506 | W32: =V32/V31-1 -> 0.16508021 | Y32: 44287 | Z32: 173.371 | AA32: =Z32/Z31-1 -> 0.12066273
B33: 44317 | C33: 122.30827 | D33: =C33/C32-1 -> -0.052107118 | F33: 44317 | G33: 4204.1099 | H33: =G33/G32-1 -> 0.0054864886 | J33: Alphabet | M33: 44317 | N33: 56.174481 | O33: =N33/N32-1 -> -0.012270146 | Q33: 44317 | R33: 243.2601 | S33: =R33/R32-1 -> -0.0099135388 | U33: 44317 | V33: 120.578 | W33: =V33/V32-1 -> 0.00059753043 | Y33: 44317 | Z33: 161.1535 | AA33: =Z33/Z32-1 -> -0.070470257
B34: 44348 | C34: 134.65848 | D34: =C34/C33-1 -> 0.1009761 | F34: 44348 | G34: 4297.5 | H34: =G34/G33-1 -> 0.02221401 | J34: Levered Raw Beta | K34: =SLOPE(W11:W69,$H$11:$H$69) -> 1.0510813 | M34: 44348 | N34: 56.314046 | O34: =N34/N33-1 -> 0.0024844939 | Q34: 44348 | R34: 264.54395 | S34: =R34/R33-1 -> 0.087494184 | U34: 44348 | V34: 125.316 | W34: =V34/V33-1 -> 0.039294058 | Y34: 44348 | Z34: 172.008 | AA34: =Z34/Z33-1 -> 0.067354993
B35: 44378 | C35: 143.40892 | D35: =C35/C34-1 -> 0.064982481 | F35: 44378 | G35: 4395.2598 | H35: =G35/G34-1 -> 0.022748055 | J35: Raw Beta Weight | K35: 0.75 | M35: 44378 | N35: 55.02137 | O35: =N35/N34-1 -> -0.022954769 | Q35: 44378 | R35: 278.22525 | S35: =R35/R34-1 -> 0.051716568 | U35: 44378 | V35: 135.22099 | W35: =V35/V34-1 -> 0.079040113 | Y35: 44378 | Z35: 166.3795 | AA35: =Z35/Z34-1 -> -0.032722287
B36: 44409 | C36: 149.27861 | D36: =C36/C35-1 -> 0.040929741 | F36: 44409 | G36: 4522.6802 | H36: =G36/G35-1 -> 0.028990416 | J36: Market Beta | K36: 1 | M36: 44409 | N36: 53.759734 | O36: =N36/N35-1 -> -0.022929934 | Q36: 44409 | R36: 294.79712 | S36: =R36/R35-1 -> 0.059562779 | U36: 44409 | V36: 145.46201 | W36: =V36/V35-1 -> 0.075735378 | Y36: 44409 | Z36: 173.5395 | AA36: =Z36/Z35-1 -> 0.043034172
B37: 44440 | C37: 139.33061 | D37: =C37/C36-1 -> -0.066640478 | F37: 44440 | G37: 4307.54 | H37: =G37/G36-1 -> -0.047569169 | J37: Market Beta Weight | K37: 0.25 | M37: 44440 | N37: 51.937368 | O37: =N37/N36-1 -> -0.033898338 | Q37: 44440 | R37: 275.83246 | S37: =R37/R36-1 -> -0.064331229 | U37: 44440 | V37: 133.2655 | W37: =V37/V36-1 -> -0.083846658 | Y37: 44440 | Z37: 164.252 | AA37: =Z37/Z36-1 -> -0.053518108
B38: 44470 | C38: 147.50337 | D38: =C38/C37-1 -> 0.058657318 | F38: 44470 | G38: 4605.3799 | H38: =G38/G37-1 -> 0.069143836 | M38: 44470 | N38: 49.156038 | O38: =N38/N37-1 -> -0.053551625 | Q38: 44470 | R38: 324.45932 | S38: =R38/R37-1 -> 0.1762913 | U38: 44470 | V38: 148.27049 | W38: =V38/V37-1 -> 0.11259471 | Y38: 44470 | Z38: 168.62151 | AA38: =Z38/Z37-1 -> 0.026602459
B39: 44501 | C39: 162.76576 | D39: =C39/C38-1 -> 0.10347147 | F39: 44501 | G39: 4567 | H39: =G39/G38-1 -> -0.0083337062 | J39: Adjusted Beta | K39: =K34*K35+(K36*K37) -> 1.0383109 | M39: 44501 | N39: 50.212399 | O39: =N39/N38-1 -> 0.021489966 | Q39: 44501 | R39: 323.45154 | S39: =R39/R38-1 -> -0.003106035 | U39: 44501 | V39: 142.452 | W39: =V39/V38-1 -> -0.039242447 | Y39: 44501 | Z39: 175.3535 | AA39: =Z39/Z38-1 -> 0.039923698
B40: 44531 | C40: 175.1028 | D40: =C40/C39-1 -> 0.07579626 | F40: 44531 | G40: 4766.1802 | H40: =G40/G39-1 -> 0.043612914 | M40: 44531 | N40: 55.142077 | O40: =N40/N39-1 -> 0.098176501 | Q40: 44531 | R40: 329.65982 | S40: =R40/R39-1 -> 0.019193858 | U40: 44531 | V40: 144.6795 | W40: =V40/V39-1 -> 0.015636903 | Y40: 44531 | Z40: 166.71699 | AA40: =Z40/Z39-1 -> -0.049251968
B41: 44562 | C41: 172.35159 | D41: =C41/C40-1 -> -0.015711942 | F41: 44562 | G41: 4515.5498 | H41: =G41/G40-1 -> -0.052585165 | J41: Amazon | M41: 44562 | N41: 51.853991 | O41: =N41/N40-1 -> -0.059629345 | Q41: 44562 | R41: 304.82159 | S41: =R41/R40-1 -> -0.075345024 | U41: 44562 | V41: 135.6985 | W41: =V41/V40-1 -> -0.062075151 | Y41: 44562 | Z41: 149.5735 | AA41: =Z41/Z40-1 -> -0.10282991
B42: 44593 | C42: 162.82581 | D42: =C42/C41-1 -> -0.055269504 | F42: 44593 | G42: 4373.9399 | H42: =G42/G41-1 -> -0.031360492 | J42: Levered Raw Beta | K42: =SLOPE(AA11:AA69,$H$11:$H$69) -> 1.1619963 | M42: 44593 | N42: 50.863599 | O42: =N42/N41-1 -> -0.019099624 | Q42: 44593 | R42: 292.87302 | S42: =R42/R41-1 -> -0.039198594 | U42: 44593 | V42: 134.89101 | W42: =V42/V41-1 -> -0.0059506626 | Y42: 44593 | Z42: 153.563 | AA42: =Z42/Z41-1 -> 0.026672519
B43: 44621 | C43: 172.40332 | D43: =C43/C42-1 -> 0.058820615 | F43: 44621 | G43: 4530.4102 | H43: =G43/G42-1 -> 0.035773288 | J43: Raw Beta Weight | K43: 0.75 | M43: 44621 | N43: 49.23653 | O43: =N43/N42-1 -> -0.031988873 | Q43: 44621 | R43: 302.82935 | S43: =R43/R42-1 -> 0.033995382 | U43: 44621 | V43: 139.64951 | W43: =V43/V42-1 -> 0.035276629 | Y43: 44621 | Z43: 162.9975 | AA43: =Z43/Z42-1 -> 0.061437285
B44: 44652 | C44: 155.65765 | D44: =C44/C43-1 -> -0.097130763 | F44: 44652 | G44: 4131.9302 | H44: =G44/G43-1 -> -0.087956712 | J44: Market Beta | K44: 1 | M44: 44652 | N44: 47.926667 | O44: =N44/N43-1 -> -0.026603491 | Q44: 44652 | R44: 272.58667 | S44: =R44/R43-1 -> -0.099867058 | U44: 44652 | V44: 114.9665 | W44: =V44/V43-1 -> -0.17674969 | Y44: 44652 | Z44: 124.2815 | AA44: =Z44/Z43-1 -> -0.23752509
B45: 44682 | C45: 146.95897 | D45: =C45/C44-1 -> -0.055883439 | F45: 44682 | G45: 4132.1499 | H45: =G45/G44-1 -> 5.3177569e-05 | J45: Market Beta Weight | K45: 0.25 | M45: 44682 | N45: 47.926667 | O45: =N45/N44-1 -> 0 | Q45: 44682 | R45: 267.03711 | S45: =R45/R44-1 -> -0.020358886 | U45: 44682 | V45: 114.039 | W45: =V45/V44-1 -> -0.0080675502 | Y45: 44682 | Z45: 120.2095 | AA45: =Z45/Z44-1 -> -0.032764321
B46: 44713 | C46: 135.19049 | D46: =C46/C45-1 -> -0.080080026 | F46: 44713 | G46: 3785.3799 | H46: =G46/G45-1 -> -0.08392 | M46: 44713 | N46: 40.531456 | O46: =N46/N45-1 -> -0.15430262 | Q46: 44713 | R46: 252.85205 | S46: =R46/R45-1 -> -0.053120175 | U46: 44713 | V46: 109.3725 | W46: =V46/V45-1 -> -0.040920237 | Y46: 44713 | Z46: 106.21 | AA46: =Z46/Z45-1 -> -0.11645921
B47: 44743 | C47: 160.69197 | D47: =C47/C46-1 -> 0.18863368 | F47: 44743 | G47: 4130.29 | H47: =G47/G46-1 -> 0.091116392 | J47: Adjusted Beta | K47: =K42*K43+(K44*K45) -> 1.1214972 | M47: 44743 | N47: 43.927166 | O47: =N47/N46-1 -> 0.083779612 | Q47: 44743 | R47: 276.39166 | S47: =R47/R46-1 -> 0.093096385 | U47: 44743 | V47: 116.64 | W47: =V47/V46-1 -> 0.066447243 | Y47: 44743 | Z47: 134.95 | AA47: =Z47/Z46-1 -> 0.27059597
B48: 44774 | C48: 155.46115 | D48: =C48/C47-1 -> -0.032551844 | F48: 44774 | G48: 3955 | H48: =G48/G47-1 -> -0.042440128 | M48: 44774 | N48: 42.710938 | O48: =N48/N47-1 -> -0.027687367 | Q48: 44774 | R48: 257.4202 | S48: =R48/R47-1 -> -0.068639791 | U48: 44774 | V48: 109.15 | W48: =V48/V47-1 -> -0.064214652 | Y48: 44774 | Z48: 126.77 | AA48: =Z48/Z47-1 -> -0.060615044
B49: 44805 | C49: 136.84374 | D49: =C49/C48-1 -> -0.11975607 | F49: 44805 | G49: 3585.6201 | H49: =G49/G48-1 -> -0.093395672 | M49: 44805 | N49: 37.989126 | O49: =N49/N48-1 -> -0.11055278 | Q49: 44805 | R49: 229.77937 | S49: =R49/R48-1 -> -0.10737628 | U49: 44805 | V49: 96.150002 | W49: =V49/V48-1 -> -0.11910215 | Y49: 44805 | Z49: 113 | AA49: =Z49/Z48-1 -> -0.10862189
B50: 44835 | C50: 151.83517 | D50: =C50/C49-1 -> 0.10955153 | F50: 44835 | G50: 3871.98 | H50: =G50/G49-1 -> 0.079863414 | M50: 44835 | N50: 42.788306 | O50: =N50/N49-1 -> 0.12633037 | Q50: 44835 | R50: 229.01968 | S50: =R50/R49-1 -> -0.0033061671 | U50: 44835 | V50: 94.660004 | W50: =V50/V49-1 -> -0.015496599 | Y50: 44835 | Z50: 102.44 | AA50: =Z50/Z49-1 -> -0.09345131
B51: 44866 | C51: 146.57727 | D51: =C51/C50-1 -> -0.034629025 | F51: 44866 | G51: 4080.1101 | H51: =G51/G50-1 -> 0.053752893 | M51: 44866 | N51: 44.805263 | O51: =N51/N50-1 -> 0.047138036 | Q51: 44866 | R51: 251.72137 | S51: =R51/R50-1 -> 0.099125501 | U51: 44866 | V51: 101.45 | W51: =V51/V50-1 -> 0.071730327 | Y51: 44866 | Z51: 96.540001 | AA51: =Z51/Z50-1 -> -0.057594698
B52: 44896 | C52: 128.86833 | D52: =C52/C51-1 -> -0.12081641 | F52: 44896 | G52: 3839.5 | H52: =G52/G51-1 -> -0.058971474 | M52: 44896 | N52: 39.834905 | O52: =N52/N51-1 -> -0.11093245 | Q52: 44896 | R52: 237.27345 | S52: =R52/R51-1 -> -0.057396485 | U52: 44896 | V52: 88.730003 | W52: =V52/V51-1 -> -0.12538191 | Y52: 44896 | Z52: 84 | AA52: =Z52/Z51-1 -> -0.12989435
B53: 44927 | C53: 143.11099 | D53: =C53/C52-1 -> 0.11052102 | F53: 44927 | G53: 4076.6001 | H53: =G53/G52-1 -> 0.061752858 | M53: 44927 | N53: 44.505525 | O53: =N53/N52-1 -> 0.11724943 | Q53: 44927 | R53: 245.1786 | S53: =R53/R52-1 -> 0.033316626 | U53: 44927 | V53: 99.870003 | W53: =V53/V52-1 -> 0.12554942 | Y53: 44927 | Z53: 103.13 | AA53: =Z53/Z52-1 -> 0.22773806
B54: 44958 | C54: 146.2055 | D54: =C54/C53-1 -> 0.021623168 | F54: 44958 | G54: 3970.1499 | H54: =G54/G53-1 -> -0.026112494 | M54: 44958 | N54: 43.925646 | O54: =N54/N53-1 -> -0.013029385 | Q54: 44958 | R54: 246.77148 | S54: =R54/R53-1 -> 0.0064968149 | U54: 44958 | V54: 90.300003 | W54: =V54/V53-1 -> -0.095824569 | Y54: 44958 | Z54: 94.230003 | AA54: =Z54/Z53-1 -> -0.08629879
B55: 44986 | C55: 163.80232 | D55: =C55/C54-1 -> 0.12035673 | F55: 44986 | G55: 4109.3101 | H55: =G55/G54-1 -> 0.035051613 | M55: 44986 | N55: 46.39012 | O55: =N55/N54-1 -> 0.056105598 | Q55: 44986 | R55: 285.95306 | S55: =R55/R54-1 -> 0.15877677 | U55: 44986 | V55: 104 | W55: =V55/V54-1 -> 0.15171646 | Y55: 44986 | Z55: 103.29 | AA55: =Z55/Z54-1 -> 0.096147699
B56: 45017 | C56: 168.55049 | D56: =C56/C55-1 -> 0.02898719 | F56: 45017 | G56: 4169.48 | H56: =G56/G55-1 -> 0.014642341 | M56: 45017 | N56: 47.752324 | O56: =N56/N55-1 -> 0.0293641 | Q56: 45017 | R56: 304.75879 | S56: =R56/R55-1 -> 0.065765076 | U56: 45017 | V56: 108.22 | W56: =V56/V55-1 -> 0.040576933 | Y56: 45017 | Z56: 105.45 | AA56: =Z56/Z55-1 -> 0.020911956
B57: 45047 | C57: 176.07011 | D57: =C57/C56-1 -> 0.044613474 | F57: 45047 | G57: 4179.8301 | H57: =G57/G56-1 -> 0.0024823475 | M57: 45047 | N57: 52.053681 | O57: =N57/N56-1 -> 0.090076389 | Q57: 45047 | R57: 325.7168 | S57: =R57/R56-1 -> 0.068769167 | U57: 45047 | V57: 123.37 | W57: =V57/V56-1 -> 0.13999262 | Y57: 45047 | Z57: 120.58 | AA57: =Z57/Z56-1 -> 0.14348037
B58: 45078 | C58: 192.94531 | D58: =C58/C57-1 -> 0.095843631 | F58: 45078 | G58: 4450.3799 | H58: =G58/G57-1 -> 0.064727465 | M58: 45078 | N58: 52.636917 | O58: =N58/N57-1 -> 0.011204503 | Q58: 45078 | R58: 338.50623 | S58: =R58/R57-1 -> 0.039265488 | U58: 45078 | V58: 120.97 | W58: =V58/V57-1 -> -0.019453692 | Y58: 45078 | Z58: 130.36 | AA58: =Z58/Z57-1 -> 0.081107968
B59: 45108 | C59: 195.4122 | D59: =C59/C58-1 -> 0.012785426 | F59: 45108 | G59: 4588.96 | H59: =G59/G58-1 -> 0.031138932 | M59: 45108 | N59: 51.141157 | O59: =N59/N58-1 -> -0.028416552 | Q59: 45108 | R59: 333.91382 | S59: =R59/R58-1 -> -0.013566687 | U59: 45108 | V59: 133.11 | W59: =V59/V58-1 -> 0.10035546 | Y59: 45108 | Z59: 133.67999 | AA59: =Z59/Z58-1 -> 0.025467873
... B69: 45413 | C69: 182.80206 | D69: =C69/C68-1 -> 0.074678584 | F69: 45413 | G69: 5222.6802 | H69: =G69/G68-1 -> 0.037132992 | M69: 45413 | N69: 57.498 | O69: =N69/N68-1 -> 0.0025806452 | Q69: 45413 | R69: 414.73999 | S69: =R69/R68-1 -> 0.06526598 | U69: 45413 | V69: 170.28999 | W69: =V69/V68-1 -> 0.034317262 | Y69: 45413 | Z69: 187.07001 | AA69: =Z69/Z68-1 -> 0.068971469

Sheet Intrinsic Growth
A6: # | B6: Calculation of ROIC | F6: ='Historical & Forecasted FS'!H6 -> 2019 | G6: ='Historical & Forecasted FS'!I6 -> 2020 | H6: ='Historical & Forecasted FS'!J6 -> 2021 | I6: ='Historical & Forecasted FS'!K6 -> 2022 | J6: ='Historical & Forecasted FS'!L6 -> 2023
B8: ='Historical & Forecasted FS'!B65 -> Short Term Investments | F8: ='Historical & Forecasted FS'!H65 -> 51713 | G8: ='Historical & Forecasted FS'!I65 -> 52927 | H8: ='Historical & Forecasted FS'!J65 -> 27699 | I8: ='Historical & Forecasted FS'!K65 -> 24658 | J8: ='Historical & Forecasted FS'!L65 -> 31590
B9: ='Historical & Forecasted FS'!B67 -> Accounts Receivable | F9: ='Historical & Forecasted FS'!H67 -> 22926 | G9: ='Historical & Forecasted FS'!I67 -> 16120 | H9: ='Historical & Forecasted FS'!J67 -> 26278 | I9: ='Historical & Forecasted FS'!K67 -> 28184 | J9: ='Historical & Forecasted FS'!L67 -> 29508
B10: ='Historical & Forecasted FS'!B68 -> Other Receivables | F10: ='Historical & Forecasted FS'!H68 -> 22878 | G10: ='Historical & Forecasted FS'!I68 -> 21325 | H10: ='Historical & Forecasted FS'!J68 -> 25228 | I10: ='Historical & Forecasted FS'!K68 -> 32748 | J10: ='Historical & Forecasted FS'!L68 -> 31477
B11: ='Historical & Forecasted FS'!B70 -> Inventory | F11: ='Historical & Forecasted FS'!H70 -> 4106 | G11: ='Historical & Forecasted FS'!I70 -> 4061 | H11: ='Historical & Forecasted FS'!J70 -> 6580 | I11: ='Historical & Forecasted FS'!K70 -> 4946 | J11: ='Historical & Forecasted FS'!L70 -> 6331
B12: ='Historical & Forecasted FS'!B71 -> Other Current Assets | F12: ='Historical & Forecasted FS'!H71 -> 12329 | G12: ='Historical & Forecasted FS'!I71 -> 11264 | H12: ='Historical & Forecasted FS'!J71 -> 14111 | I12: ='Historical & Forecasted FS'!K71 -> 21223 | J12: ='Historical & Forecasted FS'!L71 -> 14695
B13: ='Historical & Forecasted FS'!B72 -> Total Current Assets | F13: =SUM(F8:F12) -> 113952 | G13: =SUM(G8:G12) -> 105697 | H13: =SUM(H8:H12) -> 99896 | I13: =SUM(I8:I12) -> 111759 | J13: =SUM(J8:J12) -> 113601
B15: ='Historical & Forecasted FS'!B84 -> Accounts Payable
B16: ='Historical & Forecasted FS'!B85 -> Short-term Borrowings | F16: ='Historical & Forecasted FS'!H84 -> 46236 | G16: ='Historical & Forecasted FS'!I84 -> 42296 | H16: ='Historical & Forecasted FS'!J84 -> 54763 | I16: ='Historical & Forecasted FS'!K84 -> 64115 | J16: ='Historical & Forecasted FS'!L84 -> 62611
B17: ='Historical & Forecasted FS'!B86 -> Curr. Port. of LT Debt | F17: ='Historical & Forecasted FS'!H85 -> 5980 | G17: ='Historical & Forecasted FS'!I85 -> 4996 | H17: ='Historical & Forecasted FS'!J85 -> 6000 | I17: ='Historical & Forecasted FS'!K85 -> 9982 | J17: ='Historical & Forecasted FS'!L85 -> 5985
B18: ='Historical & Forecasted FS'!B87 -> Curr. Port. of Leases | F18: ='Historical & Forecasted FS'!H86 -> 10260 | G18: ='Historical & Forecasted FS'!I86 -> 8773 | H18: ='Historical & Forecasted FS'!J86 -> 9613 | I18: ='Historical & Forecasted FS'!K86 -> 11128 | J18: ='Historical & Forecasted FS'!L86 -> 9822
B19: ='Historical & Forecasted FS'!B88 -> Unearned Revenue, Current | F19: ='Historical & Forecasted FS'!H87 -> - | G19: ='Historical & Forecasted FS'!I87 -> 1460 | H19: ='Historical & Forecasted FS'!J87 -> 1528 | I19: ='Historical & Forecasted FS'!K87 -> 1663 | J19: ='Historical & Forecasted FS'!L87 -> 1575
B20: ='Historical & Forecasted FS'!B89 -> Other Current Liabilities | F20: ='Historical & Forecasted FS'!H88 -> 5522 | G20: ='Historical & Forecasted FS'!I88 -> 6643 | H20: ='Historical & Forecasted FS'!J88 -> 7612 | I20: ='Historical & Forecasted FS'!K88 -> 7912 | J20: ='Historical & Forecasted FS'!L88 -> 8061
B21: ='Historical & Forecasted FS'!B90 -> Total Current Liabilities | F21: =SUM(F16:F20) -> 67998 | G21: =SUM(G16:G20) -> 64168 | H21: =SUM(H16:H20) -> 79516 | I21: =SUM(I16:I20) -> 94800 | J21: =SUM(J16:J20) -> 88054
A23: # | B23: Net Working Capital | F23: =F13-F21 -> 45954 | G23: =G13-G21 -> 41529 | H23: =H13-H21 -> 20380 | I23: =I13-I21 -> 16959 | J23: =J13-J21 -> 25547
B25: ='Historical & Forecasted FS'!B74 -> Gross Property, Plant & Equipment | F25: ='Historical & Forecasted FS'!H74 -> 95957 | G25: ='Historical & Forecasted FS'!I74 -> 112096 | H25: ='Historical & Forecasted FS'!J74 -> 119810 | I25: ='Historical & Forecasted FS'!K74 -> 124874 | J25: ='Historical & Forecasted FS'!L74 -> 125260
B26: ='Historical & Forecasted FS'!B76 -> Net Property, Plant & Equipment | F26: ='Historical & Forecasted FS'!H76 -> 37378 | G26: ='Historical & Forecasted FS'!I76 -> 45336 | H26: ='Historical & Forecasted FS'!J76 -> 49527 | I26: ='Historical & Forecasted FS'!K76 -> 52534 | J26: ='Historical & Forecasted FS'!L76 -> 54376
B27: ='Historical & Forecasted FS'!B77 -> Long-term Investments | F27: ='Historical & Forecasted FS'!H77 -> 105341 | G27: ='Historical & Forecasted FS'!I77 -> 100887 | H27: ='Historical & Forecasted FS'!J77 -> 127877 | I27: ='Historical & Forecasted FS'!K77 -> 120805 | J27: ='Historical & Forecasted FS'!L77 -> 100544
B28: ='Historical & Forecasted FS'!B78 -> Goodwill | F28: ='Historical & Forecasted FS'!H78 -> - | G28: ='Historical & Forecasted FS'!I78 -> - | H28: ='Historical & Forecasted FS'!J78 -> - | I28: ='Historical & Forecasted FS'!K78 -> - | J28: ='Historical & Forecasted FS'!L78 -> -
B29: ='Historical & Forecasted FS'!B79 -> Other Intangibles | F29: ='Historical & Forecasted FS'!H79 -> - | G29: ='Historical & Forecasted FS'!I79 -> - | H29: ='Historical & Forecasted FS'!J79 -> - | I29: ='Historical & Forecasted FS'!K79 -> - | J29: ='Historical & Forecasted FS'!L79 -> -
B30: ='Historical & Forecasted FS'!B80 -> Other Long-Term Assets | F30: ='Historical & Forecasted FS'!H80 -> 32978 | G30: ='Historical & Forecasted FS'!I80 -> 33952 | H30: ='Historical & Forecasted FS'!J80 -> 38762 | I30: ='Historical & Forecasted FS'!K80 -> 44011 | J30: ='Historical & Forecasted FS'!L80 -> 54097
B31: Gross Block | F31: =SUM(F25:F30) -> 271654 | G31: =SUM(G25:G30) -> 292271 | H31: =SUM(H25:H30) -> 335976 | I31: =SUM(I25:I30) -> 342224 | J31: =SUM(J25:J30) -> 334277
B32: ='Historical & Forecasted FS'!B75 -> Accumulated Depreciation | F32: ='Historical & Forecasted FS'!H75 -> -58579 | G32: ='Historical & Forecasted FS'!I75 -> -66760 | H32: ='Historical & Forecasted FS'!J75 -> -70283 | I32: ='Historical & Forecasted FS'!K75 -> -72340 | J32: ='Historical & Forecasted FS'!L75 -> -70884
A33: # | B33: Net Non-Current Assets | F33: =SUM(F31:F32) -> 213075 | G33: =SUM(G31:G32) -> 225511 | H33: =SUM(H31:H32) -> 265693 | I33: =SUM(I31:I32) -> 269884 | J33: =SUM(J31:J32) -> 263393
A35: # | B35: Invested Capital | F35: =F33+F23 -> 259029 | G35: =G33+G23 -> 267040 | H35: =H33+H23 -> 286073 | I35: =I33+I23 -> 286843 | J35: =J33+J23 -> 288940
B36: EBIT | F36: ='Historical & Forecasted FS'!H23 -> 63930 | G36: ='Historical & Forecasted FS'!I23 -> 66288 | H36: ='Historical & Forecasted FS'!J23 -> 108949 | I36: ='Historical & Forecasted FS'!K23 -> 119437 | J36: ='Historical & Forecasted FS'!L23 -> 114301
A38: # | B38: ROIC | F38: =F36/F35 -> 0.24680634 | G38: =G36/G35 -> 0.24823247 | H38: =H36/H35 -> 0.38084335 | I38: =I36/I35 -> 0.41638457 | J38: =J36/J35 -> 0.39558732
A40: # | B40: Calculation of Reinvestment Rate | F40: =F6 -> 2019 | G40: =G6 -> 2020 | H40: =H6 -> 2021 | I40: =I6 -> 2022 | J40: =J6 -> 2023
B42: Net Capex | F42: =('Historical & Forecasted FS'!H74-'Historical & Forecasted FS'!G74)+'Historical & Forecasted FS'!H38 -> 18101 | G42: =('Historical & Forecasted FS'!I74-'Historical & Forecasted FS'!H74)+'Historical & Forecasted FS'!I38 -> 27195 | H42: =('Historical & Forecasted FS'!J74-'Historical & Forecasted FS'!I74)+'Historical & Forecasted FS'!J38 -> 18998 | I42: =('Historical & Forecasted FS'!K74-'Historical & Forecasted FS'!J74)+'Historical & Forecasted FS'!K38 -> 16168 | J42: =('Historical & Forecasted FS'!L74-'Historical & Forecasted FS'!K74)+'Historical & Forecasted FS'!L38 -> 11905
B43: Change in Working Capital | G43: =G23-F23 -> -4425 | H43: =H23-G23 -> -21149 | I43: =I23-H23 -> -3421 | J43: =J23-I23 -> 8588
B45: EBIT | F45: =F36 -> 63930 | G45: =G36 -> 66288 | H45: =H36 -> 108949 | I45: =I36 -> 119437 | J45: =J36 -> 114301
B46: Marginal Tax Rate | F46: {=WACC!F14:F18} -> 0.1472 | G46: 0.1472 | H46: 0.1472 | I46: 0.1472 | J46: 0.1472
B48: Reinvestment | G48: =SUM(G42:G43) -> 22770 | H48: =SUM(H42:H43) -> -2151 | I48: =SUM(I42:I43) -> 12747 | J48: =SUM(J42:J43) -> 20493
A49: # | B49: Reinvestment Rate | G49: =G48/(G45*(1-G46)) -> 0.40279208 | H49: =H48/(H45*(1-H46)) -> -0.023151011 | I49: =I48/(I45*(1-I46)) -> 0.12514742 | J49: =J48/(J45*(1-J46)) -> 0.2102366
H51: 4-year Average | J51: =AVERAGE(G49:J49) -> 0.17875627
H52: 4-year Median | J52: =MEDIAN(G49:J49) -> 0.16769201
A54: # | B54: Calculation of Growth Rate | F54: =F40 -> 2019 | G54: =G40 -> 2020 | H54: =H40 -> 2021 | I54: =I40 -> 2022 | J54: =J40 -> 2023
B56: Reinvestment Rate | G56: =G49 -> 0.40279208 | H56: =H49 -> -0.023151011 | I56: =I49 -> 0.12514742 | J56: =J49 -> 0.2102366
B57: ROIC | G57: =G38 -> 0.24823247 | H57: =H38 -> 0.38084335 | I57: =I38 -> 0.41638457 | J57: =J38 -> 0.39558732
A59: # | B59: Intrinsic Growth Rate | G59: =G56*G57 -> 0.099986075 | H59: =H56*H57 -> -0.0088169088 | I59: =I56*I57 -> 0.052109456 | J59: =J56*J57 -> 0.083166932
H61: 4-year Average | J61: =AVERAGE(G59:J59) -> 0.056611388
H62: 4-year Median | J62: =MEDIAN(G59:J59) -> 0.067638194

Sheet DCF
B6: Calculation of PV of FCFF | F6: ='Historical & Forecasted FS'!L6 -> 2023 | G6: ='Historical & Forecasted FS'!N6 -> 2024 | H6: ='Historical & Forecasted FS'!O6 -> 2025 | I6: ='Historical & Forecasted FS'!P6 -> 2026 | J6: ='Historical & Forecasted FS'!Q6 -> 2027 | K6: ='Historical & Forecasted FS'!R6 -> 2028
B8: EBIT | F8: ='Historical & Forecasted FS'!L23 -> 114301 | G8: ='Historical & Forecasted FS'!N23 -> 125971.87 | H8: ='Historical & Forecasted FS'!O23 -> 140195.12 | I8: ='Historical & Forecasted FS'!P23 -> 158259.51 | J8: ='Historical & Forecasted FS'!Q23 -> 179875.13 | K8: ='Historical & Forecasted FS'!R23 -> 205689.43
B9: Tax Rate | F9: =WACC!F14 -> 0.1472 | G9: =F9 -> 0.1472 | H9: =G9 -> 0.1472 | I9: =H9 -> 0.1472 | J9: =I9 -> 0.1472 | K9: =J9 -> 0.1472
B10: Less: Reinvestment Rate | F10: ='Intrinsic Growth'!$J$52 -> 0.16769201 | G10: =F10 -> 0.16769201 | H10: =G10 -> 0.16769201 | I10: =H10 -> 0.16769201 | J10: =I10 -> 0.16769201 | K10: =J10 -> 0.16769201
B11: Add: Depreciation | F11: ='Historical & Forecasted FS'!L26 -> 11519 | G11: ='Historical & Forecasted FS'!N26 -> 12531.867 | H11: ='Historical & Forecasted FS'!O26 -> 12885.333 | I11: ='Historical & Forecasted FS'!P26 -> 12885 | J11: ='Historical & Forecasted FS'!Q26 -> 12885 | K11: ='Historical & Forecasted FS'!R26 -> 12885
B12: Less: Increase in NWC | F12: =('Historical & Forecasted FS'!L72-'Historical & Forecasted FS'!L90)-('Historical & Forecasted FS'!K72-'Historical & Forecasted FS'!K90) -> 16835 | G12: ='Historical & Forecasted FS'!N72-'Historical & Forecasted FS'!N90-('Historical & Forecasted FS'!L72-'Historical & Forecasted FS'!L90) -> 10985.273 | H12: ='Historical & Forecasted FS'!O72-'Historical & Forecasted FS'!O90-('Historical & Forecasted FS'!N72-'Historical & Forecasted FS'!N90) -> 8795.3273 | I12: ='Historical & Forecasted FS'!P72-'Historical & Forecasted FS'!P90-('Historical & Forecasted FS'!O72-'Historical & Forecasted FS'!O90) -> 8540.4997 | J12: ='Historical & Forecasted FS'!Q72-'Historical & Forecasted FS'!Q90-('Historical & Forecasted FS'!P72-'Historical & Forecasted FS'!P90) -> 11562.747 | K12: ='Historical & Forecasted FS'!R72-'Historical & Forecasted FS'!R90-('Historical & Forecasted FS'!Q72-'Historical & Forecasted FS'!Q90) -> 14022.222
B13: Less: Capex | F13: =-'Historical & Forecasted FS'!L128 -> 10959 | G13: =-'Historical & Forecasted FS'!N128 -> 11258 | H13: =-'Historical & Forecasted FS'!O128 -> 12768 | I13: =-'Historical & Forecasted FS'!P128 -> 13282 | J13: =-'Historical & Forecasted FS'!Q128 -> 15576 | K13: =-'Historical & Forecasted FS'!R128 -> 18765
B14: Free Cashflow to Firm (FCFF) | F14: =(F8*(1-F9))+F11-F12-F13 -> 81200.893 | G14: =(G8*(1-G9))+G11-G12-G13 -> 97717.402 | H14: =(H8*(1-H9))+H11-H12-H13 -> 110880.41 | I14: =(I8*(1-I9))+I11-I12-I13 -> 126026.21 | J14: =(J8*(1-J9))+J11-J12-J13 -> 139143.76 | K14: =(K8*(1-K9))+K11-K12-K13 -> 155509.72
B15: Mid Year Convention | G15: 0.5 | H15: =G15+1 -> 1.5 | I15: =H15+1 -> 2.5 | J15: =I15+1 -> 3.5 | K15: =J15+1 -> 4.5
B16: Discounting Factor | G16: =1/(1+$E$21)^G15 -> 0.95720724 | H16: =1/(1+$E$21)^H15 -> 0.87703702 | I16: =1/(1+$E$21)^I15 -> 0.8035814 | J16: =1/(1+$E$21)^J15 -> 0.736278 | K16: =1/(1+$E$21)^K15 -> 0.67461155
B17: PV of FCFF | G17: =G14*G16 -> 93535.805 | H17: =H14*H16 -> 97246.22 | I17: =I14*I16 -> 101272.32 | J17: =J14*J16 -> 102448.49 | K17: =K14*K16 -> 104908.66
B19: Expected Growth Rate | E19: 0.0845
B20: Terminal Growth Rate | E20: 0.0212
B21: WACC | E21: =WACC!J44 -> 0.091410307
B23: Calculation of Terminal Value
B25: FCFF (n+1) | E25: =K14*(1+E20) -> 158806.53
B26: WACC | E26: =E21 -> 0.091410307
B27: Terminal Growth Rate | E27: =E20 -> 0.0212
B28: Terminal Value | E28: =E25/(E26-E27) -> 2261869.2
B30: Calculation of Equity Value per Share | G30: Sensitivity Analysis
G31: =E34 -> 2025294.6 | H31: 0.07 | I31: =WACC!J44 -> 0.091410307 | J31: 0.11 | K31: 0.13
B32: PV of FCFF | E32: =SUM(G17:K17) -> 499411.49 | G32: 0.01 | H32: 2477603.4 | I32: 1815371.6 | J32: 1471368.5 | K32: 1221063
B33: PV of Terminal Value | E33: =E28*K16 -> 1525883.1 | G33: 0.02 | H33: 2868012.6 | I33: 1999653.2 | J33: 1581693.2 | K33: 1290476.1
B34: Enterprise Value | E34: =SUM(E32:E33) -> 2025294.6 | G34: =E20 -> 0.0212 | H34: 2925614 | I34: 2025294.6 | J34: 1596601.9 | K34: 1299663.1
G35: 0.03 | H35: 3453626.5 | I35: 2243951.2 | J35: 1719598.9 | K35: 1373771.8
B36: Add: Cash | E36: ='Historical & Forecasted FS'!L64 -> 30737 | G36: 0.04 | H36: 4429649.6 | I36: 2583287.8 | J36: 1896906.4 | K36: 1475577.7
B37: Less: Debt | E37: =SUM('Historical & Forecasted FS'!L85:L87,'Historical & Forecasted FS'!L92:L93) -> 123930
B38: Equity Value | E38: =SUM(E34:E36)-E37 -> 1932101.6
B39: No. of shares | E39: 15465
B40: Equity Value per Share | E40: =E38/E39 -> 124.93382
B42: Share Price | E42: 186.28
B43: Discount/Premium | E43: =E42/E40 -> 1.4910294
B45: Notes:
B46: 1. Reinvestment rate of 36.38% is the industry average of Software (Systems & Applications) found under "Fundamental GR in EBIT by Industry", by Aswath Damodaran
B47: 2. Expected Growth rate is the average expected growth in EBIT of the Software (Systems & Applications) found under "Fundamental GR in EBIT of Industry", by Aswath Damodaran
B48: 3. Terminal Growth rate is the 6-year long-term GDP growth of USA, by Statista

Sheet Relative Valuation
B6: ="Comparable Company Valuation -"& " "&'Data Sheet'!$A$4 -> Comparable Company Valuation - Apple Inc.
E8: Market Data | K8: Financials | O8: Valuation
B9: Company | D9: Ticker | E9: Share Price | F9: Shares Outstanding | G9: Equity Value | H9: Net Debt | I9: Enterprise Value | K9: Revenue | L9: EBITDA | M9: Net Income | O9: EV/Revenue | P9: EV/EBITDA | Q9: P/E
B10: Apple | D10: AAPL | E10: ='Data Sheet'!G286 -> 189.75 | F10: ='Data Sheet'!F286 -> 15441.9 | G10: =F10*E10 -> 2930100.5 | H10: ='Data Sheet'!E286 -> -38169 | I10: ='Data Sheet'!H286 -> 2836524.8 | K10: ='Data Sheet'!I286 -> 385706 | L10: ='Data Sheet'!K286*'Data Sheet'!I286 -> 129982.92 | M10: ='Data Sheet'!J286 -> 100913 | O10: =$I10/$K10 -> 7.3541112 | P10: =$I10/$L10 -> 21.822288 | Q10: =$G10/$M10 -> 29.035907
B11: Alphabet | D11: GOOGL | E11: ='Data Sheet'!G276 -> 170.34 | F11: ='Data Sheet'!F276 -> 12377 | G11: =E11*F11 -> 2108298.2 | H11: ='Data Sheet'!E276 -> -81049 | I11: ='Data Sheet'!H276 -> 2037514.3 | K11: ='Data Sheet'!I276 -> 307394 | L11: ='Data Sheet'!K276*'Data Sheet'!I276 -> 100210.44 | M11: ='Data Sheet'!J276 -> 73795 | O11: =$I11/$K11 -> 6.6283477 | P11: =$I11/$L11 -> 20.332355 | Q11: =$G11/$M11 -> 28.569662
B12: Microsoft | D12: MSFT | E12: ='Data Sheet'!G277 -> 423.3 | F12: ='Data Sheet'!F277 -> 7432.3 | G12: =E12*F12 -> 3146092.6 | H12: ='Data Sheet'!E277 -> -31815 | I12: ='Data Sheet'!H277 -> 3122217.3 | K12: ='Data Sheet'!I277 -> 227583 | L12: ='Data Sheet'!K277*'Data Sheet'!I277 -> 118343.16 | M12: ='Data Sheet'!J277 -> 82541 | O12: =$I12/$K12 -> 13.719027 | P12: =$I12/$L12 -> 26.382744 | Q12: =$G12/$M12 -> 38.115513
B13: Amazon | D13: AMZN | E13: ='Data Sheet'!G279 -> 186.12 | F13: ='Data Sheet'!F279 -> 10406.6 | G13: =E13*F13 -> 1936876.4 | H13: ='Data Sheet'!E279 -> 74794 | I13: ='Data Sheet'!H279 -> 2022253.8 | K13: ='Data Sheet'!I279 -> 574785 | L13: ='Data Sheet'!K279*'Data Sheet'!I279 -> 85642.965 | M13: ='Data Sheet'!J279 -> 30425 | O13: =$I13/$K13 -> 3.5182787 | P13: =$I13/$L13 -> 23.612608 | Q13: =$G13/$M13 -> 63.660687
B14: Samsung | D14: SSNLF | E14: ='Data Sheet'!G280 -> 57.86 | F14: ='Data Sheet'!F280 -> 6792.7 | G14: =E14*F14 -> 393025.62 | H14: ='Data Sheet'!E280 -> -58910.1 | I14: ='Data Sheet'!H280 -> 324119.8 | K14: ='Data Sheet'!I280 -> 191340.6 | L14: ='Data Sheet'!K280*'Data Sheet'!I280 -> 32527.902 | M14: ='Data Sheet'!J280 -> 10695.1 | O14: =$I14/$K14 -> 1.6939416 | P14: =$I14/$L14 -> 9.9643623 | Q14: =$G14/$M14 -> 36.748195
B15: HP | D15: HPQ | E15: ='Data Sheet'!G281 -> 31.36 | F15: ='Data Sheet'!F281 -> 978.5 | G15: =E15*F15 -> 30685.76 | H15: ='Data Sheet'!E281 -> 7565 | I15: ='Data Sheet'!H281 -> 39202.2 | K15: ='Data Sheet'!I281 -> 53105 | L15: ='Data Sheet'!K281*'Data Sheet'!I281 -> 5204.29 | M15: ='Data Sheet'!J281 -> 3416 | O15: =$I15/$K15 -> 0.73820168 | P15: =$I15/$L15 -> 7.5326702 | Q15: =$G15/$M15 -> 8.9829508
B16: Dell | D16: DELL | E16: ='Data Sheet'!G282 -> 149.16 | F16: ='Data Sheet'!F282 -> 713.8 | G16: =E16*F16 -> 106470.41 | H16: ='Data Sheet'!E282 -> 19485 | I16: ='Data Sheet'!H282 -> 126049 | K16: ='Data Sheet'!I282 -> 88425 | L16: ='Data Sheet'!K282*'Data Sheet'!I282 -> 8754.075 | M16: ='Data Sheet'!J282 -> 3211 | O16: =$I16/$K16 -> 1.4254905 | P16: =$I16/$L16 -> 14.398894 | Q16: =$G16/$M16 -> 33.158022
B17: Tencent Holdings | D17: SEHK | E17: ='Data Sheet'!G283 -> 48.88 | F17: ='Data Sheet'!F283 -> 9281.2 | G17: =E17*F17 -> 453665.06 | H17: ='Data Sheet'!E283 -> -1096 | I17: ='Data Sheet'!H283 -> 456885 | K17: ='Data Sheet'!I283 -> 84328.9 | L17: ='Data Sheet'!K283*'Data Sheet'!I283 -> 25467.328 | M17: ='Data Sheet'!J283 -> 15953.7 | O17: =$I17/$K17 -> 5.4178935 | P17: =$I17/$L17 -> 17.940045 | Q17: =$G17/$M17 -> 28.436354
B19: High | O19: =MAX(O10:O17) -> 13.719027 | P19: =MAX(P10:P17) -> 26.382744 | Q19: =MAX(Q10:Q17) -> 63.660687
B20: 75th Percentile | O20: =QUARTILE(O10:O17,3) -> 6.8097885 | P20: =QUARTILE(P10:P17,3) -> 22.269868 | Q20: =QUARTILE(Q10:Q17,3) -> 37.090025
B21: Average | O21: =AVERAGE(O10:O17) -> 5.0619115 | P21: =AVERAGE(P10:P17) -> 17.748246 | Q21: =AVERAGE(Q10:Q17) -> 33.338411
B22: Median | O22: =QUARTILE(O10:O17,2) -> 4.4680861 | P22: =QUARTILE(P10:P17,2) -> 19.1362 | Q22: =QUARTILE(Q10:Q17,2) -> 31.096965
B23: 25th Percentile | O23: =QUARTILE(O10:O17,1) -> 1.6268288 | P23: =QUARTILE(P10:P17,1) -> 13.290261 | Q23: =QUARTILE(Q10:Q17,1) -> 28.536335
B24: Low | O24: =MIN(O10:O17) -> 0.73820168 | P24: =MIN(P10:P17) -> 7.5326702 | Q24: =MIN(Q10:Q17) -> 8.9829508
B26: Comparable Valuation | O26: EV/Revenue | P26: EV/EBITDA | Q26: P/E
B28: Implied Enterprise Value | O28: =O$22*K$10 -> 1723367.6 | P28: =P$22*L$10 -> 2487379.2 | Q28: =Q29+Q30 -> 3099919
B29: Net Debt | O29: =$H$10 -> -38169 | P29: =$H$10 -> -38169 | Q29: =$H$10 -> -38169
B30: Implied Market Value | O30: =O28-O29 -> 1761536.6 | P30: =P28-P29 -> 2525548.2 | Q30: =Q22*M10 -> 3138088
B31: Shares Outstanding | O31: =$F$10 -> 15441.9 | P31: =$F$10 -> 15441.9 | Q31: =$F$10 -> 15441.9
B32: Implied Value per Share | O32: =O30/O31 -> 114.07512 | P32: =P30/P31 -> 163.55165 | Q32: =Q30/Q31 -> 203.21903
O34: =IF(O$32>$E$10,"Undervalued","Overvalued") -> Overvalued | P34: =IF(P$32>$E$10,"Undervalued","Overvalued") -> Overvalued | Q34: =IF(Q$32>$E$10,"Undervalued","Overvalued") -> Undervalued
B35: Notes:
B36: 1. The data to compute Apple comparable valuation is from Yahoo Finance

Sheet Risk
B6: ="Calculation of monthly VAR using Historical and Monte Carlo Simulation approach -"& " "&'Data Sheet'!$A$4 -> Calculation of monthly VAR using Historical and Monte Carlo Simulation approach - Apple Inc.
B8: Date | C8: Closing Price | D8: Return | E8: Sorted Returns | F8: Replication | G8: Simulated Returns | I8: Monthly VAR - Historical
B9: 31048 | C9: 0.099919 | D9: =(C9-C10)/C10 -> -0.69395156 | E9: #DIV/0! | F9: 1 | G9: =_xlfn.NORM.INV(RAND(),$L$10,$L$11) -> -0.055840742
B10: 36892 | C10: 0.326481 | D10: =(C10-C11)/C11 -> 1.3617825 | E10: 0.45378563 | F10: 2 | G10: =_xlfn.NORM.INV(RAND(),$L$10,$L$11) -> 0.2085766 | I10: Mean | L10: =AVERAGE(E10:E482) -> 0.023699244
B11: 35796 | C11: 0.138235 | D11: =(C11-C12)/C12 -> -0.27710812 | E11: 0.39522795 | F11: 3 | G11: =_xlfn.NORM.INV(RAND(),$L$10,$L$11) -> 0.0078560497 | I11: Standard Deviation | L11: =_xlfn.STDEV.S(E10:E482) -> 0.12188043
B12: 31778 | C12: 0.191225 | D12: =(C12-C13)/C13 -> -0.75828022 | E12: 0.37036612 | F12: 4 | G12: =_xlfn.NORM.INV(RAND(),$L$10,$L$11) -> 0.10738937 | I12: Min | L12: =MIN(E10:E482) -> -0.57743621
B13: 38261 | C13: 0.791102 | D13: =(C13-C14)/C14 -> 2.5081506 | E13: 0.35225795 | F13: 5 | G13: =_xlfn.NORM.INV(RAND(),$L$10,$L$11) -> -0.13024675 | I13: Max | L13: =MAX(E10:E482) -> 0.45378563
B14: 34243 | C14: 0.225504 | D14: =(C14-C15)/C15 -> -0.39491253 | E14: 0.31551345 | F14: 6 | G14: =_xlfn.NORM.INV(RAND(),$L$10,$L$11) -> -0.16706507 | I14: Current market price | L14: 191.73
B15: 31990 | C15: 0.37268 | D15: =(C15-C16)/C16 -> -0.059598939 | E15: 0.30909142 | F15: 7 | G15: =_xlfn.NORM.INV(RAND(),$L$10,$L$11) -> 0.12869124
B16: 33239 | C16: 0.396299 | D16: =(C16-C17)/C17 -> 1.2221792 | E16: 0.29069544 | F16: 8 | G16: =_xlfn.NORM.INV(RAND(),$L$10,$L$11) -> -0.38568375
B17: 35827 | C17: 0.178338 | D17: =(C17-C18)/C18 -> -0.44505746 | E17: 0.29010743 | F17: 9 | G17: =_xlfn.NORM.INV(RAND(),$L$10,$L$11) -> 0.042047751 | I17: Percentile | J17: Confidence | K17: VAR % | L17: Stock Price | M17: VAR ($)
B18: 34608 | C18: 0.321363 | D18: =(C18-C19)/C19 -> 0.039928938 | E18: 0.28200597 | F18: 10 | G18: =_xlfn.NORM.INV(RAND(),$L$10,$L$11) -> -0.012036175 | I18: 0.05 | J18: =1-I18 -> 0.95 | K18: =_xlfn.PERCENTILE.INC($E$10:$E$482,I18) -> -0.15626113 | L18: =$L$14*(1+K18) -> 161.77005 | M18: =-($L$14-L18) -> -29.959947
B19: 36130 | C19: 0.309024 | D19: =(C19-C20)/C20 -> -0.11005388 | E19: 0.28179986 | F19: 11 | G19: =_xlfn.NORM.INV(RAND(),$L$10,$L$11) -> 0.115219 | I19: 0.01 | J19: =1-I19 -> 0.99 | K19: =_xlfn.PERCENTILE.INC($E$10:$E$482,I19) -> -0.30528163 | L19: =$L$14*(1+K19) -> 133.19835 | M19: =-($L$14-L19) -> -58.531646
B20: 36251 | C20: 0.347239 | D20: =(C20-C21)/C21 -> -0.65697303 | E20: 0.27999749 | F20: 12 | G20: =_xlfn.NORM.INV(RAND(),$L$10,$L$11) -> -0.021344343 | I20: 0.005 | J20: =1-I20 -> 0.995 | K20: =_xlfn.PERCENTILE.INC($E$10:$E$482,I20) -> -0.3206602 | L20: =$L$14*(1+K20) -> 130.24982 | M20: =-($L$14-L20) -> -61.48018
B21: 38292 | C21: 1.012279 | D21: =(C21-C22)/C22 -> 2.4801767 | E21: 0.27958089 | F21: 13 | G21: =_xlfn.NORM.INV(RAND(),$L$10,$L$11) -> 0.094714397 | I21: 0.1 | J21: =1-I21 -> 0.9 | K21: =_xlfn.PERCENTILE.INC($E$10:$E$482,I21) -> -0.11961468 | L21: =$L$14*(1+K21) -> 168.79628 | M21: =-($L$14-L21) -> -22.933723
B22: 32112 | C22: 0.29087 | D22: =(C22-C23)/C23 -> 0.1643789 | E22: 0.27550506 | F22: 14 | G22: =_xlfn.NORM.INV(RAND(),$L$10,$L$11) -> 0.015493134
B23: 34516 | C23: 0.249807 | D23: =(C23-C24)/C24 -> -0.58698596 | E23: 0.27123069 | F23: 15 | G23: =_xlfn.NORM.INV(RAND(),$L$10,$L$11) -> 0.078054974 | I23: Monthly VAR - Monte Carlo Simulation
B24: 36434 | C24: 0.604839 | D24: =(C24-C25)/C25 -> 1.2318947 | E24: 0.26554948 | F24: 16 | G24: =_xlfn.NORM.INV(RAND(),$L$10,$L$11) -> 0.024441495
B25: 37742 | C25: 0.270998 | D25: =(C25-C26)/C26 -> 0.12361517 | E25: 0.26230524 | F25: 17 | G25: =_xlfn.NORM.INV(RAND(),$L$10,$L$11) -> 0.026249036 | I25: Mean | L25: =AVERAGE(G10:G482) -> 0.032154807
B26: 31809 | C26: 0.241184 | D26: =(C26-C27)/C27 -> -0.69498372 | E26: 0.26125768 | F26: 18 | G26: =_xlfn.NORM.INV(RAND(),$L$10,$L$11) -> -0.087246742 | I26: Standard Deviation | L26: =_xlfn.STDEV.S(G10:G482) -> 0.12170378
B27: 36678 | C27: 0.790725 | D27: =(C27-C28)/C28 -> 3.8160905 | E27: 0.24702329 | F27: 19 | G27: =_xlfn.NORM.INV(RAND(),$L$10,$L$11) -> 0.32646687 | I27: Min | L27: =MIN(G10:G482) -> -0.38568375
B28: 35643 | C28: 0.164184 | D28: =(C28-C29)/C29 -> -0.97137403 | E28: 0.24285779 | F28: 20 | G28: =_xlfn.NORM.INV(RAND(),$L$10,$L$11) -> 0.096289825 | I28: Max | L28: =MAX(G10:G482) -> 0.36267377
B29: 39356 | C29: 5.735491 | D29: =(C29-C30)/C30 -> 20.004816 | E29: 0.23770141 | F29: 21 | G29: =_xlfn.NORM.INV(RAND(),$L$10,$L$11) -> 0.054421456 | I29: Current market price | L29: =L14 -> 191.73
B30: 31868 | C30: 0.273056 | D30: =(C30-C31)/C31 -> 1.0670088 | E30: 0.22868688 | F30: 22 | G30: =_xlfn.NORM.INV(RAND(),$L$10,$L$11) -> 0.063656571
B31: 35612 | C31: 0.132102 | D31: =(C31-C32)/C32 -> -0.60498412 | E31: 0.22806757 | F31: 23 | G31: =_xlfn.NORM.INV(RAND(),$L$10,$L$11) -> 0.10464044 | I31: Percentile | J31: Confidence | K31: VAR % | L31: Stock Price | M31: VAR ($)
B32: 32629 | C32: 0.334422 | D32: =(C32-C33)/C33 -> 1.6232468 | E32: 0.22436113 | F32: 24 | G32: =_xlfn.NORM.INV(RAND(),$L$10,$L$11) -> 0.042280987 | I32: 0.05 | J32: =1-I32 -> 0.95 | K32: =_xlfn.PERCENTILE.INC($G$10:$G$482,I32) -> -0.17761193 | L32: =$L$14*(1+K32) -> 157.67646 | M32: =-($L$14-L32) -> -34.053535
B33: 31533 | C33: 0.127484 | D33: =(C33-C34)/C34 -> -0.55703038 | E33: 0.22314969 | F33: 25 | G33: =_xlfn.NORM.INV(RAND(),$L$10,$L$11) -> 0.23845275 | I33: 0.01 | J33: =1-I33 -> 0.99 | K33: =_xlfn.PERCENTILE.INC($G$10:$G$482,I33) -> -0.23725477 | L33: =$L$14*(1+K33) -> 146.24114 | M33: =-($L$14-L33) -> -45.488857
B34: 36039 | C34: 0.287794 | D34: =(C34-C35)/C35 -> -0.61047226 | E34: 0.22244452 | F34: 26 | G34: =_xlfn.NORM.INV(RAND(),$L$10,$L$11) -> 0.19509354 | I34: 0.005 | J34: =1-I34 -> 0.995 | K34: =_xlfn.PERCENTILE.INC($G$10:$G$482,I34) -> -0.24591361 | L34: =$L$14*(1+K34) -> 144.58098 | M34: =-($L$14-L34) -> -47.149016
B35: 36465 | C35: 0.738828 | D35: =(C35-C36)/C36 -> -0.99413733 | E35: 0.22152837 | F35: 27 | G35: =_xlfn.NORM.INV(RAND(),$L$10,$L$11) -> 0.19198735 | I35: 0.1 | J35: =1-I35 -> 0.9 | K35: =_xlfn.PERCENTILE.INC($G$10:$G$482,I35) -> -0.13596369 | L35: =$L$14*(1+K35) -> 165.66168 | M35: =-($L$14-L35) -> -26.068318
B36: 44044 | C36: 126.02241 | D36: =(C36-C37)/C37 -> 33.438948 | E36: 0.21437956 | F36: 28 | G36: =_xlfn.NORM.INV(RAND(),$L$10,$L$11) -> -0.0031643335
B37: 39203 | C37: 3.659299 | D37: =(C37-C38)/C38 -> 10.379337 | E37: 0.21432817 | F37: 29 | G37: =_xlfn.NORM.INV(RAND(),$L$10,$L$11) -> 0.1555431
B38: 37196 | C38: 0.321574 | D38: =(C38-C39)/C39 -> -0.93877551 | E38: 0.21298787 | F38: 30 | G38: =_xlfn.NORM.INV(RAND(),$L$10,$L$11) -> 0.099868048
B39: 39539 | C39: 5.252375 | D39: =(C39-C40)/C40 -> 14.763478 | E39: 0.21219601 | F39: 31 | G39: =_xlfn.NORM.INV(RAND(),$L$10,$L$11) -> 0.004339108
B40: 36951 | C40: 0.333199 | D40: =(C40-C41)/C41 -> 0.27480268 | E40: 0.20931524 | F40: 32 | G40: =_xlfn.NORM.INV(RAND(),$L$10,$L$11) -> 0.039825038
B41: 35977 | C41: 0.261373 | D41: =(C41-C42)/C42 -> -0.37822812 | E41: 0.20697012 | F41: 33 | G41: =_xlfn.NORM.INV(RAND(),$L$10,$L$11) -> -0.13598161
B42: 36342 | C42: 0.420368 | D42: =(C42-C43)/C43 -> -0.54307627 | E42: 0.20243251 | F42: 34 | G42: =_xlfn.NORM.INV(RAND(),$L$10,$L$11) -> -0.045426374
B43: 36739 | C43: 0.919996 | D43: =(C43-C44)/C44 -> -0.75785781 | E43: 0.19926219 | F43: 35 | G43: =_xlfn.NORM.INV(RAND(),$L$10,$L$11) -> 0.050836194
B44: 39904 | C44: 3.799404 | D44: =(C44-C45)/C45 -> -0.92976786 | E44: 0.19701292 | F44: 36 | G44: =_xlfn.NORM.INV(RAND(),$L$10,$L$11) -> 0.12288858
B45: 43313 | C45: 54.097797 | D45: =(C45-C46)/C46 -> 205.8433 | E45: 0.19622696 | F45: 37 | G45: =_xlfn.NORM.INV(RAND(),$L$10,$L$11) -> -0.098699367
B46: 33178 | C46: 0.26154 | D46: =(C46-C47)/C47 -> -0.77472616 | E46: 0.19511972 | F46: 38 | G46: =_xlfn.NORM.INV(RAND(),$L$10,$L$11) -> 0.10659277
B47: 38353 | C47: 1.160987 | D47: =(C47-C48)/C48 -> 1.3860293 | E47: 0.19409815 | F47: 39 | G47: =_xlfn.NORM.INV(RAND(),$L$10,$L$11) -> 0.048253859
... B482: 36770 | C482: 0.388757 | D482: =(C482-C483)/C483 -> #DIV/0! | E482: -0.57743621 | F482: 474 | G482: =_xlfn.NORM.INV(RAND(),$L$10,$L$11) -> 0.11387412

Sheet Dupont Analysis
B26: Dupont Summary
B38: Dupont Analysis
B39: Return on Equity (ROE)
G40: ='Historical & Forecasted FS'!H6 -> 2019 | H40: ='Historical & Forecasted FS'!I6 -> 2020 | I40: ='Historical & Forecasted FS'!J6 -> 2021 | J40: ='Historical & Forecasted FS'!K6 -> 2022 | K40: ='Historical & Forecasted FS'!L6 -> 2023
B41: Net Profit | G41: ='Historical & Forecasted FS'!H47 -> 55256 | H41: ='Historical & Forecasted FS'!I47 -> 57411 | I41: ='Historical & Forecasted FS'!J47 -> 94680 | J41: ='Historical & Forecasted FS'!K47 -> 99803 | K41: ='Historical & Forecasted FS'!L47 -> 96995
B42: Average Shareholder Equity | G42: =('Historical & Forecasted FS'!H105+'Historical & Forecasted FS'!G105)/2 -> 98817.5 | H42: =('Historical & Forecasted FS'!I105+'Historical & Forecasted FS'!H105)/2 -> 77913.5 | I42: =('Historical & Forecasted FS'!J105+'Historical & Forecasted FS'!I105)/2 -> 64214.5 | J42: =('Historical & Forecasted FS'!K105+'Historical & Forecasted FS'!J105)/2 -> 56881 | K42: =('Historical & Forecasted FS'!L105+'Historical & Forecasted FS'!K105)/2 -> 56409
B43: Return on Equity (ROE) | G43: =G41/G42 -> 0.55917221 | H43: =H41/H42 -> 0.73685562 | I43: =I41/I42 -> 1.4744333 | J43: =J41/J42 -> 1.7545929 | K43: =K41/K42 -> 1.7194951
B45: ROE - Dupont Equation
G46: =G40 -> 2019 | H46: =H40 -> 2020 | I46: =I40 -> 2021 | J46: =J40 -> 2022 | K46: =K40 -> 2023
B47: Net Profit | G47: ='Historical & Forecasted FS'!H47 -> 55256 | H47: ='Historical & Forecasted FS'!I47 -> 57411 | I47: ='Historical & Forecasted FS'!J47 -> 94680 | J47: ='Historical & Forecasted FS'!K47 -> 99803 | K47: ='Historical & Forecasted FS'!L47 -> 96995
B48: Revenue | G48: ='Historical & Forecasted FS'!H8 -> 260174 | H48: ='Historical & Forecasted FS'!I8 -> 274515 | I48: ='Historical & Forecasted FS'!J8 -> 365817 | J48: ='Historical & Forecasted FS'!K8 -> 394328 | K48: ='Historical & Forecasted FS'!L8 -> 383285
B49: Net Profit Margin (A) | G49: =G47/G48 -> 0.21238095 | H49: =H47/H48 -> 0.20913611 | I49: =I47/I48 -> 0.25881793 | J49: =J47/J48 -> 0.25309641 | K49: =K47/K48 -> 0.25306234
B51: Revenue | G51: ='Historical & Forecasted FS'!H8 -> 260174 | H51: ='Historical & Forecasted FS'!I8 -> 274515 | I51: ='Historical & Forecasted FS'!J8 -> 365817 | J51: ='Historical & Forecasted FS'!K8 -> 394328 | K51: ='Historical & Forecasted FS'!L8 -> 383285
B52: Average Total Asset | G52: =('Historical & Forecasted FS'!H82+'Historical & Forecasted FS'!G82)/2 -> 352120.5 | H52: =('Historical & Forecasted FS'!I82+'Historical & Forecasted FS'!H82)/2 -> 331202 | I52: =('Historical & Forecasted FS'!J82+'Historical & Forecasted FS'!I82)/2 -> 337445 | J52: =('Historical & Forecasted FS'!K82+'Historical & Forecasted FS'!J82)/2 -> 351878.5 | K52: =('Historical & Forecasted FS'!L82+'Historical & Forecasted FS'!K82)/2 -> 352669
B53: Asset Turnover Ratio (B) | G53: =G51/G52 -> 0.73887774 | H53: =H51/H52 -> 0.82884463 | I53: =I51/I52 -> 1.0840789 | J53: =J51/J52 -> 1.1206368 | K53: =K51/K52 -> 1.0868123
B55: Average Total Asset | G55: =G52 -> 352120.5 | H55: =H52 -> 331202 | I55: =I52 -> 337445 | J55: =J52 -> 351878.5 | K55: =K52 -> 352669
B56: Average Shareholder's Equity | G56: =G42 -> 98817.5 | H56: =H42 -> 77913.5 | I56: =I42 -> 64214.5 | J56: =J42 -> 56881 | K56: =K42 -> 56409
B57: Equity Multiplier (C) | G57: =G55/G56 -> 3.5633415 | H57: =H55/H56 -> 4.2508936 | I57: =I55/I56 -> 5.2549658 | J57: =J55/J56 -> 6.1862221 | K57: =K55/K56 -> 6.2519988
B59: Return on Equity (A*B*C) | G59: =G49*G53*G57 -> 0.55917221 | H59: =H49*H53*H57 -> 0.73685562 | I59: =I49*I53*I57 -> 1.4744333 | J59: =J49*J53*J57 -> 1.7545929 | K59: =K49*K53*K57 -> 1.7194951
B61: Return on Asset (ROA)
G62: =G46 -> 2019 | H62: =H46 -> 2020 | I62: =I46 -> 2021 | J62: =J46 -> 2022 | K62: =K46 -> 2023
B63: Net Profit | G63: =G47 -> 55256 | H63: =H47 -> 57411 | I63: =I47 -> 94680 | J63: =J47 -> 99803 | K63: =K47 -> 96995
B64: Average Total Asset | G64: =G55 -> 352120.5 | H64: =H55 -> 331202 | I64: =I55 -> 337445 | J64: =J55 -> 351878.5 | K64: =K55 -> 352669
B65: Return on Asset (ROA) | G65: =G63/G64 -> 0.15692355 | H65: =H63/H64 -> 0.17334134 | I65: =I63/I64 -> 0.28057906 | J65: =J63/J64 -> 0.28362915 | K65: =K63/K64 -> 0.27503126
B67: ROA - Dupont Equation
G68: =G62 -> 2019 | H68: =H62 -> 2020 | I68: =I62 -> 2021 | J68: =J62 -> 2022 | K68: =K62 -> 2023
B69: Net Profit | G69: =G63 -> 55256 | H69: =H63 -> 57411 | I69: =I63 -> 94680 | J69: =J63 -> 99803 | K69: =K63 -> 96995
B70: Revenue | G70: =G51 -> 260174 | H70: =H51 -> 274515 | I70: =I51 -> 365817 | J70: =J51 -> 394328 | K70: =K51 -> 383285
B71: Net Profit Margin (A) | G71: =G69/G70 -> 0.21238095 | H71: =H69/H70 -> 0.20913611 | I71: =I69/I70 -> 0.25881793 | J71: =J69/J70 -> 0.25309641 | K71: =K69/K70 -> 0.25306234
B73: Revenue | G73: =G70 -> 260174 | H73: =H70 -> 274515 | I73: =I70 -> 365817 | J73: =J70 -> 394328 | K73: =K70 -> 383285
B74: Average Total Asset | G74: =G64 -> 352120.5 | H74: =H64 -> 331202 | I74: =I64 -> 337445 | J74: =J64 -> 351878.5 | K74: =K64 -> 352669
B75: Asset Turnover Ratio (B) | G75: =G73/G74 -> 0.73887774 | H75: =H73/H74 -> 0.82884463 | I75: =I73/I74 -> 1.0840789 | J75: =J73/J74 -> 1.1206368 | K75: =K73/K74 -> 1.0868123
B77: Return on Asset (A*B) | G77: =G75*G71 -> 0.15692355 | H77: =H75*H71 -> 0.17334134 | I77: =I75*I71 -> 0.28057906 | J77: =J75*J71 -> 0.28362915 | K77: =K75*K71 -> 0.27503126

Sheet Data>

Sheet Data Sheet
A4: Apple Inc.
A5: Apple Inc. (NasdaqGS:AAPL) > Financials > Income Statement
A7: In Millions of the reported currency, except per share items. | G7: Template: | H7: Standard | J7: Restatement: | K7: Latest Filings
G8: Period Type: | H8: Annual | J8: Order: | K8: Latest on Right
G9: Currency: | H9: Reported Currency | J9: Conversion: | K9: Historical
G10: Units: | H10: S&P Capital IQ (Default) | J10: Decimals: | K10: Capital IQ (Default)
G11: Source: | H11: Capital IQ & Proprietary Data
A14: Income Statement
A15: For the Fiscal Period Ending | B15: 12 months Sep-27-2014 | C15: 12 months Sep-26-2015 | D15: 12 months Sep-24-2016 | E15: 12 months Sep-30-2017 | F15: 12 months Sep-29-2018 | G15: 12 months Sep-28-2019 | H15: 12 months Sep-26-2020 | I15: 12 months Sep-25-2021 | J15: 12 months Sep-24-2022 | K15: 12 months Sep-30-2023 | L15: LTM 12 months Dec-30-2023
A16: Currency | B16: USD | C16: USD | D16: USD | E16: USD | F16: USD | G16: USD | H16: USD | I16: USD | J16: USD | K16: USD | L16: USD
A18: Revenue | B18: 182795 | C18: 233715 | D18: 215639 | E18: 229234 | F18: 265595 | G18: 260174 | H18: 274515 | I18: 365817 | J18: 394328 | K18: 383285 | L18: 385706
A19: Other Revenue | B19: - | C19: - | D19: - | E19: - | F19: - | G19: - | H19: - | I19: - | J19: - | K19: - | L19: -
A20: Total Revenue | B20: 182795 | C20: 233715 | D20: 215639 | E20: 229234 | F20: 265595 | G20: 260174 | H20: 274515 | I20: 365817 | J20: 394328 | K20: 383285 | L20: 385706
A22: Cost Of Goods Sold | B22: 112258 | C22: 140089 | D22: 131376 | E22: 141048 | F22: 163756 | G22: 161782 | H22: 169559 | I22: 212981 | J22: 223546 | K22: 214137 | L22: 212035
A23: Gross Profit | B23: 70537 | C23: 93626 | D23: 84263 | E23: 88186 | F23: 101839 | G23: 98392 | H23: 104956 | I23: 152836 | J23: 170782 | K23: 169148 | L23: 173671
A25: Selling General & Admin Exp. | B25: 11993 | C25: 14329 | D25: 14194 | E25: 15261 | F25: 16705 | G25: 18245 | H25: 19916 | I25: 21973 | J25: 25094 | K25: 24932 | L25: 25111
A26: R & D Exp. | B26: 6041 | C26: 8067 | D26: 10045 | E26: 11581 | F26: 14236 | G26: 16217 | H26: 18752 | I26: 21914 | J26: 26251 | K26: 29915 | L26: 29902
A27: Depreciation & Amort. | B27: - | C27: - | D27: - | E27: - | F27: - | G27: - | H27: - | I27: - | J27: - | K27: - | L27: -
A28: Other Operating Expense/(Income) | B28: - | C28: - | D28: - | E28: - | F28: - | G28: - | H28: - | I28: - | J28: - | K28: - | L28: -
A30: Other Operating Exp., Total | B30: 18034 | C30: 22396 | D30: 24239 | E30: 26842 | F30: 30941 | G30: 34462 | H30: 38668 | I30: 43887 | J30: 51345 | K30: 54847 | L30: 55013
A32: Operating Income | B32: 52503 | C32: 71230 | D32: 60024 | E32: 61344 | F32: 70898 | G32: 63930 | H32: 66288 | I32: 108949 | J32: 119437 | K32: 114301 | L32: 118658
A34: Interest Expense | B34: -384 | C34: -733 | D34: -1456 | E34: -2323 | F34: -3240 | G34: -3576 | H34: -2873 | I34: -2645 | J34: -2931 | K34: -3933 | L34: -3933
A35: Interest and Invest. Income | B35: 1795 | C35: 2921 | D35: 3999 | E35: 5201 | F35: 5686 | G35: 4961 | H35: 3763 | I35: 2843 | J35: 2825 | K35: 3750 | L35: 3750
A36: Net Interest Exp. | B36: 1411 | C36: 2188 | D36: 2543 | E36: 2878 | F36: 2446 | G36: 1385 | H36: 890 | I36: 198 | J36: -106 | K36: -183 | L36: -183
A38: Other Non-Operating Inc. (Exp.) | B38: -431 | C38: -903 | D38: -1195 | E38: -133 | F38: -441 | G38: 422 | H38: -87 | I38: 60 | J38: -228 | K38: -382 | L38: -39
A39: EBT Excl. Unusual Items | B39: 53483 | C39: 72515 | D39: 61372 | E39: 64089 | F39: 72903 | G39: 65737 | H39: 67091 | I39: 109207 | J39: 119103 | K39: 113736 | L39: 118436
A41: Impairment of Goodwill | B41: - | C41: - | D41: - | E41: - | F41: - | G41: - | H41: - | I41: - | J41: - | K41: - | L41: -
A42: Other Unusual Items | B42: - | C42: - | D42: - | E42: - | F42: - | G42: - | H42: - | I42: - | J42: - | K42: - | L42: -
A43: EBT Incl. Unusual Items | B43: 53483 | C43: 72515 | D43: 61372 | E43: 64089 | F43: 72903 | G43: 65737 | H43: 67091 | I43: 109207 | J43: 119103 | K43: 113736 | L43: 118436
A45: Income Tax Expense | B45: 13973 | C45: 19121 | D45: 15685 | E45: 15738 | F45: 13372 | G45: 10481 | H45: 9680 | I45: 14527 | J45: 19300 | K45: 16741 | L45: 17523
A46: Earnings from Cont. Ops. | B46: 39510 | C46: 53394 | D46: 45687 | E46: 48351 | F46: 59531 | G46: 55256 | H46: 57411 | I46: 94680 | J46: 99803 | K46: 96995 | L46: 100913
A48: Earnings of Discontinued Ops. | B48: - | C48: - | D48: - | E48: - | F48: - | G48: - | H48: - | I48: - | J48: - | K48: - | L48: -
A49: Extraord. Item & Account. Change | B49: - | C49: - | D49: - | E49: - | F49: - | G49: - | H49: - | I49: - | J49: - | K49: - | L49: -
A50: Net Income to Company | B50: 39510 | C50: 53394 | D50: 45687 | E50: 48351 | F50: 59531 | G50: 55256 | H50: 57411 | I50: 94680 | J50: 99803 | K50: 96995 | L50: 100913
A52: Minority Int. in Earnings | B52: - | C52: - | D52: - | E52: - | F52: - | G52: - | H52: - | I52: - | J52: - | K52: - | L52: -
A53: Net Income | B53: 39510 | C53: 53394 | D53: 45687 | E53: 48351 | F53: 59531 | G53: 55256 | H53: 57411 | I53: 94680 | J53: 99803 | K53: 96995 | L53: 100913
A55: Pref. Dividends and Other Adj. | B55: - | C55: - | D55: - | E55: - | F55: - | G55: - | H55: - | I55: - | J55: - | K55: - | L55: -
A57: NI to Common Incl Extra Items | B57: 39510 | C57: 53394 | D57: 45687 | E57: 48351 | F57: 59531 | G57: 55256 | H57: 57411 | I57: 94680 | J57: 99803 | K57: 96995 | L57: 100913
A58: NI to Common Excl. Extra Items | B58: 39510 | C58: 53394 | D58: 45687 | E58: 48351 | F58: 59531 | G58: 55256 | H58: 57411 | I58: 94680 | J58: 99803 | K58: 96995 | L58: 100913
A60: Per Share Items
A61: Basic EPS | B61: 1.62 | C61: 2.32 | D61: 2.09 | E61: 2.32 | F61: 3 | G61: 2.99 | H61: 3.31 | I61: 5.67 | J61: 6.15 | K61: 6.16 | L61: 6.45
A62: Basic EPS Excl. Extra Items | B62: 1.623101 | C62: 2.320097 | D62: 2.087758 | E62: 2.316885 | F62: 3.003353 | G62: 2.991445 | H62: 3.308587 | I62: 5.669029 | J62: 6.154614 | K62: 6.160669 | L62: 6.448736
A63: Weighted Avg. Basic Shares Out. | B63: 24342.288 | C63: 23013.684 | D63: 21883.28 | E63: 20868.968 | F63: 19821.51 | G63: 18471.336 | H63: 17352.119 | I63: 16701.272 | J63: 16215.963 | K63: 15744.231 | L63: 15648.491
A65: Diluted EPS | B65: 1.61 | C65: 2.31 | D65: 2.08 | E65: 2.3 | F65: 2.98 | G65: 2.97 | H65: 3.28 | I65: 5.61 | J65: 6.11 | K65: 6.13 | L65: 6.42
A66: Diluted EPS Excl. Extra Items | B66: 1.6125 | C66: 2.305 | D66: 2.0775 | E66: 2.3025 | F66: 2.98 | G66: 2.97 | H66: 3.28 | I66: 5.61 | J66: 6.11 | K66: 6.13 | L66: 6.418925
A67: Weighted Avg. Diluted Shares Out. | B67: 24490.652 | C67: 23172.276 | D67: 22001.124 | E67: 21006.768 | F67: 20000.435 | G67: 18595.651 | H67: 17528.214 | I67: 16864.919 | J67: 16325.819 | K67: 15812.547 | L67: 15717.778
A69: Normalized Basic EPS | B69: 1.37 | C69: 1.97 | D69: 1.75 | E69: 1.92 | F69: 2.3 | G69: 2.22 | H69: 2.42 | I69: 4.09 | J69: 4.59 | K69: 4.51 | L69: 4.73
A70: Normalized Diluted EPS | B70: 1.364883 | C70: 1.955866 | D70: 1.743433 | E70: 1.906796 | F70: 2.278169 | G70: 2.209421 | H70: 2.39225 | I70: 4.047121 | J70: 4.55961 | K70: 4.49548 | L70: 4.709476
A72: Dividends per Share | B72: 0.46 | C72: 0.5 | D72: 0.55 | E72: 0.6 | F72: 0.68 | G72: 0.75 | H72: 0.8 | I72: 0.85 | J72: 0.9 | K72: 0.94 | L72: 0.95
A73: Payout Ratio % | B73: 0.281599 | C73: 0.216522 | D73: 0.265939 | E73: 0.264089 | F73: 0.230333 | G73: 0.255519 | H73: 0.245266 | I73: 0.152798 | J73: 0.148702 | K73: 0.154904 | L73: 0.149455
A75: Shares per Depository Receipt | B75: 0.1 | C75: 0.1 | D75: 0.1 | E75: 0.1 | F75: 0.1 | G75: 0.1 | H75: 0.1 | I75: 0.1 | J75: 0.1 | K75: 0.1 | L75: 0.1
A77: Supplemental Items
A78: EBITDA | B78: 60449 | C78: 82487 | D78: 70529 | E78: 71501 | F78: 81801 | G78: 76477 | H78: 77344 | I78: 120233 | J78: 130541 | K78: 125820 | L78: 130109
A79: EBITA | B79: 53603 | C79: 72530 | D79: 60024 | E79: 61344 | F79: 70898 | G79: 63930 | H79: 66288 | I79: 108949 | J79: 119437 | K79: 114301 | L79: 118658
A80: EBIT | B80: 52503 | C80: 71230 | D80: 60024 | E80: 61344 | F80: 70898 | G80: 63930 | H80: 66288 | I80: 108949 | J80: 119437 | K80: 114301 | L80: 118658
A81: EBITDAR | B81: 61166 | C81: 83281 | D81: 71468 | E81: 72601 | F81: 83001 | G81: 77777 | H81: 88144 | I81: 134833 | J81: 147341 | K81: 141720 | L81: NA
A82: As Reported Total Revenue* | B82: NA | C82: NA | D82: NA | E82: 229234 | F82: 265595 | G82: 260174 | H82: 274515 | I82: 365817 | J82: 394328 | K82: 383285 | L82: 385706
A83: Effective Tax Rate % | B83: 0.26126 | C83: 0.263683 | D83: 0.255572 | E83: 0.245564 | F83: 0.183421 | G83: 0.159438 | H83: 0.144281 | I83: 0.133022 | J83: 0.162044 | K83: 0.147191 | L83: 0.147953
A84: Current Domestic Taxes | B84: 9479 | C84: 12995 | D84: 8642 | E84: 8101 | F84: 41976 | G84: 6859 | H84: 6761 | I84: 9877 | J84: 9409 | K84: 11015 | L84: 11015
A85: Current Foreign Taxes | B85: 2147 | C85: 4744 | D85: 2105 | E85: 1671 | F85: 3986 | G85: 3962 | H85: 3134 | I85: 9424 | J85: 8996 | K85: 8750 | L85: 8750
A86: Total Current Taxes | B86: 11626 | C86: 17739 | D86: 10747 | E86: 9772 | F86: 45962 | G86: 10821 | H86: 9895 | I86: 19301 | J86: 18405 | K86: 19765 | L86: 19765
A87: Deferred Domestic Taxes | B87: 3005 | C87: 3188 | D87: 4905 | E87: 5982 | F87: -33771 | G87: -3006 | H87: -3598 | I87: -7514 | J87: -2181 | K87: -3693 | L87: -3693
A88: Deferred Foreign Taxes | B88: -658 | C88: -1806 | D88: 33 | E88: -16 | F88: 1181 | G88: 2666 | H88: 3383 | I88: 2740 | J88: 3076 | K88: 669 | L88: 669
A89: Total Deferred Taxes | B89: 2347 | C89: 1382 | D89: 4938 | E89: 5966 | F89: -32590 | G89: -340 | H89: -215 | I89: -4774 | J89: 895 | K89: -3024 | L89: -3024
A91: Normalized Net Income | B91: 33426.875 | C91: 45321.875 | D91: 38357.5 | E91: 40055.625 | F91: 45564.375 | G91: 41085.625 | H91: 41931.875 | I91: 68254.375 | J91: 74439.375 | K91: 71085 | L91: 74022.5
A92: Interest on Long Term Debt | B92: 381 | C92: 722 | D92: 1400 | E92: 2200 | F92: 3000 | G92: 3200 | H92: 2800 | I92: 2600 | J92: 2800 | K92: 3700 | L92: NA
A93: Filing Date | B93: 42669 | C93: 43042 | D93: 43409 | E93: 43769 | F93: 44134 | G93: 44498 | H93: 44862 | I93: 45233 | J93: 45233 | K93: 45233 | L93: 45324
A94: Restatement Type | B94: NC | C94: NC | D94: NC | E94: NC | F94: NC | G94: NC | H94: NC | I94: NC | J94: NC | K94: O | L94: O
A95: Calculation Type | B95: REP | C95: REP | D95: REP | E95: REP | F95: REP | G95: REP | H95: REP | I95: REP | J95: REP | K95: REP | L95: LTM
A97: Supplemental Operating Expense Items
A98: R&D Exp. | B98: 6041 | C98: 8067 | D98: 10045 | E98: 11581 | F98: 14236 | G98: 16217 | H98: 18752 | I98: 21914 | J98: 26251 | K98: 29915 | L98: 29902
A99: Net Rental Exp. | B99: 717 | C99: 794 | D99: 939 | E99: 1100 | F99: 1200 | G99: 1300 | H99: 10800 | I99: 14600 | J99: 16800 | K99: 15900 | L99: NA
A100: Imputed Oper. Lease Interest Exp. | B100: 84.301992 | C100: 93.456976 | D100: 144.50834 | E100: 201.6872 | F100: 270.2688 | G100: 334.2456 | H100: 2155.4208 | I100: 2387.392 | J100: 2928.7104 | K100: 3902.1144 | L100: -
A101: Imputed Oper. Lease Depreciation | B101: 632.69801 | C101: 700.54302 | D101: 794.49166 | E101: 898.3128 | F101: 929.7312 | G101: 965.7544 | H101: 8644.5792 | I101: 12212.608 | J101: 13871.29 | K101: 11997.886 | L101: -
A103: Stock-Based Comp., COGS | B103: 450 | C103: 575 | D103: 769 | E103: - | F103: -
A104: Stock-Based Comp., R&D Exp. | B104: 1216 | C104: 1536 | D104: 1889 | E104: - | F104: -
A105: Stock-Based Comp., SG&A Exp. | B105: 1197 | C105: 1475 | D105: 1552 | E105: - | F105: -
A106: Stock-Based Comp., Unallocated | B106: - | C106: - | D106: - | E106: 4840 | F106: 5340 | G106: 6068 | H106: 6829 | I106: 7906 | J106: 9038 | K106: 10833 | L106: 10925
A107: Stock-Based Comp., Total | B107: 2863 | C107: 3586 | D107: 4210 | E107: 4840 | F107: 5340 | G107: 6068 | H107: 6829 | I107: 7906 | J107: 9038 | K107: 10833 | L107: 10925
A109: * Occasionally, certain items classified as Revenue by the company will be re-classified as other income if it is deemed to be non-recurring and unrelated to the core business of the firm. This field shows Total Revenue exactly as reported by the firm on its consolidated statement of income.
A110: Note: For multiple class companies, per share items are primary class equivalent, and for foreign companies listed as primary ADRs, per share items are ADR-equivalent.
A117: Apple Inc. (NasdaqGS:AAPL) > Financials > Balance Sheet
A119: In Millions of the reported currency, except per share items. | G119: Template: | H119: Standard | J119: Restatement: | K119: Latest Filings
G120: Period Type: | H120: Annual | J120: Order: | K120: Latest on Right
G121: Currency: | H121: Reported Currency | J121: Conversion: | K121: Historical
G122: Units: | H122: S&P Capital IQ (Default) | J122: Decimals: | K122: Capital IQ (Default)
G123: Source: | H123: Capital IQ & Proprietary Data
A126: Balance Sheet
A127: Balance Sheet as of: | B127: 41909 | C127: Restated Sep-26-2015 | D127: 42637 | E127: 43008 | F127: Reclassified Sep-29-2018 | G127: 43736 | H127: 44100 | I127: 44464 | J127: 44828 | K127: 45199 | L127: 45290
A128: Currency | B128: USD | C128: USD | D128: USD | E128: USD | F128: USD | G128: USD | H128: USD | I128: USD | J128: USD | K128: USD | L128: USD
A129: ASSETS
A130: Cash And Equivalents | B130: 13844 | C130: 21120 | D130: 20484 | E130: 20289 | F130: 25913 | G130: 48844 | H130: 38016 | I130: 34940 | J130: 23646 | K130: 29965 | L130: 40760
A131: Short Term Investments | B131: 11233 | C131: 20481 | D131: 46671 | E131: 53892 | F131: 40388 | G131: 51713 | H131: 52927 | I131: 27699 | J131: 24658 | K131: 31590 | L131: 32340
A132: Trading Asset Securities | B132: 81 | C132: 394 | D132: - | E132: - | F132: - | G132: - | H132: - | I132: - | J132: - | K132: - | L132: -
A133: Total Cash & ST Investments | B133: 25158 | C133: 41995 | D133: 67155 | E133: 74181 | F133: 66301 | G133: 100557 | H133: 90943 | I133: 62639 | J133: 48304 | K133: 61555 | L133: 73100
A135: Accounts Receivable | B135: 17460 | C135: 16849 | D135: 15754 | E135: 17874 | F135: 23186 | G135: 22926 | H135: 16120 | I135: 26278 | J135: 28184 | K135: 29508 | L135: 23194
A136: Other Receivables | B136: 9759 | C136: 13494 | D136: 13545 | E136: 17799 | F136: 25809 | G136: 22878 | H136: 21325 | I136: 25228 | J136: 32748 | K136: 31477 | L136: 26908
A137: Total Receivables | B137: 27219 | C137: 30343 | D137: 29299 | E137: 35673 | F137: 48995 | G137: 45804 | H137: 37445 | I137: 51506 | J137: 60932 | K137: 60985 | L137: 50102
A139: Inventory | B139: 2111 | C139: 2349 | D139: 2132 | E139: 4855 | F139: 3956 | G139: 4106 | H139: 4061 | I139: 6580 | J139: 4946 | K139: 6331 | L139: 6511
A140: Restricted Cash | B140: 4318 | C140: - | D140: - | E140: - | F140: - | G140: 23 | H140: - | I140: - | J140: - | K140: - | L140: -
...
